FPGA/FPGA 02/b/simple_gate.m.vhd
---------------------------------------
-- lecture 01 simple gate
-- just forwarding the signal
----------------------------------------

library ieee;
use ieee.std_logic_1164.all;
use ieee.numeric_std.all;
----------------------------------------
entity lecture01 is
port(	
	    i_sl_x : in  std_logic;
	    i_sl_dir : in std_logic;
	    i_sl_en : in std_logic;
	    o_slv_shift : out std_logic_vector(7 downto 0)
);
end lecture01;  

----------------------------------------

architecture behaviour of lecture01 is
	signal shift_reg : std_logic_vector(7 downto 0) := "00000000";
begin

    process(i_sl_x)
    begin
        -- compare to truth table
	if rising_edge(i_sl_x) then
		if (i_sl_en = '1') then
		    if (i_sl_dir = '1') then
			shift_reg <= std_logic_vector(unsigned(shift_reg)-1);
		    else 
			shift_reg <= std_logic_vector(unsigned(shift_reg)+1);
		    end if;
		end if;
	end if;
	o_slv_shift <= shift_reg;
    end process;
end behaviour;

------------------------------------------

FPGA/FPGA 02/b/simple_gate.tb.vhd
library ieee;
use ieee.std_logic_1164.all;

ENTITY lecture01_tb IS
END lecture01_tb;

ARCHITECTURE tb OF lecture01_tb IS 
    COMPONENT lecture01 is
        port(	
            i_sl_x      : in  std_logic;
	    i_sl_dir    : in  std_logic;
	    i_sl_en     : in  std_logic;
	    o_slv_shift : out std_logic_vector(7 downto 0)
        );
    end COMPONENT;

    -- "local" signals

    -- signals for UUT
    -- input 
    signal x    : std_logic := '0';
    signal dir    : std_logic := '0';
    signal en    : std_logic := '0';


    -- ouput
    signal o_slv_shift : std_logic_vector(7 downto 0) := (others => '0');

BEGIN 
    -- Instance of unit under test.
    uut: lecture01 
    PORT MAP (
        i_sl_x  => x,
	i_sl_dir => dir,
	i_sl_en => en,
	o_slv_shift => o_slv_shift
    );

-------------------------------------------------------------------------------
    -- test bench definition.
    tb_process :process
    begin
        x <= '0';
        wait for 5 ns;
        x <= '1';
        wait for 5 ns;
    end process;

    tb_process_dir :process
    begin
        dir <= '0';
        wait for 60 ns;
        dir <= '1';
        wait for 60 ns;
    end process;

    tb_process_en :process
    begin
        en <= '0';
        wait for 10 ns;
        en <= '1';
        wait for 50 ns;
    end process;


END;

FPGA/FPGA 02/b/simple_gate.vcd
$date
  Thu Jan  7 18:16:01 2021
$end
$version
  GHDL v0
$end
$timescale
  1 fs
$end
$scope module standard $end
$upscope $end
$scope module textio $end
$upscope $end
$scope module std_logic_1164 $end
$upscope $end
$scope module numeric_std $end
$upscope $end
$scope module lecture01_tb $end
$var reg 1 ! x $end
$var reg 1 " dir $end
$var reg 1 # en $end
$var reg 8 $ o_slv_shift[7:0] $end
$scope module uut $end
$var reg 1 % i_sl_x $end
$var reg 1 & i_sl_dir $end
$var reg 1 ' i_sl_en $end
$var reg 8 ( o_slv_shift[7:0] $end
$var reg 8 ) shift_reg[7:0] $end
$upscope $end
$upscope $end
$enddefinitions $end
#0
0!
0"
0#
b00000000 $
0%
0&
0'
b00000000 (
b00000000 )
#5000000
1!
1%
#10000000
0!
1#
0%
1'
#15000000
1!
1%
b00000001 )
#20000000
0!
b00000001 $
0%
b00000001 (
#25000000
1!
1%
b00000010 )
#30000000
0!
b00000010 $
0%
b00000010 (
#35000000
1!
1%
b00000011 )
#40000000
0!
b00000011 $
0%
b00000011 (
#45000000
1!
1%
b00000100 )
#50000000
0!
b00000100 $
0%
b00000100 (
#55000000
1!
1%
b00000101 )
#60000000
0!
1"
0#
b00000101 $
0%
1&
0'
b00000101 (
#65000000
1!
1%
#70000000
0!
1#
0%
1'
#75000000
1!
1%
b00000100 )
#80000000
0!
b00000100 $
0%
b00000100 (
#85000000
1!
1%
b00000011 )
#90000000
0!
b00000011 $
0%
b00000011 (
#95000000
1!
1%
b00000010 )
#100000000
0!
b00000010 $
0%
b00000010 (
#105000000
1!
1%
b00000001 )
#110000000
0!
b00000001 $
0%
b00000001 (
#115000000
1!
1%
b00000000 )
#120000000
0!
0"
0#
b00000000 $
0%
0&
0'
b00000000 (
#125000000
1!
1%
#130000000
0!
1#
0%
1'
#135000000
1!
1%
b00000001 )
#140000000
0!
b00000001 $
0%
b00000001 (
#145000000
1!
1%
b00000010 )
#150000000
0!
b00000010 $
0%
b00000010 (
#155000000
1!
1%
b00000011 )
#160000000
0!
b00000011 $
0%
b00000011 (
#165000000
1!
1%
b00000100 )
#170000000
0!
b00000100 $
0%
b00000100 (
#175000000
1!
1%
b00000101 )
#180000000
0!
1"
0#
b00000101 $
0%
1&
0'
b00000101 (
#185000000
1!
1%
#190000000
0!
1#
0%
1'
#195000000
1!
1%
b00000100 )
#200000000
0!
b00000100 $
0%
b00000100 (
