FPGA/Solutions 05/lecture05a_expert/bcd.m.vhd
---------------------------------------
-- lecture 02 shift register
-- just forwarding the signal
----------------------------------------

library ieee;
use ieee.std_logic_1164.all;
use ieee.numeric_std.all;

use ieee.MATH_REAL.all;

----------------------------------------

entity bcd is
--    GENERIC (
--    );
    port(   
        i_slv_binary   :   in std_logic_vector( 7     downto 0);
        o_slv_decimal  :  out std_logic_vector( 3*4-1 downto 0) 
    );
end bcd;  

----------------------------------------

architecture behavior of bcd is


begin
    process(i_slv_binary)
        -- temporarly variables
        variable huns : std_logic_vector ( 3 downto 0) := (others => '0');
        variable tens : std_logic_vector ( 3 downto 0) := (others => '0');
        variable ones : std_logic_vector ( 3 downto 0) := (others => '0');
    begin
        -- reset all outputs
        huns := (others => '0');
        tens := (others => '0');
        ones := (others => '0');

        for i in 7 downto 0 loop
            
            if ( unsigned(huns) >= 5 ) then
                huns := std_logic_vector( unsigned(huns) + 3);
            end if;
            if ( unsigned(tens) >= 5 ) then
                tens := std_logic_vector( unsigned(tens) + 3);
            end if;
            if ( unsigned(ones) >= 5 ) then
                ones := std_logic_vector( unsigned(ones) + 3);
            end if;

            huns := huns(2 downto 0) & tens(3);
            tens := tens(2 downto 0) & ones(3);
            ones := ones(2 downto 0) & i_slv_binary(i);

        end loop;

        o_slv_decimal <=  huns & tens & ones;

    end process;
end behavior;

------------------------------------------

FPGA/Solutions 05/lecture05a_expert/bcd.tb.vhd
library ieee;
use ieee.std_logic_1164.all;
use ieee.numeric_std.all;

use ieee.MATH_REAL.all;

ENTITY bcd_tb IS
END bcd_tb;

ARCHITECTURE tb OF bcd_tb IS 

    COMPONENT bcd is
    --    GENERIC (
    --    );
        port(   
            i_slv_binary   :   in std_logic_vector( 7     downto 0);
            o_slv_decimal  :  out std_logic_vector( 3*4-1 downto 0) 
        );
    end component bcd;  

    -- "local" signals

    -- signals for UUT
    -- input 
    signal binary   : std_logic_vector( 7 downto 0) := (others => '0') ; 

    -- ouput
    signal decimal  : std_logic_vector( 3*4-1 downto 0);

    signal ones : std_logic_vector(3 downto 0);
    signal tens : std_logic_vector(3 downto 0);
    signal hundrets : std_logic_vector(3 downto 0);

BEGIN 
    -- Instance of unit under test.
    bcd1: bcd 
        port map(   
            i_slv_binary  => binary,
            o_slv_decimal => decimal
        );


    ones     <= decimal(3 downto 0);
    tens     <= decimal(7 downto 4);
    hundrets <= decimal(11 downto 8);

-------------------------------------------------------------------------------
    -- test bench definition.
    tb_test :process
    begin
        for bin in 0 to 255 loop
            binary <= std_logic_vector(to_unsigned(bin, 8));
            wait for 2 ns;
        end loop;

    end process;

--    tb_test2 : process
--    begin
--        for i in 0 to 8 loop
--            report integer'image(i);
--        end loop;
--    end process;

END;

FPGA/Solutions 05/lecture05a_expert/bcd.vcd
$date
  Wed Nov 25 16:51:29 2020
$end
$version
  GHDL v0
$end
$timescale
  1 fs
$end
$scope module standard $end
$upscope $end
$scope module textio $end
$upscope $end
$scope module std_logic_1164 $end
$upscope $end
$scope module numeric_std $end
$upscope $end
$scope module math_real $end
$upscope $end
$scope module bcd_tb $end
$var reg 8 ! binary[7:0] $end
$var reg 12 " decimal[11:0] $end
$var reg 4 # ones[3:0] $end
$var reg 4 $ tens[3:0] $end
$var reg 4 % hundrets[3:0] $end
$scope module bcd1 $end
$var reg 8 & i_slv_binary[7:0] $end
$var reg 12 ' o_slv_decimal[11:0] $end
$upscope $end
$upscope $end
$enddefinitions $end
#0
b00000000 !
b000000000000 "
b0000 #
b0000 $
b0000 %
b00000000 &
b000000000000 '
#2000000
b00000001 !
b000000000001 "
b0001 #
b00000001 &
b000000000001 '
#4000000
b00000010 !
b000000000010 "
b0010 #
b00000010 &
b000000000010 '
#6000000
b00000011 !
b000000000011 "
b0011 #
b00000011 &
b000000000011 '
#8000000
b00000100 !
b000000000100 "
b0100 #
b00000100 &
b000000000100 '
#10000000
b00000101 !
b000000000101 "
b0101 #
b00000101 &
b000000000101 '
#12000000
b00000110 !
b000000000110 "
b0110 #
b00000110 &
b000000000110 '
#14000000
b00000111 !
b000000000111 "
b0111 #
b00000111 &
b000000000111 '
#16000000
b00001000 !
b000000001000 "
b1000 #
b00001000 &
b000000001000 '
#18000000
b00001001 !
b000000001001 "
b1001 #
b00001001 &
b000000001001 '
#20000000
b00001010 !
b000000010000 "
b0000 #
b0001 $
b00001010 &
b000000010000 '
#22000000
b00001011 !
b000000010001 "
b0001 #
b00001011 &
b000000010001 '
#24000000
b00001100 !
b000000010010 "
b0010 #
b00001100 &
b000000010010 '
#26000000
b00001101 !
b000000010011 "
b0011 #
b00001101 &
b000000010011 '
#28000000
b00001110 !
b000000010100 "
b0100 #
b00001110 &
b000000010100 '
#30000000
b00001111 !
b000000010101 "
b0101 #
b00001111 &
b000000010101 '
#32000000
b00010000 !
b000000010110 "
b0110 #
b00010000 &
b000000010110 '
#34000000
b00010001 !
b000000010111 "
b0111 #
b00010001 &
b000000010111 '
#36000000
b00010010 !
b000000011000 "
b1000 #
b00010010 &
b000000011000 '
#38000000
b00010011 !
b000000011001 "
b1001 #
b00010011 &
b000000011001 '
#40000000
b00010100 !
b000000100000 "
b0000 #
b0010 $
b00010100 &
b000000100000 '
#42000000
b00010101 !
b000000100001 "
b0001 #
b00010101 &
b000000100001 '
#44000000
b00010110 !
b000000100010 "
b0010 #
b00010110 &
b000000100010 '
#46000000
b00010111 !
b000000100011 "
b0011 #
b00010111 &
b000000100011 '
#48000000
b00011000 !
b000000100100 "
b0100 #
b00011000 &
b000000100100 '
#50000000
b00011001 !
b000000100101 "
b0101 #
b00011001 &
b000000100101 '
#52000000
b00011010 !
b000000100110 "
b0110 #
b00011010 &
b000000100110 '
#54000000
b00011011 !
b000000100111 "
b0111 #
b00011011 &
b000000100111 '
#56000000
b00011100 !
b000000101000 "
b1000 #
b00011100 &
b000000101000 '
#58000000
b00011101 !
b000000101001 "
b1001 #
b00011101 &
b000000101001 '
#60000000
b00011110 !
b000000110000 "
b0000 #
b0011 $
b00011110 &
b000000110000 '
#62000000
b00011111 !
b000000110001 "
b0001 #
b00011111 &
b000000110001 '
#64000000
b00100000 !
b000000110010 "
b0010 #
b00100000 &
b000000110010 '
#66000000
b00100001 !
b000000110011 "
b0011 #
b00100001 &
b000000110011 '
#68000000
b00100010 !
b000000110100 "
b0100 #
b00100010 &
b000000110100 '
#70000000
b00100011 !
b000000110101 "
b0101 #
b00100011 &
b000000110101 '
#72000000
b00100100 !
b000000110110 "
b0110 #
b00100100 &
b000000110110 '
#74000000
b00100101 !
b000000110111 "
b0111 #
b00100101 &
b000000110111 '
#76000000
b00100110 !
b000000111000 "
b1000 #
b00100110 &
b000000111000 '
#78000000
b00100111 !
b000000111001 "
b1001 #
b00100111 &
b000000111001 '
#80000000
b00101000 !
b000001000000 "
b0000 #
b0100 $
b00101000 &
b000001000000 '
#82000000
b00101001 !
b000001000001 "
b0001 #
b00101001 &
b000001000001 '
#84000000
b00101010 !
b000001000010 "
b0010 #
b00101010 &
b000001000010 '
#86000000
b00101011 !
b000001000011 "
b0011 #
b00101011 &
b000001000011 '
#88000000
b00101100 !
b000001000100 "
b0100 #
b00101100 &
b000001000100 '
#90000000
b00101101 !
b000001000101 "
b0101 #
b00101101 &
b000001000101 '
#92000000
b00101110 !
b000001000110 "
b0110 #
b00101110 &
b000001000110 '
#94000000
b00101111 !
b000001000111 "
b0111 #
b00101111 &
b000001000111 '
#96000000
b00110000 !
b000001001000 "
b1000 #
b00110000 &
b000001001000 '
#98000000
b00110001 !
b000001001001 "
b1001 #
b00110001 &
b000001001001 '
#100000000
b00110010 !
b000001010000 "
b0000 #
b0101 $
b00110010 &
b000001010000 '
#102000000
b00110011 !
b000001010001 "
b0001 #
b00110011 &
b000001010001 '
#104000000
b00110100 !
b000001010010 "
b0010 #
b00110100 &
b000001010010 '
#106000000
b00110101 !
b000001010011 "
b0011 #
b00110101 &
b000001010011 '
#108000000
b00110110 !
b000001010100 "
b0100 #
b00110110 &
b000001010100 '
#110000000
b00110111 !
b000001010101 "
b0101 #
b00110111 &
b000001010101 '
#112000000
b00111000 !
b000001010110 "
b0110 #
b00111000 &
b000001010110 '
#114000000
b00111001 !
b000001010111 "
b0111 #
b00111001 &
b000001010111 '
#116000000
b00111010 !
b000001011000 "
b1000 #
b00111010 &
b000001011000 '
#118000000
b00111011 !
b000001011001 "
b1001 #
b00111011 &
b000001011001 '
#120000000
b00111100 !
b000001100000 "
b0000 #
b0110 $
b00111100 &
b000001100000 '
#122000000
b00111101 !
b000001100001 "
b0001 #
b00111101 &
b000001100001 '
#124000000
b00111110 !
b000001100010 "
b0010 #
b00111110 &
b000001100010 '
#126000000
b00111111 !
b000001100011 "
b0011 #
b00111111 &
b000001100011 '
#128000000
b01000000 !
b000001100100 "
b0100 #
b01000000 &
b000001100100 '
#130000000
b01000001 !
b000001100101 "
b0101 #
b01000001 &
b000001100101 '
#132000000
b01000010 !
b000001100110 "
b0110 #
b01000010 &
b000001100110 '
#134000000
b01000011 !
b000001100111 "
b0111 #
b01000011 &
b000001100111 '
#136000000
b01000100 !
b000001101000 "
b1000 #
b01000100 &
b000001101000 '
#138000000
b01000101 !
b000001101001 "
b1001 #
b01000101 &
b000001101001 '
#140000000
b01000110 !
b000001110000 "
b0000 #
b0111 $
b01000110 &
b000001110000 '
#142000000
b01000111 !
b000001110001 "
b0001 #
b01000111 &
b000001110001 '
#144000000
b01001000 !
b000001110010 "
b0010 #
b01001000 &
b000001110010 '
#146000000
b01001001 !
b000001110011 "
b0011 #
b01001001 &
b000001110011 '
#148000000
b01001010 !
b000001110100 "
b0100 #
b01001010 &
b000001110100 '
#150000000
b01001011 !
b000001110101 "
b0101 #
b01001011 &
b000001110101 '
#152000000
b01001100 !
b000001110110 "
b0110 #
b01001100 &
b000001110110 '
#154000000
b01001101 !
b000001110111 "
b0111 #
b01001101 &
b000001110111 '
#156000000
b01001110 !
b000001111000 "
b1000 #
b01001110 &
b000001111000 '
#158000000
b01001111 !
b000001111001 "
b1001 #
b01001111 &
b000001111001 '
#160000000
b01010000 !
b000010000000 "
b0000 #
b1000 $
b01010000 &
b000010000000 '
#162000000
b01010001 !
b000010000001 "
b0001 #
b01010001 &
b000010000001 '
#164000000
b01010010 !
b000010000010 "
b0010 #
b01010010 &
b000010000010 '
#166000000
b01010011 !
b000010000011 "
b0011 #
b01010011 &
b000010000011 '
#168000000
b01010100 !
b000010000100 "
b0100 #
b01010100 &
b000010000100 '
#170000000
b01010101 !
b000010000101 "
b0101 #
b01010101 &
b000010000101 '
#172000000
b01010110 !
b000010000110 "
b0110 #
b01010110 &
b000010000110 '
#174000000
b01010111 !
b000010000111 "
b0111 #
b01010111 &
b000010000111 '
#176000000
b01011000 !
b000010001000 "
b1000 #
b01011000 &
b000010001000 '
#178000000
b01011001 !
b000010001001 "
b1001 #
b01011001 &
b000010001001 '
#180000000
b01011010 !
b000010010000 "
b0000 #
b1001 $
b01011010 &
b000010010000 '
#182000000
b01011011 !
b000010010001 "
b0001 #
b01011011 &
b000010010001 '
#184000000
b01011100 !
b000010010010 "
b0010 #
b01011100 &
b000010010010 '
#186000000
b01011101 !
b000010010011 "
b0011 #
b01011101 &
b000010010011 '
#188000000
b01011110 !
b000010010100 "
b0100 #
b01011110 &
b000010010100 '
#190000000
b01011111 !
b000010010101 "
b0101 #
b01011111 &
b000010010101 '
#192000000
b01100000 !
b000010010110 "
b0110 #
b01100000 &
b000010010110 '
#194000000
b01100001 !
b000010010111 "
b0111 #
b01100001 &
b000010010111 '
#196000000
b01100010 !
b000010011000 "
b1000 #
b01100010 &
b000010011000 '
#198000000
b01100011 !
b000010011001 "
b1001 #
b01100011 &
b000010011001 '
#200000000
b01100100 !
b000100000000 "
b0000 #
b0000 $
b0001 %
b01100100 &
b000100000000 '
#202000000
b01100101 !
b000100000001 "
b0001 #
b01100101 &
b000100000001 '
#204000000
b01100110 !
b000100000010 "
b0010 #
b01100110 &
b000100000010 '
#206000000
b01100111 !
b000100000011 "
b0011 #
b01100111 &
b000100000011 '
#208000000
b01101000 !
b000100000100 "
b0100 #
b01101000 &
b000100000100 '
#210000000
b01101001 !
b000100000101 "
b0101 #
b01101001 &
b000100000101 '
#212000000
b01101010 !
b000100000110 "
b0110 #
b01101010 &
b000100000110 '
#214000000
b01101011 !
b000100000111 "
b0111 #
b01101011 &
b000100000111 '
#216000000
b01101100 !
b000100001000 "
b1000 #
b01101100 &
b000100001000 '
#218000000
b01101101 !
b000100001001 "
b1001 #
b01101101 &
b000100001001 '
#220000000
b01101110 !
b000100010000 "
b0000 #
b0001 $
b01101110 &
b000100010000 '
#222000000
b01101111 !
b000100010001 "
b0001 #
b01101111 &
b000100010001 '
#224000000
b01110000 !
b000100010010 "
b0010 #
b01110000 &
b000100010010 '
#226000000
b01110001 !
b000100010011 "
b0011 #
b01110001 &
b000100010011 '
#228000000
b01110010 !
b000100010100 "
b0100 #
b01110010 &
b000100010100 '
#230000000
b01110011 !
b000100010101 "
b0101 #
b01110011 &
b000100010101 '
#232000000
b01110100 !
b000100010110 "
b0110 #
b01110100 &
b000100010110 '
#234000000
b01110101 !
b000100010111 "
b0111 #
b01110101 &
b000100010111 '
#236000000
b01110110 !
b000100011000 "
b1000 #
b01110110 &
b000100011000 '
#238000000
b01110111 !
b000100011001 "
b1001 #
b01110111 &
b000100011001 '
#240000000
b01111000 !
b000100100000 "
b0000 #
b0010 $
b01111000 &
b000100100000 '
#242000000
b01111001 !
b000100100001 "
b0001 #
b01111001 &
b000100100001 '
#244000000
b01111010 !
b000100100010 "
b0010 #
b01111010 &
b000100100010 '
#246000000
b01111011 !
b000100100011 "
b0011 #
b01111011 &
b000100100011 '
#248000000
b01111100 !
b000100100100 "
b0100 #
b01111100 &
b000100100100 '
#250000000
b01111101 !
b000100100101 "
b0101 #
b01111101 &
b000100100101 '
#252000000
b01111110 !
b000100100110 "
b0110 #
b01111110 &
b000100100110 '
#254000000
b01111111 !
b000100100111 "
b0111 #
b01111111 &
b000100100111 '
#256000000
b10000000 !
b000100101000 "
b1000 #
b10000000 &
b000100101000 '
#258000000
b10000001 !
b000100101001 "
b1001 #
b10000001 &
b000100101001 '
#260000000
b10000010 !
b000100110000 "
b0000 #
b0011 $
b10000010 &
b000100110000 '
#262000000
b10000011 !
b000100110001 "
b0001 #
b10000011 &
b000100110001 '
#264000000
b10000100 !
b000100110010 "
b0010 #
b10000100 &
b000100110010 '
#266000000
b10000101 !
b000100110011 "
b0011 #
b10000101 &
b000100110011 '
#268000000
b10000110 !
b000100110100 "
b0100 #
b10000110 &
b000100110100 '
#270000000
b10000111 !
b000100110101 "
b0101 #
b10000111 &
b000100110101 '
#272000000
b10001000 !
b000100110110 "
b0110 #
b10001000 &
b000100110110 '
#274000000
b10001001 !
b000100110111 "
b0111 #
b10001001 &
b000100110111 '
#276000000
b10001010 !
b000100111000 "
b1000 #
b10001010 &
b000100111000 '
#278000000
b10001011 !
b000100111001 "
b1001 #
b10001011 &
b000100111001 '
#280000000
b10001100 !
b000101000000 "
b0000 #
b0100 $
b10001100 &
b000101000000 '
#282000000
b10001101 !
b000101000001 "
b0001 #
b10001101 &
b000101000001 '
#284000000
b10001110 !
b000101000010 "
b0010 #
b10001110 &
b000101000010 '
#286000000
b10001111 !
b000101000011 "
b0011 #
b10001111 &
b000101000011 '
#288000000
b10010000 !
b000101000100 "
b0100 #
b10010000 &
b000101000100 '
#290000000
b10010001 !
b000101000101 "
b0101 #
b10010001 &
b000101000101 '
#292000000
b10010010 !
b000101000110 "
b0110 #
b10010010 &
b000101000110 '
#294000000
b10010011 !
b000101000111 "
b0111 #
b10010011 &
b000101000111 '
#296000000
b10010100 !
b000101001000 "
b1000 #
b10010100 &
b000101001000 '
#298000000
b10010101 !
b000101001001 "
b1001 #
b10010101 &
b000101001001 '
#300000000
b10010110 !
b000101010000 "
b0000 #
b0101 $
b10010110 &
b000101010000 '
#302000000
b10010111 !
b000101010001 "
b0001 #
b10010111 &
b000101010001 '
#304000000
b10011000 !
b000101010010 "
b0010 #
b10011000 &
b000101010010 '
#306000000
b10011001 !
b000101010011 "
b0011 #
b10011001 &
b000101010011 '
#308000000
b10011010 !
b000101010100 "
b0100 #
b10011010 &
b000101010100 '
#310000000
b10011011 !
b000101010101 "
b0101 #
b10011011 &
b000101010101 '
#312000000
b10011100 !
b000101010110 "
b0110 #
b10011100 &
b000101010110 '
#314000000
b10011101 !
b000101010111 "
b0111 #
b10011101 &
b000101010111 '
#316000000
b10011110 !
b000101011000 "
b1000 #
b10011110 &
b000101011000 '
#318000000
b10011111 !
b000101011001 "
b1001 #
b10011111 &
b000101011001 '
#320000000
b10100000 !
b000101100000 "
b0000 #
b0110 $
b10100000 &
b000101100000 '
#322000000
b10100001 !
b000101100001 "
b0001 #
b10100001 &
b000101100001 '
#324000000
b10100010 !
b000101100010 "
b0010 #
b10100010 &
b000101100010 '
#326000000
b10100011 !
b000101100011 "
b0011 #
b10100011 &
b000101100011 '
#328000000
b10100100 !
b000101100100 "
b0100 #
b10100100 &
b000101100100 '
#330000000
b10100101 !
b000101100101 "
b0101 #
b10100101 &
b000101100101 '
#332000000
b10100110 !
b000101100110 "
b0110 #
b10100110 &
b000101100110 '
#334000000
b10100111 !
b000101100111 "
b0111 #
b10100111 &
b000101100111 '
#336000000
b10101000 !
b000101101000 "
b1000 #
b10101000 &
b000101101000 '
#338000000
b10101001 !
b000101101001 "
b1001 #
b10101001 &
b000101101001 '
#340000000
b10101010 !
b000101110000 "
b0000 #
b0111 $
b10101010 &
b000101110000 '
#342000000
b10101011 !
b000101110001 "
b0001 #
b10101011 &
b000101110001 '
#344000000
b10101100 !
b000101110010 "
b0010 #
b10101100 &
b000101110010 '
#346000000
b10101101 !
b000101110011 "
b0011 #
b10101101 &
b000101110011 '
#348000000
b10101110 !
b000101110100 "
b0100 #
b10101110 &
b000101110100 '
#350000000
b10101111 !
b000101110101 "
b0101 #
b10101111 &
b000101110101 '
#352000000
b10110000 !
b000101110110 "
b0110 #
b10110000 &
b000101110110 '
#354000000
b10110001 !
b000101110111 "
b0111 #
b10110001 &
b000101110111 '
#356000000
b10110010 !
b000101111000 "
b1000 #
b10110010 &
b000101111000 '
#358000000
b10110011 !
b000101111001 "
b1001 #
b10110011 &
b000101111001 '
#360000000
b10110100 !
b000110000000 "
b0000 #
b1000 $
b10110100 &
b000110000000 '
#362000000
b10110101 !
b000110000001 "
b0001 #
b10110101 &
b000110000001 '
#364000000
b10110110 !
b000110000010 "
b0010 #
b10110110 &
b000110000010 '
#366000000
b10110111 !
b000110000011 "
b0011 #
b10110111 &
b000110000011 '
#368000000
b10111000 !
b000110000100 "
b0100 #
b10111000 &
b000110000100 '
#370000000
b10111001 !
b000110000101 "
b0101 #
b10111001 &
b000110000101 '
#372000000
b10111010 !
b000110000110 "
b0110 #
b10111010 &
b000110000110 '
#374000000
b10111011 !
b000110000111 "
b0111 #
b10111011 &
b000110000111 '
#376000000
b10111100 !
b000110001000 "
b1000 #
b10111100 &
b000110001000 '
#378000000
b10111101 !
b000110001001 "
b1001 #
b10111101 &
b000110001001 '
#380000000
b10111110 !
b000110010000 "
b0000 #
b1001 $
b10111110 &
b000110010000 '
#382000000
b10111111 !
b000110010001 "
b0001 #
b10111111 &
b000110010001 '
#384000000
b11000000 !
b000110010010 "
b0010 #
b11000000 &
b000110010010 '
#386000000
b11000001 !
b000110010011 "
b0011 #
b11000001 &
b000110010011 '
#388000000
b11000010 !
b000110010100 "
b0100 #
b11000010 &
b000110010100 '
#390000000
b11000011 !
b000110010101 "
b0101 #
b11000011 &
b000110010101 '
#392000000
b11000100 !
b000110010110 "
b0110 #
b11000100 &
b000110010110 '
#394000000
b11000101 !
b000110010111 "
b0111 #
b11000101 &
b000110010111 '
#396000000
b11000110 !
b000110011000 "
b1000 #
b11000110 &
b000110011000 '
#398000000
b11000111 !
b000110011001 "
b1001 #
b11000111 &
b000110011001 '
#400000000
b11001000 !
b001000000000 "
b0000 #
b0000 $
b0010 %
b11001000 &
b001000000000 '
#402000000
b11001001 !
b001000000001 "
b0001 #
b11001001 &
b001000000001 '
#404000000
b11001010 !
b001000000010 "
b0010 #
b11001010 &
b001000000010 '
#406000000
b11001011 !
b001000000011 "
b0011 #
b11001011 &
b001000000011 '
#408000000
b11001100 !
b001000000100 "
b0100 #
b11001100 &
b001000000100 '
#410000000
b11001101 !
b001000000101 "
b0101 #
b11001101 &
b001000000101 '
#412000000
b11001110 !
b001000000110 "
b0110 #
b11001110 &
b001000000110 '
#414000000
b11001111 !
b001000000111 "
b0111 #
b11001111 &
b001000000111 '
#416000000
b11010000 !
b001000001000 "
b1000 #
b11010000 &
b001000001000 '
#418000000
b11010001 !
b001000001001 "
b1001 #
b11010001 &
b001000001001 '
#420000000
b11010010 !
b001000010000 "
b0000 #
b0001 $
b11010010 &
b001000010000 '
#422000000
b11010011 !
b001000010001 "
b0001 #
b11010011 &
b001000010001 '
#424000000
b11010100 !
b001000010010 "
b0010 #
b11010100 &
b001000010010 '
#426000000
b11010101 !
b001000010011 "
b0011 #
b11010101 &
b001000010011 '
#428000000
b11010110 !
b001000010100 "
b0100 #
b11010110 &
b001000010100 '
#430000000
b11010111 !
b001000010101 "
b0101 #
b11010111 &
b001000010101 '
#432000000
b11011000 !
b001000010110 "
b0110 #
b11011000 &
b001000010110 '
#434000000
b11011001 !
b001000010111 "
b0111 #
b11011001 &
b001000010111 '
#436000000
b11011010 !
b001000011000 "
b1000 #
b11011010 &
b001000011000 '
#438000000
b11011011 !
b001000011001 "
b1001 #
b11011011 &
b001000011001 '
#440000000
b11011100 !
b001000100000 "
b0000 #
b0010 $
b11011100 &
b001000100000 '
#442000000
b11011101 !
b001000100001 "
b0001 #
b11011101 &
b001000100001 '
#444000000
b11011110 !
b001000100010 "
b0010 #
b11011110 &
b001000100010 '
#446000000
b11011111 !
b001000100011 "
b0011 #
b11011111 &
b001000100011 '
#448000000
b11100000 !
b001000100100 "
b0100 #
b11100000 &
b001000100100 '
#450000000
b11100001 !
b001000100101 "
b0101 #
b11100001 &
b001000100101 '
#452000000
b11100010 !
b001000100110 "
b0110 #
b11100010 &
b001000100110 '
#454000000
b11100011 !
b001000100111 "
b0111 #
b11100011 &
b001000100111 '
#456000000
b11100100 !
b001000101000 "
b1000 #
b11100100 &
b001000101000 '
#458000000
b11100101 !
b001000101001 "
b1001 #
b11100101 &
b001000101001 '
#460000000
b11100110 !
b001000110000 "
b0000 #
b0011 $
b11100110 &
b001000110000 '
#462000000
b11100111 !
b001000110001 "
b0001 #
b11100111 &
b001000110001 '
#464000000
b11101000 !
b001000110010 "
b0010 #
b11101000 &
b001000110010 '
#466000000
b11101001 !
b001000110011 "
b0011 #
b11101001 &
b001000110011 '
#468000000
b11101010 !
b001000110100 "
b0100 #
b11101010 &
b001000110100 '
#470000000
b11101011 !
b001000110101 "
b0101 #
b11101011 &
b001000110101 '
#472000000
b11101100 !
b001000110110 "
b0110 #
b11101100 &
b001000110110 '
#474000000
b11101101 !
b001000110111 "
b0111 #
b11101101 &
b001000110111 '
#476000000
b11101110 !
b001000111000 "
b1000 #
b11101110 &
b001000111000 '
#478000000
b11101111 !
b001000111001 "
b1001 #
b11101111 &
b001000111001 '
#480000000
b11110000 !
b001001000000 "
b0000 #
b0100 $
b11110000 &
b001001000000 '
#482000000
b11110001 !
b001001000001 "
b0001 #
b11110001 &
b001001000001 '
#484000000
b11110010 !
b001001000010 "
b0010 #
b11110010 &
b001001000010 '
#486000000
b11110011 !
b001001000011 "
b0011 #
b11110011 &
b001001000011 '
#488000000
b11110100 !
b001001000100 "
b0100 #
b11110100 &
b001001000100 '
#490000000
b11110101 !
b001001000101 "
b0101 #
b11110101 &
b001001000101 '
#492000000
b11110110 !
b001001000110 "
b0110 #
b11110110 &
b001001000110 '
#494000000
b11110111 !
b001001000111 "
b0111 #
b11110111 &
b001001000111 '
#496000000
b11111000 !
b001001001000 "
b1000 #
b11111000 &
b001001001000 '
#498000000
b11111001 !
b001001001001 "
b1001 #
b11111001 &
b001001001001 '
#500000000
b11111010 !
b001001010000 "
b0000 #
b0101 $
b11111010 &
b001001010000 '
#502000000
b11111011 !
b001001010001 "
b0001 #
b11111011 &
b001001010001 '
#504000000
b11111100 !
b001001010010 "
b0010 #
b11111100 &
b001001010010 '
#506000000
b11111101 !
b001001010011 "
b0011 #
b11111101 &
b001001010011 '
#508000000
b11111110 !
b001001010100 "
b0100 #
b11111110 &
b001001010100 '
#510000000
b11111111 !
b001001010101 "
b0101 #
b11111111 &
b001001010101 '
#512000000
b00000000 !
b000000000000 "
b0000 #
b0000 $
b0000 %
b00000000 &
b000000000000 '
#514000000
b00000001 !
b000000000001 "
b0001 #
b00000001 &
b000000000001 '
#516000000
b00000010 !
b000000000010 "
b0010 #
b00000010 &
b000000000010 '
#518000000
b00000011 !
b000000000011 "
b0011 #
b00000011 &
b000000000011 '
#520000000
b00000100 !
b000000000100 "
b0100 #
b00000100 &
b000000000100 '
#522000000
b00000101 !
b000000000101 "
b0101 #
b00000101 &
b000000000101 '
#524000000
b00000110 !
b000000000110 "
b0110 #
b00000110 &
b000000000110 '
#526000000
b00000111 !
b000000000111 "
b0111 #
b00000111 &
b000000000111 '
#528000000
b00001000 !
b000000001000 "
b1000 #
b00001000 &
b000000001000 '
#530000000
b00001001 !
b000000001001 "
b1001 #
b00001001 &
b000000001001 '
#532000000
b00001010 !
b000000010000 "
b0000 #
b0001 $
b00001010 &
b000000010000 '
#534000000
b00001011 !
b000000010001 "
b0001 #
b00001011 &
b000000010001 '
#536000000
b00001100 !
b000000010010 "
b0010 #
b00001100 &
b000000010010 '
#538000000
b00001101 !
b000000010011 "
b0011 #
b00001101 &
b000000010011 '
#540000000
b00001110 !
b000000010100 "
b0100 #
b00001110 &
b000000010100 '
#542000000
b00001111 !
b000000010101 "
b0101 #
b00001111 &
b000000010101 '
#544000000
b00010000 !
b000000010110 "
b0110 #
b00010000 &
b000000010110 '
#546000000
b00010001 !
b000000010111 "
b0111 #
b00010001 &
b000000010111 '
#548000000
b00010010 !
b000000011000 "
b1000 #
b00010010 &
b000000011000 '
#550000000
b00010011 !
b000000011001 "
b1001 #
b00010011 &
b000000011001 '
#552000000
b00010100 !
b000000100000 "
b0000 #
b0010 $
b00010100 &
b000000100000 '
#554000000
b00010101 !
b000000100001 "
b0001 #
b00010101 &
b000000100001 '
#556000000
b00010110 !
b000000100010 "
b0010 #
b00010110 &
b000000100010 '
#558000000
b00010111 !
b000000100011 "
b0011 #
b00010111 &
b000000100011 '
#560000000
b00011000 !
b000000100100 "
b0100 #
b00011000 &
b000000100100 '
#562000000
b00011001 !
b000000100101 "
b0101 #
b00011001 &
b000000100101 '
#564000000
b00011010 !
b000000100110 "
b0110 #
b00011010 &
b000000100110 '
#566000000
b00011011 !
b000000100111 "
b0111 #
b00011011 &
b000000100111 '
#568000000
b00011100 !
b000000101000 "
b1000 #
b00011100 &
b000000101000 '
#570000000
b00011101 !
b000000101001 "
b1001 #
b00011101 &
b000000101001 '
#572000000
b00011110 !
b000000110000 "
b0000 #
b0011 $
b00011110 &
b000000110000 '
#574000000
b00011111 !
b000000110001 "
b0001 #
b00011111 &
b000000110001 '
#576000000
b00100000 !
b000000110010 "
b0010 #
b00100000 &
b000000110010 '
#578000000
b00100001 !
b000000110011 "
b0011 #
b00100001 &
b000000110011 '
#580000000
b00100010 !
b000000110100 "
b0100 #
b00100010 &
b000000110100 '
#582000000
b00100011 !
b000000110101 "
b0101 #
b00100011 &
b000000110101 '
#584000000
b00100100 !
b000000110110 "
b0110 #
b00100100 &
b000000110110 '
#586000000
b00100101 !
b000000110111 "
b0111 #
b00100101 &
b000000110111 '
#588000000
b00100110 !
b000000111000 "
b1000 #
b00100110 &
b000000111000 '
#590000000
b00100111 !
b000000111001 "
b1001 #
b00100111 &
b000000111001 '
#592000000
b00101000 !
b000001000000 "
b0000 #
b0100 $
b00101000 &
b000001000000 '
#594000000
b00101001 !
b000001000001 "
b0001 #
b00101001 &
b000001000001 '
#596000000
b00101010 !
b000001000010 "
b0010 #
b00101010 &
b000001000010 '
#598000000
b00101011 !
b000001000011 "
b0011 #
b00101011 &
b000001000011 '
#600000000
b00101100 !
b000001000100 "
b0100 #
b00101100 &
b000001000100 '
#602000000
b00101101 !
b000001000101 "
b0101 #
b00101101 &
b000001000101 '
#604000000
b00101110 !
b000001000110 "
b0110 #
b00101110 &
b000001000110 '
#606000000
b00101111 !
b000001000111 "
b0111 #
b00101111 &
b000001000111 '
#608000000
b00110000 !
b000001001000 "
b1000 #
b00110000 &
b000001001000 '
#610000000
b00110001 !
b000001001001 "
b1001 #
b00110001 &
b000001001001 '
#612000000
b00110010 !
b000001010000 "
b0000 #
b0101 $
b00110010 &
b000001010000 '
#614000000
b00110011 !
b000001010001 "
b0001 #
b00110011 &
b000001010001 '
#616000000
b00110100 !
b000001010010 "
b0010 #
b00110100 &
b000001010010 '
#618000000
b00110101 !
b000001010011 "
b0011 #
b00110101 &
b000001010011 '
#620000000
b00110110 !
b000001010100 "
b0100 #
b00110110 &
b000001010100 '
#622000000
b00110111 !
b000001010101 "
b0101 #
b00110111 &
b000001010101 '
#624000000
b00111000 !
b000001010110 "
b0110 #
b00111000 &
b000001010110 '
#626000000
b00111001 !
b000001010111 "
b0111 #
b00111001 &
b000001010111 '
#628000000
b00111010 !
b000001011000 "
b1000 #
b00111010 &
b000001011000 '
#630000000
b00111011 !
b000001011001 "
b1001 #
b00111011 &
b000001011001 '
#632000000
b00111100 !
b000001100000 "
b0000 #
b0110 $
b00111100 &
b000001100000 '
