FPGA/FPGA 04/skeleton04b/7segment.m.vhd
---------------------------------------
-- lecture 02 shift register
-- just forwarding the signal
----------------------------------------

library ieee;
use ieee.std_logic_1164.all;
use ieee.numeric_std.all;

----------------------------------------

entity segment7 is
    port(   
        i_slv_number   :  in  std_logic_vector( 3 downto 0);  -- number input   0 - 9
        o_slv_segments :  out std_logic_vector( 6 downto 0)   -- segment output G - A
    );
end segment7;  

----------------------------------------

architecture behavior of segment7 is
begin
	process(i_slv_number)
	begin
	    Bums: case i_slv_number is
			when "0000" => o_slv_segments <= "0000001";
			when "0001" => o_slv_segments <= "0000011";
			when "0010" => o_slv_segments <= "0000111";
			when "0011" => o_slv_segments <= "0001111";
			when "0100" => o_slv_segments <= "0011111";
			when "0101" => o_slv_segments <= "0111111";
			when "0110" => o_slv_segments <= "1111111";
			when "0111" => o_slv_segments <= "1010101";
			when "1000" => o_slv_segments <= "0101010";
			when others => o_slv_segments <= "0001111";
		    end case bums;
	end process;

end behavior;

------------------------------------------

FPGA/FPGA 04/skeleton04b/7segment.tb.vhd
library ieee;
use ieee.std_logic_1164.all;
use ieee.numeric_std.all;

ENTITY segment7_tb IS
END segment7_tb;

ARCHITECTURE tb OF segment7_tb IS 

    COMPONENT segment7 is
        port(   
            i_slv_number   :  in  std_logic_vector( 3 downto 0);  -- number input
            o_slv_segments :  out std_logic_vector( 6 downto 0)   -- segments output
        );
    end COMPONENT;

    -- "local" signals

    -- signals for UUT
    -- input 
    signal number : std_logic_vector( 3 downto 0) := (others => '0');

    -- ouput
    signal o_slv_segments  : std_logic_vector( 6 downto 0) := (others => '0');

BEGIN 
    -- Instance of unit under test.
    segment1: segment7 
    PORT MAP (
        i_slv_number   => number,
        o_slv_segments => o_slv_segments
    );

-------------------------------------------------------------------------------
    -- test bench definition.
    tb_CLK :process
    begin
	for i in 0 to 9 loop
	    number <= std_logic_vector(to_unsigned(i, 4));
	    wait for 5 ns;
	end loop;
    end process;

END;

FPGA/FPGA 04/skeleton04b/7segment.vcd
$date
  Fri Jan  8 12:11:25 2021
$end
$version
  GHDL v0
$end
$timescale
  1 fs
$end
$scope module standard $end
$upscope $end
$scope module textio $end
$upscope $end
$scope module std_logic_1164 $end
$upscope $end
$scope module numeric_std $end
$upscope $end
$scope module segment7_tb $end
$var reg 4 ! number[3:0] $end
$var reg 7 " o_slv_segments[6:0] $end
$scope module segment1 $end
$var reg 4 # i_slv_number[3:0] $end
$var reg 7 $ o_slv_segments[6:0] $end
$upscope $end
$upscope $end
$enddefinitions $end
#0
b0000 !
b0000001 "
b0000 #
b0000001 $
#5000000
b0001 !
b0000011 "
b0001 #
b0000011 $
#10000000
b0010 !
b0000111 "
b0010 #
b0000111 $
#15000000
b0011 !
b0001111 "
b0011 #
b0001111 $
#20000000
b0100 !
b0011111 "
b0100 #
b0011111 $
#25000000
b0101 !
b0111111 "
b0101 #
b0111111 $
#30000000
b0110 !
b1111111 "
b0110 #
b1111111 $
#35000000
b0111 !
b1010101 "
b0111 #
b1010101 $
#40000000
b1000 !
b0101010 "
b1000 #
b0101010 $
#45000000
b1001 !
b0001111 "
b1001 #
b0001111 $
#50000000
b0000 !
b0000001 "
b0000 #
b0000001 $
#55000000
b0001 !
b0000011 "
b0001 #
b0000011 $
#60000000
b0010 !
b0000111 "
b0010 #
b0000111 $
#65000000
b0011 !
b0001111 "
b0011 #
b0001111 $
#70000000
b0100 !
b0011111 "
b0100 #
b0011111 $
#75000000
b0101 !
b0111111 "
b0101 #
b0111111 $
#80000000
b0110 !
b1111111 "
b0110 #
b1111111 $
#85000000
b0111 !
b1010101 "
b0111 #
b1010101 $
#90000000
b1000 !
b0101010 "
b1000 #
b0101010 $
#95000000
b1001 !
b0001111 "
b1001 #
b0001111 $
#100000000
b0000 !
b0000001 "
b0000 #
b0000001 $
#105000000
b0001 !
b0000011 "
b0001 #
b0000011 $
#110000000
b0010 !
b0000111 "
b0010 #
b0000111 $
#115000000
b0011 !
b0001111 "
b0011 #
b0001111 $
#120000000
b0100 !
b0011111 "
b0100 #
b0011111 $
#125000000
b0101 !
b0111111 "
b0101 #
b0111111 $
#130000000
b0110 !
b1111111 "
b0110 #
b1111111 $
#135000000
b0111 !
b1010101 "
b0111 #
b1010101 $
#140000000
b1000 !
b0101010 "
b1000 #
b0101010 $
#145000000
b1001 !
b0001111 "
b1001 #
b0001111 $
#150000000
b0000 !
b0000001 "
b0000 #
b0000001 $
#155000000
b0001 !
b0000011 "
b0001 #
b0000011 $
#160000000
b0010 !
b0000111 "
b0010 #
b0000111 $
#165000000
b0011 !
b0001111 "
b0011 #
b0001111 $
#170000000
b0100 !
b0011111 "
b0100 #
b0011111 $
#175000000
b0101 !
b0111111 "
b0101 #
b0111111 $
#180000000
b0110 !
b1111111 "
b0110 #
b1111111 $
#185000000
b0111 !
b1010101 "
b0111 #
b1010101 $
#190000000
b1000 !
b0101010 "
b1000 #
b0101010 $
#195000000
b1001 !
b0001111 "
b1001 #
b0001111 $
#200000000
b0000 !
b0000001 "
b0000 #
b0000001 $
#205000000
b0001 !
b0000011 "
b0001 #
b0000011 $
#210000000
b0010 !
b0000111 "
b0010 #
b0000111 $
#215000000
b0011 !
b0001111 "
b0011 #
b0001111 $
#220000000
b0100 !
b0011111 "
b0100 #
b0011111 $
#225000000
b0101 !
b0111111 "
b0101 #
b0111111 $
#230000000
b0110 !
b1111111 "
b0110 #
b1111111 $
#235000000
b0111 !
b1010101 "
b0111 #
b1010101 $
#240000000
b1000 !
b0101010 "
b1000 #
b0101010 $
#245000000
b1001 !
b0001111 "
b1001 #
b0001111 $
#250000000
b0000 !
b0000001 "
b0000 #
b0000001 $
#255000000
b0001 !
b0000011 "
b0001 #
b0000011 $
#260000000
b0010 !
b0000111 "
b0010 #
b0000111 $
#265000000
b0011 !
b0001111 "
b0011 #
b0001111 $
#270000000
b0100 !
b0011111 "
b0100 #
b0011111 $
#275000000
b0101 !
b0111111 "
b0101 #
b0111111 $
#280000000
b0110 !
b1111111 "
b0110 #
b1111111 $
#285000000
b0111 !
b1010101 "
b0111 #
b1010101 $
#290000000
b1000 !
b0101010 "
b1000 #
b0101010 $
#295000000
b1001 !
b0001111 "
b1001 #
b0001111 $
#300000000
b0000 !
b0000001 "
b0000 #
b0000001 $
#305000000
b0001 !
b0000011 "
b0001 #
b0000011 $
#310000000
b0010 !
b0000111 "
b0010 #
b0000111 $
#315000000
b0011 !
b0001111 "
b0011 #
b0001111 $
#320000000
b0100 !
b0011111 "
b0100 #
b0011111 $
#325000000
b0101 !
b0111111 "
b0101 #
b0111111 $
#330000000
b0110 !
b1111111 "
b0110 #
b1111111 $
#335000000
b0111 !
b1010101 "
b0111 #
b1010101 $
#340000000
b1000 !
b0101010 "
b1000 #
b0101010 $
#345000000
b1001 !
b0001111 "
b1001 #
b0001111 $
#350000000
b0000 !
b0000001 "
b0000 #
b0000001 $
#355000000
b0001 !
b0000011 "
b0001 #
b0000011 $
#360000000
b0010 !
b0000111 "
b0010 #
b0000111 $
#365000000
b0011 !
b0001111 "
b0011 #
b0001111 $
#370000000
b0100 !
b0011111 "
b0100 #
b0011111 $
#375000000
b0101 !
b0111111 "
b0101 #
b0111111 $
#380000000
b0110 !
b1111111 "
b0110 #
b1111111 $
#385000000
b0111 !
b1010101 "
b0111 #
b1010101 $
#390000000
b1000 !
b0101010 "
b1000 #
b0101010 $
#395000000
b1001 !
b0001111 "
b1001 #
b0001111 $
#400000000
b0000 !
b0000001 "
b0000 #
b0000001 $
#405000000
b0001 !
b0000011 "
b0001 #
b0000011 $
#410000000
b0010 !
b0000111 "
b0010 #
b0000111 $
#415000000
b0011 !
b0001111 "
b0011 #
b0001111 $
#420000000
b0100 !
b0011111 "
b0100 #
b0011111 $
#425000000
b0101 !
b0111111 "
b0101 #
b0111111 $
#430000000
b0110 !
b1111111 "
b0110 #
b1111111 $
#435000000
b0111 !
b1010101 "
b0111 #
b1010101 $
#440000000
b1000 !
b0101010 "
b1000 #
b0101010 $
#445000000
b1001 !
b0001111 "
b1001 #
b0001111 $
#450000000
b0000 !
b0000001 "
b0000 #
b0000001 $
#455000000
b0001 !
b0000011 "
b0001 #
b0000011 $
#460000000
b0010 !
b0000111 "
b0010 #
b0000111 $
#465000000
b0011 !
b0001111 "
b0011 #
b0001111 $
#470000000
b0100 !
b0011111 "
b0100 #
b0011111 $
#475000000
b0101 !
b0111111 "
b0101 #
b0111111 $
#480000000
b0110 !
b1111111 "
b0110 #
b1111111 $
#485000000
b0111 !
b1010101 "
b0111 #
b1010101 $
#490000000
b1000 !
b0101010 "
b1000 #
b0101010 $
#495000000
b1001 !
b0001111 "
b1001 #
b0001111 $
#500000000
b0000 !
b0000001 "
b0000 #
b0000001 $
#505000000
b0001 !
b0000011 "
b0001 #
b0000011 $
#510000000
b0010 !
b0000111 "
b0010 #
b0000111 $
#515000000
b0011 !
b0001111 "
b0011 #
b0001111 $
#520000000
b0100 !
b0011111 "
b0100 #
b0011111 $
#525000000
b0101 !
b0111111 "
b0101 #
b0111111 $
#530000000
b0110 !
b1111111 "
b0110 #
b1111111 $
#535000000
b0111 !
b1010101 "
b0111 #
b1010101 $
#540000000
b1000 !
b0101010 "
b1000 #
b0101010 $
#545000000
b1001 !
b0001111 "
b1001 #
b0001111 $
#550000000
b0000 !
b0000001 "
b0000 #
b0000001 $
#555000000
b0001 !
b0000011 "
b0001 #
b0000011 $
#560000000
b0010 !
b0000111 "
b0010 #
b0000111 $
#565000000
b0011 !
b0001111 "
b0011 #
b0001111 $
#570000000
b0100 !
b0011111 "
b0100 #
b0011111 $
#575000000
b0101 !
b0111111 "
b0101 #
b0111111 $
#580000000
b0110 !
b1111111 "
b0110 #
b1111111 $
#585000000
b0111 !
b1010101 "
b0111 #
b1010101 $
#590000000
b1000 !
b0101010 "
b1000 #
b0101010 $
#595000000
b1001 !
b0001111 "
b1001 #
b0001111 $
#600000000
b0000 !
b0000001 "
b0000 #
b0000001 $
#605000000
b0001 !
b0000011 "
b0001 #
b0000011 $
#610000000
b0010 !
b0000111 "
b0010 #
b0000111 $
#615000000
b0011 !
b0001111 "
b0011 #
b0001111 $
#620000000
b0100 !
b0011111 "
b0100 #
b0011111 $
#625000000
b0101 !
b0111111 "
b0101 #
b0111111 $
#630000000
b0110 !
b1111111 "
b0110 #
b1111111 $
#635000000
b0111 !
b1010101 "
b0111 #
b1010101 $
#640000000
b1000 !
b0101010 "
b1000 #
b0101010 $
#645000000
b1001 !
b0001111 "
b1001 #
b0001111 $
#650000000
b0000 !
b0000001 "
b0000 #
b0000001 $
#655000000
b0001 !
b0000011 "
b0001 #
b0000011 $
#660000000
b0010 !
b0000111 "
b0010 #
b0000111 $
#665000000
b0011 !
b0001111 "
b0011 #
b0001111 $
#670000000
b0100 !
b0011111 "
b0100 #
b0011111 $
#675000000
b0101 !
b0111111 "
b0101 #
b0111111 $
#680000000
b0110 !
b1111111 "
b0110 #
b1111111 $
#685000000
b0111 !
b1010101 "
b0111 #
b1010101 $
#690000000
b1000 !
b0101010 "
b1000 #
b0101010 $
#695000000
b1001 !
b0001111 "
b1001 #
b0001111 $
#700000000
b0000 !
b0000001 "
b0000 #
b0000001 $
#705000000
b0001 !
b0000011 "
b0001 #
b0000011 $
#710000000
b0010 !
b0000111 "
b0010 #
b0000111 $
#715000000
b0011 !
b0001111 "
b0011 #
b0001111 $
#720000000
b0100 !
b0011111 "
b0100 #
b0011111 $
#725000000
b0101 !
b0111111 "
b0101 #
b0111111 $
#730000000
b0110 !
b1111111 "
b0110 #
b1111111 $
#735000000
b0111 !
b1010101 "
b0111 #
b1010101 $
#740000000
b1000 !
b0101010 "
b1000 #
b0101010 $
#745000000
b1001 !
b0001111 "
b1001 #
b0001111 $
#750000000
b0000 !
b0000001 "
b0000 #
b0000001 $
#755000000
b0001 !
b0000011 "
b0001 #
b0000011 $
#760000000
b0010 !
b0000111 "
b0010 #
b0000111 $
#765000000
b0011 !
b0001111 "
b0011 #
b0001111 $
#770000000
b0100 !
b0011111 "
b0100 #
b0011111 $
#775000000
b0101 !
b0111111 "
b0101 #
b0111111 $
#780000000
b0110 !
b1111111 "
b0110 #
b1111111 $
#785000000
b0111 !
b1010101 "
b0111 #
b1010101 $
#790000000
b1000 !
b0101010 "
b1000 #
b0101010 $
#795000000
b1001 !
b0001111 "
b1001 #
b0001111 $
#800000000
b0000 !
b0000001 "
b0000 #
b0000001 $
#805000000
b0001 !
b0000011 "
b0001 #
b0000011 $
#810000000
b0010 !
b0000111 "
b0010 #
b0000111 $
#815000000
b0011 !
b0001111 "
b0011 #
b0001111 $
#820000000
b0100 !
b0011111 "
b0100 #
b0011111 $
#825000000
b0101 !
b0111111 "
b0101 #
b0111111 $
#830000000
b0110 !
b1111111 "
b0110 #
b1111111 $
#835000000
b0111 !
b1010101 "
b0111 #
b1010101 $
#840000000
b1000 !
b0101010 "
b1000 #
b0101010 $
#845000000
b1001 !
b0001111 "
b1001 #
b0001111 $
#850000000
b0000 !
b0000001 "
b0000 #
b0000001 $
#855000000
b0001 !
b0000011 "
b0001 #
b0000011 $
#860000000
b0010 !
b0000111 "
b0010 #
b0000111 $
#865000000
b0011 !
b0001111 "
b0011 #
b0001111 $
#870000000
b0100 !
b0011111 "
b0100 #
b0011111 $
#875000000
b0101 !
b0111111 "
b0101 #
b0111111 $
#880000000
b0110 !
b1111111 "
b0110 #
b1111111 $
#885000000
b0111 !
b1010101 "
b0111 #
b1010101 $
#890000000
b1000 !
b0101010 "
b1000 #
b0101010 $
#895000000
b1001 !
b0001111 "
b1001 #
b0001111 $
#900000000
b0000 !
b0000001 "
b0000 #
b0000001 $
#905000000
b0001 !
b0000011 "
b0001 #
b0000011 $
#910000000
b0010 !
b0000111 "
b0010 #
b0000111 $
#915000000
b0011 !
b0001111 "
b0011 #
b0001111 $
#920000000
b0100 !
b0011111 "
b0100 #
b0011111 $
#925000000
b0101 !
b0111111 "
b0101 #
b0111111 $
#930000000
b0110 !
b1111111 "
b0110 #
b1111111 $
#935000000
b0111 !
b1010101 "
b0111 #
b1010101 $
#940000000
b1000 !
b0101010 "
b1000 #
b0101010 $
#945000000
b1001 !
b0001111 "
b1001 #
b0001111 $
#950000000
b0000 !
b0000001 "
b0000 #
b0000001 $
#955000000
b0001 !
b0000011 "
b0001 #
b0000011 $
#960000000
b0010 !
b0000111 "
b0010 #
b0000111 $
#965000000
b0011 !
b0001111 "
b0011 #
b0001111 $
#970000000
b0100 !
b0011111 "
b0100 #
b0011111 $
#975000000
b0101 !
b0111111 "
b0101 #
b0111111 $
#980000000
b0110 !
b1111111 "
b0110 #
b1111111 $
#985000000
b0111 !
b1010101 "
b0111 #
b1010101 $
#990000000
b1000 !
b0101010 "
b1000 #
b0101010 $
#995000000
b1001 !
b0001111 "
b1001 #
b0001111 $
#1000000000
b0000 !
b0000001 "
b0000 #
b0000001 $
#1005000000
b0001 !
b0000011 "
b0001 #
b0000011 $
#1010000000
b0010 !
b0000111 "
b0010 #
b0000111 $
#1015000000
b0011 !
b0001111 "
b0011 #
b0001111 $
#1020000000
b0100 !
b0011111 "
b0100 #
b0011111 $
#1025000000
b0101 !
b0111111 "
b0101 #
b0111111 $
#1030000000
b0110 !
b1111111 "
b0110 #
b1111111 $
#1035000000
b0111 !
b1010101 "
b0111 #
b1010101 $
#1040000000
b1000 !
b0101010 "
b1000 #
b0101010 $
#1045000000
b1001 !
b0001111 "
b1001 #
b0001111 $
#1050000000
b0000 !
b0000001 "
b0000 #
b0000001 $
#1055000000
b0001 !
b0000011 "
b0001 #
b0000011 $
#1060000000
b0010 !
b0000111 "
b0010 #
b0000111 $
#1065000000
b0011 !
b0001111 "
b0011 #
b0001111 $
#1070000000
b0100 !
b0011111 "
b0100 #
b0011111 $
#1075000000
b0101 !
b0111111 "
b0101 #
b0111111 $
#1080000000
b0110 !
b1111111 "
b0110 #
b1111111 $
#1085000000
b0111 !
b1010101 "
b0111 #
b1010101 $
#1090000000
b1000 !
b0101010 "
b1000 #
b0101010 $
#1095000000
b1001 !
b0001111 "
b1001 #
b0001111 $
#1100000000
b0000 !
b0000001 "
b0000 #
b0000001 $
#1105000000
b0001 !
b0000011 "
b0001 #
b0000011 $
#1110000000
b0010 !
b0000111 "
b0010 #
b0000111 $
#1115000000
b0011 !
b0001111 "
b0011 #
b0001111 $
#1120000000
b0100 !
b0011111 "
b0100 #
b0011111 $
#1125000000
b0101 !
b0111111 "
b0101 #
b0111111 $
#1130000000
b0110 !
b1111111 "
b0110 #
b1111111 $
#1135000000
b0111 !
b1010101 "
b0111 #
b1010101 $
#1140000000
b1000 !
b0101010 "
b1000 #
b0101010 $
#1145000000
b1001 !
b0001111 "
b1001 #
b0001111 $
#1150000000
b0000 !
b0000001 "
b0000 #
b0000001 $
#1155000000
b0001 !
b0000011 "
b0001 #
b0000011 $
#1160000000
b0010 !
b0000111 "
b0010 #
b0000111 $
#1165000000
b0011 !
b0001111 "
b0011 #
b0001111 $
#1170000000
b0100 !
b0011111 "
b0100 #
b0011111 $
#1175000000
b0101 !
b0111111 "
b0101 #
b0111111 $
#1180000000
b0110 !
b1111111 "
b0110 #
b1111111 $
#1185000000
b0111 !
b1010101 "
b0111 #
b1010101 $
#1190000000
b1000 !
b0101010 "
b1000 #
b0101010 $
#1195000000
b1001 !
b0001111 "
b1001 #
b0001111 $
#1200000000
b0000 !
b0000001 "
b0000 #
b0000001 $
#1205000000
b0001 !
b0000011 "
b0001 #
b0000011 $
#1210000000
b0010 !
b0000111 "
b0010 #
b0000111 $
#1215000000
b0011 !
b0001111 "
b0011 #
b0001111 $
#1220000000
b0100 !
b0011111 "
b0100 #
b0011111 $
#1225000000
b0101 !
b0111111 "
b0101 #
b0111111 $
#1230000000
b0110 !
b1111111 "
b0110 #
b1111111 $
#1235000000
b0111 !
b1010101 "
b0111 #
b1010101 $
#1240000000
b1000 !
b0101010 "
b1000 #
b0101010 $
#1245000000
b1001 !
b0001111 "
b1001 #
b0001111 $
#1250000000
b0000 !
b0000001 "
b0000 #
b0000001 $
#1255000000
b0001 !
b0000011 "
b0001 #
b0000011 $
#1260000000
b0010 !
b0000111 "
b0010 #
b0000111 $
#1265000000
b0011 !
b0001111 "
b0011 #
b0001111 $
#1270000000
b0100 !
b0011111 "
b0100 #
b0011111 $
#1275000000
b0101 !
b0111111 "
b0101 #
b0111111 $
#1280000000
b0110 !
b1111111 "
b0110 #
b1111111 $
#1285000000
b0111 !
b1010101 "
b0111 #
b1010101 $
#1290000000
b1000 !
b0101010 "
b1000 #
b0101010 $
#1295000000
b1001 !
b0001111 "
b1001 #
b0001111 $
#1300000000
b0000 !
b0000001 "
b0000 #
b0000001 $
#1305000000
b0001 !
b0000011 "
b0001 #
b0000011 $
#1310000000
b0010 !
b0000111 "
b0010 #
b0000111 $
#1315000000
b0011 !
b0001111 "
b0011 #
b0001111 $
#1320000000
b0100 !
b0011111 "
b0100 #
b0011111 $
#1325000000
b0101 !
b0111111 "
b0101 #
b0111111 $
#1330000000
b0110 !
b1111111 "
b0110 #
b1111111 $
#1335000000
b0111 !
b1010101 "
b0111 #
b1010101 $
#1340000000
b1000 !
b0101010 "
b1000 #
b0101010 $
#1345000000
b1001 !
b0001111 "
b1001 #
b0001111 $
#1350000000
b0000 !
b0000001 "
b0000 #
b0000001 $
#1355000000
b0001 !
b0000011 "
b0001 #
b0000011 $
#1360000000
b0010 !
b0000111 "
b0010 #
b0000111 $
#1365000000
b0011 !
b0001111 "
b0011 #
b0001111 $
#1370000000
b0100 !
b0011111 "
b0100 #
b0011111 $
#1375000000
b0101 !
b0111111 "
b0101 #
b0111111 $
#1380000000
b0110 !
b1111111 "
b0110 #
b1111111 $
#1385000000
b0111 !
b1010101 "
b0111 #
b1010101 $
#1390000000
b1000 !
b0101010 "
b1000 #
b0101010 $
#1395000000
b1001 !
b0001111 "
b1001 #
b0001111 $
#1400000000
b0000 !
b0000001 "
b0000 #
b0000001 $
#1405000000
b0001 !
b0000011 "
b0001 #
b0000011 $
#1410000000
b0010 !
b0000111 "
b0010 #
b0000111 $
#1415000000
b0011 !
b0001111 "
b0011 #
b0001111 $
#1420000000
b0100 !
b0011111 "
b0100 #
b0011111 $
#1425000000
b0101 !
b0111111 "
b0101 #
b0111111 $
#1430000000
b0110 !
b1111111 "
b0110 #
b1111111 $
#1435000000
b0111 !
b1010101 "
b0111 #
b1010101 $
#1440000000
b1000 !
b0101010 "
b1000 #
b0101010 $
#1445000000
b1001 !
b0001111 "
b1001 #
b0001111 $
#1450000000
b0000 !
b0000001 "
b0000 #
b0000001 $
#1455000000
b0001 !
b0000011 "
b0001 #
b0000011 $
#1460000000
b0010 !
b0000111 "
b0010 #
b0000111 $
#1465000000
b0011 !
b0001111 "
b0011 #
b0001111 $
#1470000000
b0100 !
b0011111 "
b0100 #
b0011111 $
#1475000000
b0101 !
b0111111 "
b0101 #
b0111111 $
#1480000000
b0110 !
b1111111 "
b0110 #
b1111111 $
#1485000000
b0111 !
b1010101 "
b0111 #
b1010101 $
#1490000000
b1000 !
b0101010 "
b1000 #
b0101010 $
#1495000000
b1001 !
b0001111 "
b1001 #
b0001111 $
#1500000000
b0000 !
b0000001 "
b0000 #
b0000001 $
#1505000000
b0001 !
b0000011 "
b0001 #
b0000011 $
#1510000000
b0010 !
b0000111 "
b0010 #
b0000111 $
#1515000000
b0011 !
b0001111 "
b0011 #
b0001111 $
#1520000000
b0100 !
b0011111 "
b0100 #
b0011111 $
#1525000000
b0101 !
b0111111 "
b0101 #
b0111111 $
#1530000000
b0110 !
b1111111 "
b0110 #
b1111111 $
#1535000000
b0111 !
b1010101 "
b0111 #
b1010101 $
#1540000000
b1000 !
b0101010 "
b1000 #
b0101010 $
#1545000000
b1001 !
b0001111 "
b1001 #
b0001111 $
#1550000000
b0000 !
b0000001 "
b0000 #
b0000001 $
#1555000000
b0001 !
b0000011 "
b0001 #
b0000011 $
#1560000000
b0010 !
b0000111 "
b0010 #
b0000111 $
#1565000000
b0011 !
b0001111 "
b0011 #
b0001111 $
#1570000000
b0100 !
b0011111 "
b0100 #
b0011111 $
#1575000000
b0101 !
b0111111 "
b0101 #
b0111111 $
#1580000000
b0110 !
b1111111 "
b0110 #
b1111111 $
#1585000000
b0111 !
b1010101 "
b0111 #
b1010101 $
#1590000000
b1000 !
b0101010 "
b1000 #
b0101010 $
#1595000000
b1001 !
b0001111 "
b1001 #
b0001111 $
#1600000000
b0000 !
b0000001 "
b0000 #
b0000001 $
#1605000000
b0001 !
b0000011 "
b0001 #
b0000011 $
#1610000000
b0010 !
b0000111 "
b0010 #
b0000111 $
#1615000000
b0011 !
b0001111 "
b0011 #
b0001111 $
#1620000000
b0100 !
b0011111 "
b0100 #
b0011111 $
#1625000000
b0101 !
b0111111 "
b0101 #
b0111111 $
#1630000000
b0110 !
b1111111 "
b0110 #
b1111111 $
#1635000000
b0111 !
b1010101 "
b0111 #
b1010101 $
#1640000000
b1000 !
b0101010 "
b1000 #
b0101010 $
#1645000000
b1001 !
b0001111 "
b1001 #
b0001111 $
#1650000000
b0000 !
b0000001 "
b0000 #
b0000001 $
#1655000000
b0001 !
b0000011 "
b0001 #
b0000011 $
#1660000000
b0010 !
b0000111 "
b0010 #
b0000111 $
#1665000000
b0011 !
b0001111 "
b0011 #
b0001111 $
#1670000000
b0100 !
b0011111 "
b0100 #
b0011111 $
#1675000000
b0101 !
b0111111 "
b0101 #
b0111111 $
#1680000000
b0110 !
b1111111 "
b0110 #
b1111111 $
#1685000000
b0111 !
b1010101 "
b0111 #
b1010101 $
#1690000000
b1000 !
b0101010 "
b1000 #
b0101010 $
#1695000000
b1001 !
b0001111 "
b1001 #
b0001111 $
#1700000000
b0000 !
b0000001 "
b0000 #
b0000001 $
#1705000000
b0001 !
b0000011 "
b0001 #
b0000011 $
#1710000000
b0010 !
b0000111 "
b0010 #
b0000111 $
#1715000000
b0011 !
b0001111 "
b0011 #
b0001111 $
#1720000000
b0100 !
b0011111 "
b0100 #
b0011111 $
#1725000000
b0101 !
b0111111 "
b0101 #
b0111111 $
#1730000000
b0110 !
b1111111 "
b0110 #
b1111111 $
#1735000000
b0111 !
b1010101 "
b0111 #
b1010101 $
#1740000000
b1000 !
b0101010 "
b1000 #
b0101010 $
#1745000000
b1001 !
b0001111 "
b1001 #
b0001111 $
#1750000000
b0000 !
b0000001 "
b0000 #
b0000001 $
#1755000000
b0001 !
b0000011 "
b0001 #
b0000011 $
#1760000000
b0010 !
b0000111 "
b0010 #
b0000111 $
#1765000000
b0011 !
b0001111 "
b0011 #
b0001111 $
#1770000000
b0100 !
b0011111 "
b0100 #
b0011111 $
#1775000000
b0101 !
b0111111 "
b0101 #
b0111111 $
#1780000000
b0110 !
b1111111 "
b0110 #
b1111111 $
#1785000000
b0111 !
b1010101 "
b0111 #
b1010101 $
#1790000000
b1000 !
b0101010 "
b1000 #
b0101010 $
#1795000000
b1001 !
b0001111 "
b1001 #
b0001111 $
#1800000000
b0000 !
b0000001 "
b0000 #
b0000001 $
#1805000000
b0001 !
b0000011 "
b0001 #
b0000011 $
#1810000000
b0010 !
b0000111 "
b0010 #
b0000111 $
#1815000000
b0011 !
b0001111 "
b0011 #
b0001111 $
#1820000000
b0100 !
b0011111 "
b0100 #
b0011111 $
#1825000000
b0101 !
b0111111 "
b0101 #
b0111111 $
#1830000000
b0110 !
b1111111 "
b0110 #
b1111111 $
#1835000000
b0111 !
b1010101 "
b0111 #
b1010101 $
#1840000000
b1000 !
b0101010 "
b1000 #
b0101010 $
#1845000000
b1001 !
b0001111 "
b1001 #
b0001111 $
#1850000000
b0000 !
b0000001 "
b0000 #
b0000001 $
#1855000000
b0001 !
b0000011 "
b0001 #
b0000011 $
#1860000000
b0010 !
b0000111 "
b0010 #
b0000111 $
#1865000000
b0011 !
b0001111 "
b0011 #
b0001111 $
#1870000000
b0100 !
b0011111 "
b0100 #
b0011111 $
#1875000000
b0101 !
b0111111 "
b0101 #
b0111111 $
#1880000000
b0110 !
b1111111 "
b0110 #
b1111111 $
#1885000000
b0111 !
b1010101 "
b0111 #
b1010101 $
#1890000000
b1000 !
b0101010 "
b1000 #
b0101010 $
#1895000000
b1001 !
b0001111 "
b1001 #
b0001111 $
#1900000000
b0000 !
b0000001 "
b0000 #
b0000001 $
#1905000000
b0001 !
b0000011 "
b0001 #
b0000011 $
#1910000000
b0010 !
b0000111 "
b0010 #
b0000111 $
#1915000000
b0011 !
b0001111 "
b0011 #
b0001111 $
#1920000000
b0100 !
b0011111 "
b0100 #
b0011111 $
#1925000000
b0101 !
b0111111 "
b0101 #
b0111111 $
#1930000000
b0110 !
b1111111 "
b0110 #
b1111111 $
#1935000000
b0111 !
b1010101 "
b0111 #
b1010101 $
#1940000000
b1000 !
b0101010 "
b1000 #
b0101010 $
#1945000000
b1001 !
b0001111 "
b1001 #
b0001111 $
#1950000000
b0000 !
b0000001 "
b0000 #
b0000001 $
#1955000000
b0001 !
b0000011 "
b0001 #
b0000011 $
#1960000000
b0010 !
b0000111 "
b0010 #
b0000111 $
#1965000000
b0011 !
b0001111 "
b0011 #
b0001111 $
#1970000000
b0100 !
b0011111 "
b0100 #
b0011111 $
#1975000000
b0101 !
b0111111 "
b0101 #
b0111111 $
#1980000000
b0110 !
b1111111 "
b0110 #
b1111111 $
#1985000000
b0111 !
b1010101 "
b0111 #
b1010101 $
#1990000000
b1000 !
b0101010 "
b1000 #
b0101010 $
#1995000000
b1001 !
b0001111 "
b1001 #
b0001111 $
#2000000000
b0000 !
b0000001 "
b0000 #
b0000001 $
