FPGA/FPGA 03/counter/simple_gate.m.vhd
---------------------------------------
-- lecture 01 simple gate
-- just forwarding the signal
----------------------------------------

library ieee;
use ieee.std_logic_1164.all;
use ieee.numeric_std.all;
----------------------------------------
entity lecture01 is
generic(data_width : integer := 9);
port(	
	    i_sl_x : in  std_logic;
	    i_sl_dir : in std_logic;
	    i_sl_en : in std_logic;
	    i_sl_reset : in std_logic;
	    o_slv_shift : out std_logic_vector(data_width-1 downto 0)
);
end lecture01;  

----------------------------------------

architecture behaviour of lecture01 is
	signal shift_reg : std_logic_vector(data_width-1 downto 0) := (others => '0');
	signal reset : std_logic_vector(data_width-1 downto 0) := (others =>'0');
begin

    process(i_sl_x)
    begin
        -- compare to truth table
	if rising_edge(i_sl_x) then
		if (i_sl_en = '1') then
		    if (i_sl_dir = '1') then
			shift_reg <= std_logic_vector(unsigned(shift_reg)-1);
		    else 
			shift_reg <= std_logic_vector(unsigned(shift_reg)+1);
		    end if;
		end if;
	end if;
	if (i_sl_reset = '1') then
	    shift_reg <= reset;
	end if;
	o_slv_shift <= shift_reg;

    end process;
end behaviour;

------------------------------------------

FPGA/FPGA 03/counter/simple_gate.tb.vhd
library ieee;
use ieee.std_logic_1164.all;

ENTITY lecture01_tb IS
END lecture01_tb;

ARCHITECTURE tb OF lecture01_tb IS 
    COMPONENT lecture01 is
	generic(DATA_WIDTH : integer :=9);
        port(	
            i_sl_x      : in  std_logic;
	    i_sl_dir    : in  std_logic;
	    i_sl_en     : in  std_logic;
	    i_sl_reset  : in  std_logic;
	    o_slv_shift : out std_logic_vector(DATA_WIDTH-1 downto 0)
        );
    end COMPONENT;

    -- "local" signals
    constant DATA_WIDTH : integer := 9;
    -- signals for UUT
    -- input 
    signal x    : std_logic := '0';
    signal dir    : std_logic := '0';
    signal en    : std_logic := '0';
    signal reset : std_logic := '0';


    -- ouput
    signal o_slv_shift : std_logic_vector(DATA_WIDTH-1 downto 0) := (others => '0');

BEGIN 
    -- Instance of unit under test.
    uut: lecture01 
    GENERIC MAP(DATA_WIDTH => 9)
    PORT MAP (
        i_sl_x  => x,
	i_sl_dir => dir,
	i_sl_en => en,
	i_sl_reset => reset,
	o_slv_shift => o_slv_shift
    );

-------------------------------------------------------------------------------
    -- test bench definition.
    tb_process :process
    begin
        x <= '0';
        wait for 5 ns;
        x <= '1';
        wait for 5 ns;
    end process;

    tb_process_dir :process
    begin
        dir <= '0';
        wait for 60 ns;
        dir <= '1';
        wait for 60 ns;
    end process;

    tb_process_en :process
    begin
        en <= '0';
        wait for 10 ns;
        en <= '1';
        wait for 50 ns;
    end process;

    tb_process_reset :process
    begin
        reset <= '0';
        wait for 30 ns;
        reset <= '1';
        wait for 5 ns;
    end process;


END;

FPGA/FPGA 03/skeleton3c/counter.vcd
$date
  Thu Jan  7 19:43:03 2021
$end
$version
  GHDL v0
$end
$timescale
  1 fs
$end
$scope module standard $end
$upscope $end
$scope module textio $end
$upscope $end
$scope module std_logic_1164 $end
$upscope $end
$scope module numeric_std $end
$upscope $end
$scope module lecture01_tb $end
$var reg 1 ! x $end
$var reg 1 " dir $end
$var reg 1 # en $end
$var reg 1 $ reset $end
$var reg 9 % o_slv_shift[8:0] $end
$scope module uut $end
$var reg 1 & i_sl_x $end
$var reg 1 ' i_sl_dir $end
$var reg 1 ( i_sl_en $end
$var reg 1 ) i_sl_reset $end
$var reg 9 * o_slv_shift[8:0] $end
$var reg 9 + shift_reg[8:0] $end
$var reg 9 , reset[8:0] $end
$upscope $end
$upscope $end
$enddefinitions $end
#0
0!
0"
0#
0$
b000000000 %
0&
0'
0(
0)
b000000000 *
b000000000 +
b000000000 ,
#5000000
1!
1&
#10000000
0!
1#
0&
1(
#15000000
1!
1&
b000000001 +
#20000000
0!
b000000001 %
0&
b000000001 *
#25000000
1!
1&
b000000010 +
#30000000
0!
1$
b000000010 %
0&
1)
b000000010 *
b000000000 +
#35000000
1!
0$
b000000000 %
1&
0)
b000000000 *
b000000001 +
#40000000
0!
b000000001 %
0&
b000000001 *
#45000000
1!
1&
b000000010 +
#50000000
0!
b000000010 %
0&
b000000010 *
#55000000
1!
1&
b000000011 +
#60000000
0!
1"
0#
b000000011 %
0&
1'
0(
b000000011 *
#65000000
1!
1$
1&
1)
b000000000 +
#70000000
0!
1#
0$
b000000000 %
0&
1(
0)
b000000000 *
#75000000
1!
1&
b111111111 +
#80000000
0!
b111111111 %
0&
b111111111 *
#85000000
1!
1&
b111111110 +
#90000000
0!
b111111110 %
0&
b111111110 *
#95000000
1!
1&
b111111101 +
#100000000
0!
1$
b111111101 %
0&
1)
b111111101 *
b000000000 +
#105000000
1!
0$
b000000000 %
1&
0)
b000000000 *
b111111111 +
#110000000
0!
b111111111 %
0&
b111111111 *
#115000000
1!
1&
b111111110 +
#120000000
0!
0"
0#
b111111110 %
0&
0'
0(
b111111110 *
#125000000
1!
1&
#130000000
0!
1#
0&
1(
#135000000
1!
1$
1&
1)
b000000000 +
#140000000
0!
0$
b000000000 %
0&
0)
b000000000 *
#145000000
1!
1&
b000000001 +
#150000000
0!
b000000001 %
0&
b000000001 *
#155000000
1!
1&
b000000010 +
#160000000
0!
b000000010 %
0&
b000000010 *
#165000000
1!
1&
b000000011 +
#170000000
0!
1$
b000000011 %
0&
1)
b000000011 *
b000000000 +
#175000000
1!
0$
b000000000 %
1&
0)
b000000000 *
b000000001 +
#180000000
0!
1"
0#
b000000001 %
0&
1'
0(
b000000001 *
#185000000
1!
1&
#190000000
0!
1#
0&
1(
#195000000
1!
1&
b000000000 +
#200000000
0!
b000000000 %
0&
b000000000 *
