FPGA/FPGA 03/skeleton3c/counter.m.vhd
---------------------------------------
-- lecture 01 simple gate
-- just forwarding the signal
----------------------------------------

library ieee;
use ieee.std_logic_1164.all;
use ieee.numeric_std.all;
----------------------------------------
entity counter is
generic(DATA_WIDTH : integer := 8);
port(	
	    i_sl_CLK : in  std_logic;
	    i_sl_dir : in std_logic;
	    i_sl_en : in std_logic;
	    i_sl_rst : in std_logic;
	    o_slv_counter : out std_logic_vector(data_width-1 downto 0)
);
end counter;  

----------------------------------------

architecture behaviour of counter is
	signal shift_reg : std_logic_vector(data_width-1 downto 0) := (others => '0');
	signal reset : std_logic_vector(data_width-1 downto 0) := (others =>'0');
begin

    process(i_sl_CLK)
    begin
        -- compare to truth table
	if rising_edge(i_sl_CLK) then
		if (i_sl_en = '1') then
		    if (i_sl_dir = '1') then
			shift_reg <= std_logic_vector(unsigned(shift_reg)-1);
		    else 
			shift_reg <= std_logic_vector(unsigned(shift_reg)+1);
		    end if;
		end if;
	end if;
	if (i_sl_rst = '1') then
	    shift_reg <= reset;
	end if;
	o_slv_counter <= shift_reg;

    end process;
end behaviour;

------------------------------------------

FPGA/FPGA 03/skeleton3c/pwm.m.vhd
---------------------------------------
-- lecture 02 shift register
-- just forwarding the signal
----------------------------------------

library ieee;
use ieee.std_logic_1164.all;
use ieee.numeric_std.all;

----------------------------------------

entity pwm is
    generic(
        DATA_WIDTH    :  integer := 8
    );
    port(   
        i_sl_CLK      :  in  std_logic;                                 -- clock
        i_slv_val     :  in  std_logic_vector(DATA_WIDTH-1 downto 0);   -- pwm value
        o_sl_pwm      :  out std_logic                                  -- pwm output
    );
end pwm;  

----------------------------------------

architecture behavior of pwm is
    COMPONENT counter is
        generic(
            DATA_WIDTH    :  integer := 8
        );
        port(   
            i_sl_CLK      :  in  std_logic;                      -- clock
            i_sl_en       :  in  std_logic;                      -- enable
            i_sl_dir      :  in  std_logic;                      -- direction
            i_sl_rst      :  in  std_logic;                                 -- reset
            o_slv_counter :  out std_logic_vector(DATA_WIDTH-1 downto 0)    -- counter
        );
    end COMPONENT;

    signal slv_pwm_cnt : std_logic_vector(DATA_WIDTH-1 downto 0) := (others => '0');

begin
    pwm_cnt: counter 
    GENERIC MAP(
        DATA_WIDTH => DATA_WIDTH
    )
    PORT MAP (
        i_sl_CLK    => i_sl_clk,
        i_sl_en     => '1',         -- assing constant values
        i_sl_dir    => '0',
        i_sl_rst    => '0',
        o_slv_counter => slv_pwm_cnt
    );


    process(i_sl_CLK)
    begin
        if rising_edge(i_sl_CLK) then
	    if unsigned(slv_pwm_cnt) >= unsigned(i_slv_val) then
                o_sl_pwm <= '0';
            else
                o_sl_pwm <= '1';
            end if;
        end if;
    end process;

end behavior;

------------------------------------------

FPGA/FPGA 03/skeleton3c/pwm.tb.vhd
library ieee;
use ieee.std_logic_1164.all;

ENTITY pwm_tb IS
END pwm_tb;

ARCHITECTURE tb OF pwm_tb IS 

    -- some constant values
    constant DATA_WIDTH : integer := 4;

    COMPONENT pwm is
        generic(
            DATA_WIDTH    :  integer := 8
        );
        port(   
            i_sl_CLK      :  in  std_logic;                      -- clock
            i_slv_val     :  in  std_logic_vector(DATA_WIDTH-1 downto 0);    -- pwm value
            o_sl_pwm      :  out std_logic                       -- output
        );
    end COMPONENT;

    -- "local" signals

    -- signals for UUT
    -- input 
    signal CLK    : std_logic := '0';

    signal i_slv_val : std_logic_vector(DATA_WIDTH-1 downto 0) := (others => '0');

    -- ouput
    signal o_sl_pwm : std_logic := '0';

BEGIN 
    -- Instance of unit under test.
    uut: pwm 
    GENERIC MAP(
        DATA_WIDTH  => DATA_WIDTH
    )
    PORT MAP (
        i_sl_CLK    => CLK,
        i_slv_val   => i_slv_val,
        o_sl_pwm    => o_sl_pwm
    );

-------------------------------------------------------------------------------
    -- test bench definition.
    tb_CLK :process
    begin
        CLK <= '0';
        wait for 1 ns;
        CLK <= '1';
        wait for 1 ns;
    end process;

    tb_rst: process
    begin
        wait for 300 ns;
        i_slv_val <= "0011";
        wait for 10 us;
    end process;

END;

FPGA/FPGA 03/skeleton3c/pwm.vcd
$date
  Thu Jan  7 23:28:30 2021
$end
$version
  GHDL v0
$end
$timescale
  1 fs
$end
$scope module standard $end
$upscope $end
$scope module textio $end
$upscope $end
$scope module std_logic_1164 $end
$upscope $end
$scope module numeric_std $end
$upscope $end
$scope module pwm_tb $end
$var reg 1 ! clk $end
$var reg 4 " i_slv_val[3:0] $end
$var reg 1 # o_sl_pwm $end
$scope module uut $end
$var reg 1 $ i_sl_clk $end
$var reg 4 % i_slv_val[3:0] $end
$var reg 1 & o_sl_pwm $end
$var reg 4 ' slv_pwm_cnt[3:0] $end
$scope module pwm_cnt $end
$var reg 1 ( i_sl_clk $end
$var reg 1 ) i_sl_dir $end
$var reg 1 * i_sl_en $end
$var reg 1 + i_sl_rst $end
$var reg 4 , o_slv_counter[3:0] $end
$var reg 4 - shift_reg[3:0] $end
$var reg 4 . reset[3:0] $end
$upscope $end
$upscope $end
$upscope $end
$enddefinitions $end
#0
0!
b0000 "
U#
0$
b0000 %
U&
b0000 '
0(
0)
1*
0+
b0000 ,
b0000 -
b0000 .
#1000000
1!
0#
1$
0&
1(
b0001 -
#2000000
0!
0$
b0001 '
0(
b0001 ,
#3000000
1!
1$
1(
b0010 -
#4000000
0!
0$
b0010 '
0(
b0010 ,
#5000000
1!
1$
1(
b0011 -
#6000000
0!
0$
b0011 '
0(
b0011 ,
#7000000
1!
1$
1(
b0100 -
#8000000
0!
0$
b0100 '
0(
b0100 ,
#9000000
1!
1$
1(
b0101 -
#10000000
0!
0$
b0101 '
0(
b0101 ,
#11000000
1!
1$
1(
b0110 -
#12000000
0!
0$
b0110 '
0(
b0110 ,
#13000000
1!
1$
1(
b0111 -
#14000000
0!
0$
b0111 '
0(
b0111 ,
#15000000
1!
1$
1(
b1000 -
#16000000
0!
0$
b1000 '
0(
b1000 ,
#17000000
1!
1$
1(
b1001 -
#18000000
0!
0$
b1001 '
0(
b1001 ,
#19000000
1!
1$
1(
b1010 -
#20000000
0!
0$
b1010 '
0(
b1010 ,
#21000000
1!
1$
1(
b1011 -
#22000000
0!
0$
b1011 '
0(
b1011 ,
#23000000
1!
1$
1(
b1100 -
#24000000
0!
0$
b1100 '
0(
b1100 ,
#25000000
1!
1$
1(
b1101 -
#26000000
0!
0$
b1101 '
0(
b1101 ,
#27000000
1!
1$
1(
b1110 -
#28000000
0!
0$
b1110 '
0(
b1110 ,
#29000000
1!
1$
1(
b1111 -
#30000000
0!
0$
b1111 '
0(
b1111 ,
#31000000
1!
1$
1(
b0000 -
#32000000
0!
0$
b0000 '
0(
b0000 ,
#33000000
1!
1$
1(
b0001 -
#34000000
0!
0$
b0001 '
0(
b0001 ,
#35000000
1!
1$
1(
b0010 -
#36000000
0!
0$
b0010 '
0(
b0010 ,
#37000000
1!
1$
1(
b0011 -
#38000000
0!
0$
b0011 '
0(
b0011 ,
#39000000
1!
1$
1(
b0100 -
#40000000
0!
0$
b0100 '
0(
b0100 ,
#41000000
1!
1$
1(
b0101 -
#42000000
0!
0$
b0101 '
0(
b0101 ,
#43000000
1!
1$
1(
b0110 -
#44000000
0!
0$
b0110 '
0(
b0110 ,
#45000000
1!
1$
1(
b0111 -
#46000000
0!
0$
b0111 '
0(
b0111 ,
#47000000
1!
1$
1(
b1000 -
#48000000
0!
0$
b1000 '
0(
b1000 ,
#49000000
1!
1$
1(
b1001 -
#50000000
0!
0$
b1001 '
0(
b1001 ,
#51000000
1!
1$
1(
b1010 -
#52000000
0!
0$
b1010 '
0(
b1010 ,
#53000000
1!
1$
1(
b1011 -
#54000000
0!
0$
b1011 '
0(
b1011 ,
#55000000
1!
1$
1(
b1100 -
#56000000
0!
0$
b1100 '
0(
b1100 ,
#57000000
1!
1$
1(
b1101 -
#58000000
0!
0$
b1101 '
0(
b1101 ,
#59000000
1!
1$
1(
b1110 -
#60000000
0!
0$
b1110 '
0(
b1110 ,
#61000000
1!
1$
1(
b1111 -
#62000000
0!
0$
b1111 '
0(
b1111 ,
#63000000
1!
1$
1(
b0000 -
#64000000
0!
0$
b0000 '
0(
b0000 ,
#65000000
1!
1$
1(
b0001 -
#66000000
0!
0$
b0001 '
0(
b0001 ,
#67000000
1!
1$
1(
b0010 -
#68000000
0!
0$
b0010 '
0(
b0010 ,
#69000000
1!
1$
1(
b0011 -
#70000000
0!
0$
b0011 '
0(
b0011 ,
#71000000
1!
1$
1(
b0100 -
#72000000
0!
0$
b0100 '
0(
b0100 ,
#73000000
1!
1$
1(
b0101 -
#74000000
0!
0$
b0101 '
0(
b0101 ,
#75000000
1!
1$
1(
b0110 -
#76000000
0!
0$
b0110 '
0(
b0110 ,
#77000000
1!
1$
1(
b0111 -
#78000000
0!
0$
b0111 '
0(
b0111 ,
#79000000
1!
1$
1(
b1000 -
#80000000
0!
0$
b1000 '
0(
b1000 ,
#81000000
1!
1$
1(
b1001 -
#82000000
0!
0$
b1001 '
0(
b1001 ,
#83000000
1!
1$
1(
b1010 -
#84000000
0!
0$
b1010 '
0(
b1010 ,
#85000000
1!
1$
1(
b1011 -
#86000000
0!
0$
b1011 '
0(
b1011 ,
#87000000
1!
1$
1(
b1100 -
#88000000
0!
0$
b1100 '
0(
b1100 ,
#89000000
1!
1$
1(
b1101 -
#90000000
0!
0$
b1101 '
0(
b1101 ,
#91000000
1!
1$
1(
b1110 -
#92000000
0!
0$
b1110 '
0(
b1110 ,
#93000000
1!
1$
1(
b1111 -
#94000000
0!
0$
b1111 '
0(
b1111 ,
#95000000
1!
1$
1(
b0000 -
#96000000
0!
0$
b0000 '
0(
b0000 ,
#97000000
1!
1$
1(
b0001 -
#98000000
0!
0$
b0001 '
0(
b0001 ,
#99000000
1!
1$
1(
b0010 -
#100000000
0!
0$
b0010 '
0(
b0010 ,
#101000000
1!
1$
1(
b0011 -
#102000000
0!
0$
b0011 '
0(
b0011 ,
#103000000
1!
1$
1(
b0100 -
#104000000
0!
0$
b0100 '
0(
b0100 ,
#105000000
1!
1$
1(
b0101 -
#106000000
0!
0$
b0101 '
0(
b0101 ,
#107000000
1!
1$
1(
b0110 -
#108000000
0!
0$
b0110 '
0(
b0110 ,
#109000000
1!
1$
1(
b0111 -
#110000000
0!
0$
b0111 '
0(
b0111 ,
#111000000
1!
1$
1(
b1000 -
#112000000
0!
0$
b1000 '
0(
b1000 ,
#113000000
1!
1$
1(
b1001 -
#114000000
0!
0$
b1001 '
0(
b1001 ,
#115000000
1!
1$
1(
b1010 -
#116000000
0!
0$
b1010 '
0(
b1010 ,
#117000000
1!
1$
1(
b1011 -
#118000000
0!
0$
b1011 '
0(
b1011 ,
#119000000
1!
1$
1(
b1100 -
#120000000
0!
0$
b1100 '
0(
b1100 ,
#121000000
1!
1$
1(
b1101 -
#122000000
0!
0$
b1101 '
0(
b1101 ,
#123000000
1!
1$
1(
b1110 -
#124000000
0!
0$
b1110 '
0(
b1110 ,
#125000000
1!
1$
1(
b1111 -
#126000000
0!
0$
b1111 '
0(
b1111 ,
#127000000
1!
1$
1(
b0000 -
#128000000
0!
0$
b0000 '
0(
b0000 ,
#129000000
1!
1$
1(
b0001 -
#130000000
0!
0$
b0001 '
0(
b0001 ,
#131000000
1!
1$
1(
b0010 -
#132000000
0!
0$
b0010 '
0(
b0010 ,
#133000000
1!
1$
1(
b0011 -
#134000000
0!
0$
b0011 '
0(
b0011 ,
#135000000
1!
1$
1(
b0100 -
#136000000
0!
0$
b0100 '
0(
b0100 ,
#137000000
1!
1$
1(
b0101 -
#138000000
0!
0$
b0101 '
0(
b0101 ,
#139000000
1!
1$
1(
b0110 -
#140000000
0!
0$
b0110 '
0(
b0110 ,
#141000000
1!
1$
1(
b0111 -
#142000000
0!
0$
b0111 '
0(
b0111 ,
#143000000
1!
1$
1(
b1000 -
#144000000
0!
0$
b1000 '
0(
b1000 ,
#145000000
1!
1$
1(
b1001 -
#146000000
0!
0$
b1001 '
0(
b1001 ,
#147000000
1!
1$
1(
b1010 -
#148000000
0!
0$
b1010 '
0(
b1010 ,
#149000000
1!
1$
1(
b1011 -
#150000000
0!
0$
b1011 '
0(
b1011 ,
#151000000
1!
1$
1(
b1100 -
#152000000
0!
0$
b1100 '
0(
b1100 ,
#153000000
1!
1$
1(
b1101 -
#154000000
0!
0$
b1101 '
0(
b1101 ,
#155000000
1!
1$
1(
b1110 -
#156000000
0!
0$
b1110 '
0(
b1110 ,
#157000000
1!
1$
1(
b1111 -
#158000000
0!
0$
b1111 '
0(
b1111 ,
#159000000
1!
1$
1(
b0000 -
#160000000
0!
0$
b0000 '
0(
b0000 ,
#161000000
1!
1$
1(
b0001 -
#162000000
0!
0$
b0001 '
0(
b0001 ,
#163000000
1!
1$
1(
b0010 -
#164000000
0!
0$
b0010 '
0(
b0010 ,
#165000000
1!
1$
1(
b0011 -
#166000000
0!
0$
b0011 '
0(
b0011 ,
#167000000
1!
1$
1(
b0100 -
#168000000
0!
0$
b0100 '
0(
b0100 ,
#169000000
1!
1$
1(
b0101 -
#170000000
0!
0$
b0101 '
0(
b0101 ,
#171000000
1!
1$
1(
b0110 -
#172000000
0!
0$
b0110 '
0(
b0110 ,
#173000000
1!
1$
1(
b0111 -
#174000000
0!
0$
b0111 '
0(
b0111 ,
#175000000
1!
1$
1(
b1000 -
#176000000
0!
0$
b1000 '
0(
b1000 ,
#177000000
1!
1$
1(
b1001 -
#178000000
0!
0$
b1001 '
0(
b1001 ,
#179000000
1!
1$
1(
b1010 -
#180000000
0!
0$
b1010 '
0(
b1010 ,
#181000000
1!
1$
1(
b1011 -
#182000000
0!
0$
b1011 '
0(
b1011 ,
#183000000
1!
1$
1(
b1100 -
#184000000
0!
0$
b1100 '
0(
b1100 ,
#185000000
1!
1$
1(
b1101 -
#186000000
0!
0$
b1101 '
0(
b1101 ,
#187000000
1!
1$
1(
b1110 -
#188000000
0!
0$
b1110 '
0(
b1110 ,
#189000000
1!
1$
1(
b1111 -
#190000000
0!
0$
b1111 '
0(
b1111 ,
#191000000
1!
1$
1(
b0000 -
#192000000
0!
0$
b0000 '
0(
b0000 ,
#193000000
1!
1$
1(
b0001 -
#194000000
0!
0$
b0001 '
0(
b0001 ,
#195000000
1!
1$
1(
b0010 -
#196000000
0!
0$
b0010 '
0(
b0010 ,
#197000000
1!
1$
1(
b0011 -
#198000000
0!
0$
b0011 '
0(
b0011 ,
#199000000
1!
1$
1(
b0100 -
#200000000
0!
0$
b0100 '
0(
b0100 ,
#201000000
1!
1$
1(
b0101 -
#202000000
0!
0$
b0101 '
0(
b0101 ,
#203000000
1!
1$
1(
b0110 -
#204000000
0!
0$
b0110 '
0(
b0110 ,
#205000000
1!
1$
1(
b0111 -
#206000000
0!
0$
b0111 '
0(
b0111 ,
#207000000
1!
1$
1(
b1000 -
#208000000
0!
0$
b1000 '
0(
b1000 ,
#209000000
1!
1$
1(
b1001 -
#210000000
0!
0$
b1001 '
0(
b1001 ,
#211000000
1!
1$
1(
b1010 -
#212000000
0!
0$
b1010 '
0(
b1010 ,
#213000000
1!
1$
1(
b1011 -
#214000000
0!
0$
b1011 '
0(
b1011 ,
#215000000
1!
1$
1(
b1100 -
#216000000
0!
0$
b1100 '
0(
b1100 ,
#217000000
1!
1$
1(
b1101 -
#218000000
0!
0$
b1101 '
0(
b1101 ,
#219000000
1!
1$
1(
b1110 -
#220000000
0!
0$
b1110 '
0(
b1110 ,
#221000000
1!
1$
1(
b1111 -
#222000000
0!
0$
b1111 '
0(
b1111 ,
#223000000
1!
1$
1(
b0000 -
#224000000
0!
0$
b0000 '
0(
b0000 ,
#225000000
1!
1$
1(
b0001 -
#226000000
0!
0$
b0001 '
0(
b0001 ,
#227000000
1!
1$
1(
b0010 -
#228000000
0!
0$
b0010 '
0(
b0010 ,
#229000000
1!
1$
1(
b0011 -
#230000000
0!
0$
b0011 '
0(
b0011 ,
#231000000
1!
1$
1(
b0100 -
#232000000
0!
0$
b0100 '
0(
b0100 ,
#233000000
1!
1$
1(
b0101 -
#234000000
0!
0$
b0101 '
0(
b0101 ,
#235000000
1!
1$
1(
b0110 -
#236000000
0!
0$
b0110 '
0(
b0110 ,
#237000000
1!
1$
1(
b0111 -
#238000000
0!
0$
b0111 '
0(
b0111 ,
#239000000
1!
1$
1(
b1000 -
#240000000
0!
0$
b1000 '
0(
b1000 ,
#241000000
1!
1$
1(
b1001 -
#242000000
0!
0$
b1001 '
0(
b1001 ,
#243000000
1!
1$
1(
b1010 -
#244000000
0!
0$
b1010 '
0(
b1010 ,
#245000000
1!
1$
1(
b1011 -
#246000000
0!
0$
b1011 '
0(
b1011 ,
#247000000
1!
1$
1(
b1100 -
#248000000
0!
0$
b1100 '
0(
b1100 ,
#249000000
1!
1$
1(
b1101 -
#250000000
0!
0$
b1101 '
0(
b1101 ,
#251000000
1!
1$
1(
b1110 -
#252000000
0!
0$
b1110 '
0(
b1110 ,
#253000000
1!
1$
1(
b1111 -
#254000000
0!
0$
b1111 '
0(
b1111 ,
#255000000
1!
1$
1(
b0000 -
#256000000
0!
0$
b0000 '
0(
b0000 ,
#257000000
1!
1$
1(
b0001 -
#258000000
0!
0$
b0001 '
0(
b0001 ,
#259000000
1!
1$
1(
b0010 -
#260000000
0!
0$
b0010 '
0(
b0010 ,
#261000000
1!
1$
1(
b0011 -
#262000000
0!
0$
b0011 '
0(
b0011 ,
#263000000
1!
1$
1(
b0100 -
#264000000
0!
0$
b0100 '
0(
b0100 ,
#265000000
1!
1$
1(
b0101 -
#266000000
0!
0$
b0101 '
0(
b0101 ,
#267000000
1!
1$
1(
b0110 -
#268000000
0!
0$
b0110 '
0(
b0110 ,
#269000000
1!
1$
1(
b0111 -
#270000000
0!
0$
b0111 '
0(
b0111 ,
#271000000
1!
1$
1(
b1000 -
#272000000
0!
0$
b1000 '
0(
b1000 ,
#273000000
1!
1$
1(
b1001 -
#274000000
0!
0$
b1001 '
0(
b1001 ,
#275000000
1!
1$
1(
b1010 -
#276000000
0!
0$
b1010 '
0(
b1010 ,
#277000000
1!
1$
1(
b1011 -
#278000000
0!
0$
b1011 '
0(
b1011 ,
#279000000
1!
1$
1(
b1100 -
#280000000
0!
0$
b1100 '
0(
b1100 ,
#281000000
1!
1$
1(
b1101 -
#282000000
0!
0$
b1101 '
0(
b1101 ,
#283000000
1!
1$
1(
b1110 -
#284000000
0!
0$
b1110 '
0(
b1110 ,
#285000000
1!
1$
1(
b1111 -
#286000000
0!
0$
b1111 '
0(
b1111 ,
#287000000
1!
1$
1(
b0000 -
#288000000
0!
0$
b0000 '
0(
b0000 ,
#289000000
1!
1$
1(
b0001 -
#290000000
0!
0$
b0001 '
0(
b0001 ,
#291000000
1!
1$
1(
b0010 -
#292000000
0!
0$
b0010 '
0(
b0010 ,
#293000000
1!
1$
1(
b0011 -
#294000000
0!
0$
b0011 '
0(
b0011 ,
#295000000
1!
1$
1(
b0100 -
#296000000
0!
0$
b0100 '
0(
b0100 ,
#297000000
1!
1$
1(
b0101 -
#298000000
0!
0$
b0101 '
0(
b0101 ,
#299000000
1!
1$
1(
b0110 -
#300000000
0!
b0011 "
0$
b0011 %
b0110 '
0(
b0110 ,
#301000000
1!
1$
1(
b0111 -
#302000000
0!
0$
b0111 '
0(
b0111 ,
#303000000
1!
1$
1(
b1000 -
#304000000
0!
0$
b1000 '
0(
b1000 ,
#305000000
1!
1$
1(
b1001 -
#306000000
0!
0$
b1001 '
0(
b1001 ,
#307000000
1!
1$
1(
b1010 -
#308000000
0!
0$
b1010 '
0(
b1010 ,
#309000000
1!
1$
1(
b1011 -
#310000000
0!
0$
b1011 '
0(
b1011 ,
#311000000
1!
1$
1(
b1100 -
#312000000
0!
0$
b1100 '
0(
b1100 ,
#313000000
1!
1$
1(
b1101 -
#314000000
0!
0$
b1101 '
0(
b1101 ,
#315000000
1!
1$
1(
b1110 -
#316000000
0!
0$
b1110 '
0(
b1110 ,
#317000000
1!
1$
1(
b1111 -
#318000000
0!
0$
b1111 '
0(
b1111 ,
#319000000
1!
1$
1(
b0000 -
#320000000
0!
0$
b0000 '
0(
b0000 ,
#321000000
1!
1#
1$
1&
1(
b0001 -
#322000000
0!
0$
b0001 '
0(
b0001 ,
#323000000
1!
1$
1(
b0010 -
#324000000
0!
0$
b0010 '
0(
b0010 ,
#325000000
1!
1$
1(
b0011 -
#326000000
0!
0$
b0011 '
0(
b0011 ,
#327000000
1!
0#
1$
0&
1(
b0100 -
#328000000
0!
0$
b0100 '
0(
b0100 ,
#329000000
1!
1$
1(
b0101 -
#330000000
0!
0$
b0101 '
0(
b0101 ,
#331000000
1!
1$
1(
b0110 -
#332000000
0!
0$
b0110 '
0(
b0110 ,
#333000000
1!
1$
1(
b0111 -
#334000000
0!
0$
b0111 '
0(
b0111 ,
#335000000
1!
1$
1(
b1000 -
#336000000
0!
0$
b1000 '
0(
b1000 ,
#337000000
1!
1$
1(
b1001 -
#338000000
0!
0$
b1001 '
0(
b1001 ,
#339000000
1!
1$
1(
b1010 -
#340000000
0!
0$
b1010 '
0(
b1010 ,
#341000000
1!
1$
1(
b1011 -
#342000000
0!
0$
b1011 '
0(
b1011 ,
#343000000
1!
1$
1(
b1100 -
#344000000
0!
0$
b1100 '
0(
b1100 ,
#345000000
1!
1$
1(
b1101 -
#346000000
0!
0$
b1101 '
0(
b1101 ,
#347000000
1!
1$
1(
b1110 -
#348000000
0!
0$
b1110 '
0(
b1110 ,
#349000000
1!
1$
1(
b1111 -
#350000000
0!
0$
b1111 '
0(
b1111 ,
#351000000
1!
1$
1(
b0000 -
#352000000
0!
0$
b0000 '
0(
b0000 ,
#353000000
1!
1#
1$
1&
1(
b0001 -
#354000000
0!
0$
b0001 '
0(
b0001 ,
#355000000
1!
1$
1(
b0010 -
#356000000
0!
0$
b0010 '
0(
b0010 ,
#357000000
1!
1$
1(
b0011 -
#358000000
0!
0$
b0011 '
0(
b0011 ,
#359000000
1!
0#
1$
0&
1(
b0100 -
#360000000
0!
0$
b0100 '
0(
b0100 ,
#361000000
1!
1$
1(
b0101 -
#362000000
0!
0$
b0101 '
0(
b0101 ,
#363000000
1!
1$
1(
b0110 -
#364000000
0!
0$
b0110 '
0(
b0110 ,
#365000000
1!
1$
1(
b0111 -
#366000000
0!
0$
b0111 '
0(
b0111 ,
#367000000
1!
1$
1(
b1000 -
#368000000
0!
0$
b1000 '
0(
b1000 ,
#369000000
1!
1$
1(
b1001 -
#370000000
0!
0$
b1001 '
0(
b1001 ,
#371000000
1!
1$
1(
b1010 -
#372000000
0!
0$
b1010 '
0(
b1010 ,
#373000000
1!
1$
1(
b1011 -
#374000000
0!
0$
b1011 '
0(
b1011 ,
#375000000
1!
1$
1(
b1100 -
#376000000
0!
0$
b1100 '
0(
b1100 ,
#377000000
1!
1$
1(
b1101 -
#378000000
0!
0$
b1101 '
0(
b1101 ,
#379000000
1!
1$
1(
b1110 -
#380000000
0!
0$
b1110 '
0(
b1110 ,
#381000000
1!
1$
1(
b1111 -
#382000000
0!
0$
b1111 '
0(
b1111 ,
#383000000
1!
1$
1(
b0000 -
#384000000
0!
0$
b0000 '
0(
b0000 ,
#385000000
1!
1#
1$
1&
1(
b0001 -
#386000000
0!
0$
b0001 '
0(
b0001 ,
#387000000
1!
1$
1(
b0010 -
#388000000
0!
0$
b0010 '
0(
b0010 ,
#389000000
1!
1$
1(
b0011 -
#390000000
0!
0$
b0011 '
0(
b0011 ,
#391000000
1!
0#
1$
0&
1(
b0100 -
#392000000
0!
0$
b0100 '
0(
b0100 ,
#393000000
1!
1$
1(
b0101 -
#394000000
0!
0$
b0101 '
0(
b0101 ,
#395000000
1!
1$
1(
b0110 -
#396000000
0!
0$
b0110 '
0(
b0110 ,
#397000000
1!
1$
1(
b0111 -
#398000000
0!
0$
b0111 '
0(
b0111 ,
#399000000
1!
1$
1(
b1000 -
#400000000
0!
0$
b1000 '
0(
b1000 ,
#401000000
1!
1$
1(
b1001 -
#402000000
0!
0$
b1001 '
0(
b1001 ,
#403000000
1!
1$
1(
b1010 -
#404000000
0!
0$
b1010 '
0(
b1010 ,
#405000000
1!
1$
1(
b1011 -
#406000000
0!
0$
b1011 '
0(
b1011 ,
#407000000
1!
1$
1(
b1100 -
#408000000
0!
0$
b1100 '
0(
b1100 ,
#409000000
1!
1$
1(
b1101 -
#410000000
0!
0$
b1101 '
0(
b1101 ,
#411000000
1!
1$
1(
b1110 -
#412000000
0!
0$
b1110 '
0(
b1110 ,
#413000000
1!
1$
1(
b1111 -
#414000000
0!
0$
b1111 '
0(
b1111 ,
#415000000
1!
1$
1(
b0000 -
#416000000
0!
0$
b0000 '
0(
b0000 ,
#417000000
1!
1#
1$
1&
1(
b0001 -
#418000000
0!
0$
b0001 '
0(
b0001 ,
#419000000
1!
1$
1(
b0010 -
#420000000
0!
0$
b0010 '
0(
b0010 ,
#421000000
1!
1$
1(
b0011 -
#422000000
0!
0$
b0011 '
0(
b0011 ,
#423000000
1!
0#
1$
0&
1(
b0100 -
#424000000
0!
0$
b0100 '
0(
b0100 ,
#425000000
1!
1$
1(
b0101 -
#426000000
0!
0$
b0101 '
0(
b0101 ,
#427000000
1!
1$
1(
b0110 -
#428000000
0!
0$
b0110 '
0(
b0110 ,
#429000000
1!
1$
1(
b0111 -
#430000000
0!
0$
b0111 '
0(
b0111 ,
#431000000
1!
1$
1(
b1000 -
#432000000
0!
0$
b1000 '
0(
b1000 ,
#433000000
1!
1$
1(
b1001 -
#434000000
0!
0$
b1001 '
0(
b1001 ,
#435000000
1!
1$
1(
b1010 -
#436000000
0!
0$
b1010 '
0(
b1010 ,
#437000000
1!
1$
1(
b1011 -
#438000000
0!
0$
b1011 '
0(
b1011 ,
#439000000
1!
1$
1(
b1100 -
#440000000
0!
0$
b1100 '
0(
b1100 ,
#441000000
1!
1$
1(
b1101 -
#442000000
0!
0$
b1101 '
0(
b1101 ,
#443000000
1!
1$
1(
b1110 -
#444000000
0!
0$
b1110 '
0(
b1110 ,
#445000000
1!
1$
1(
b1111 -
#446000000
0!
0$
b1111 '
0(
b1111 ,
#447000000
1!
1$
1(
b0000 -
#448000000
0!
0$
b0000 '
0(
b0000 ,
#449000000
1!
1#
1$
1&
1(
b0001 -
#450000000
0!
0$
b0001 '
0(
b0001 ,
#451000000
1!
1$
1(
b0010 -
#452000000
0!
0$
b0010 '
0(
b0010 ,
#453000000
1!
1$
1(
b0011 -
#454000000
0!
0$
b0011 '
0(
b0011 ,
#455000000
1!
0#
1$
0&
1(
b0100 -
#456000000
0!
0$
b0100 '
0(
b0100 ,
#457000000
1!
1$
1(
b0101 -
#458000000
0!
0$
b0101 '
0(
b0101 ,
#459000000
1!
1$
1(
b0110 -
#460000000
0!
0$
b0110 '
0(
b0110 ,
#461000000
1!
1$
1(
b0111 -
#462000000
0!
0$
b0111 '
0(
b0111 ,
#463000000
1!
1$
1(
b1000 -
#464000000
0!
0$
b1000 '
0(
b1000 ,
#465000000
1!
1$
1(
b1001 -
#466000000
0!
0$
b1001 '
0(
b1001 ,
#467000000
1!
1$
1(
b1010 -
#468000000
0!
0$
b1010 '
0(
b1010 ,
#469000000
1!
1$
1(
b1011 -
#470000000
0!
0$
b1011 '
0(
b1011 ,
#471000000
1!
1$
1(
b1100 -
#472000000
0!
0$
b1100 '
0(
b1100 ,
#473000000
1!
1$
1(
b1101 -
#474000000
0!
0$
b1101 '
0(
b1101 ,
#475000000
1!
1$
1(
b1110 -
#476000000
0!
0$
b1110 '
0(
b1110 ,
#477000000
1!
1$
1(
b1111 -
#478000000
0!
0$
b1111 '
0(
b1111 ,
#479000000
1!
1$
1(
b0000 -
#480000000
0!
0$
b0000 '
0(
b0000 ,
#481000000
1!
1#
1$
1&
1(
b0001 -
#482000000
0!
0$
b0001 '
0(
b0001 ,
#483000000
1!
1$
1(
b0010 -
#484000000
0!
0$
b0010 '
0(
b0010 ,
#485000000
1!
1$
1(
b0011 -
#486000000
0!
0$
b0011 '
0(
b0011 ,
#487000000
1!
0#
1$
0&
1(
b0100 -
#488000000
0!
0$
b0100 '
0(
b0100 ,
#489000000
1!
1$
1(
b0101 -
#490000000
0!
0$
b0101 '
0(
b0101 ,
#491000000
1!
1$
1(
b0110 -
#492000000
0!
0$
b0110 '
0(
b0110 ,
#493000000
1!
1$
1(
b0111 -
#494000000
0!
0$
b0111 '
0(
b0111 ,
#495000000
1!
1$
1(
b1000 -
#496000000
0!
0$
b1000 '
0(
b1000 ,
#497000000
1!
1$
1(
b1001 -
#498000000
0!
0$
b1001 '
0(
b1001 ,
#499000000
1!
1$
1(
b1010 -
#500000000
0!
0$
b1010 '
0(
b1010 ,
#501000000
1!
1$
1(
b1011 -
#502000000
0!
0$
b1011 '
0(
b1011 ,
#503000000
1!
1$
1(
b1100 -
#504000000
0!
0$
b1100 '
0(
b1100 ,
#505000000
1!
1$
1(
b1101 -
#506000000
0!
0$
b1101 '
0(
b1101 ,
#507000000
1!
1$
1(
b1110 -
#508000000
0!
0$
b1110 '
0(
b1110 ,
#509000000
1!
1$
1(
b1111 -
#510000000
0!
0$
b1111 '
0(
b1111 ,
#511000000
1!
1$
1(
b0000 -
#512000000
0!
0$
b0000 '
0(
b0000 ,
#513000000
1!
1#
1$
1&
1(
b0001 -
#514000000
0!
0$
b0001 '
0(
b0001 ,
#515000000
1!
1$
1(
b0010 -
#516000000
0!
0$
b0010 '
0(
b0010 ,
#517000000
1!
1$
1(
b0011 -
#518000000
0!
0$
b0011 '
0(
b0011 ,
#519000000
1!
0#
1$
0&
1(
b0100 -
#520000000
0!
0$
b0100 '
0(
b0100 ,
#521000000
1!
1$
1(
b0101 -
#522000000
0!
0$
b0101 '
0(
b0101 ,
#523000000
1!
1$
1(
b0110 -
