FPGA/FPGA 05/Exercise_5/pwm.m.vhd
---------------------------------------
-- lecture 02 shift register
-- just forwarding the signal
----------------------------------------

library ieee;
use ieee.std_logic_1164.all;
use ieee.numeric_std.all;
use ieee.MATH_REAL.all;

----------------------------------------

entity pwm is

    port(   
        i_sl_CLK      :  in  std_logic;                                 -- clock
	o_sl_number   :  out std_logic_vector(7 downto 0);
	o_sl_twelve     :  out std_logic_vector(11 downto 0)
    );
end pwm;  

----------------------------------------

architecture behavior of pwm is



signal slv_pwm_number : std_logic_vector(7 downto 0) := "00000000";


begin
    process(i_sl_CLK)
	variable slv_pwm_ones : unsigned(3 downto 0) := (others => '0');
	variable slv_pwm_tens : unsigned(3 downto 0) := (others => '0');
	variable slv_pwm_huns : unsigned(3 downto 0) := (others => '0');
    begin
	if rising_edge(i_sl_CLK) then
		slv_pwm_number <= std_logic_vector(unsigned(slv_pwm_number)+1);
	end if;
	slv_pwm_ones := (others => '0');
	slv_pwm_tens := (others => '0');
	slv_pwm_huns := (others => '0');
	for i in 7 downto 0 loop
		if (slv_pwm_ones >= 5) then
			slv_pwm_ones := slv_pwm_ones + 3;
		end if;
		if (slv_pwm_tens >= 5) then
			slv_pwm_tens := slv_pwm_tens + 3;
		end if;
		if (slv_pwm_huns >= 5) then
			slv_pwm_huns := slv_pwm_huns + 3;
		end if;
		
		slv_pwm_huns := slv_pwm_huns(2 downto 0) & slv_pwm_tens(3);
		slv_pwm_tens := slv_pwm_tens(2 downto 0) & slv_pwm_ones(3);
		slv_pwm_ones := slv_pwm_ones(2 downto 0) & slv_pwm_number(i);

	
		
	end loop;

	o_sl_number <= slv_pwm_number;
	o_sl_twelve <= std_logic_vector(slv_pwm_huns) & std_logic_vector(slv_pwm_tens) & std_logic_vector(slv_pwm_ones);
	
    end process;

end behavior;

------------------------------------------

FPGA/FPGA 05/Exercise_5/pwm.tb.vhd
library ieee;
use ieee.std_logic_1164.all;

ENTITY pwm_tb IS
END pwm_tb;

ARCHITECTURE tb OF pwm_tb IS 

    COMPONENT pwm is

        port(   
            i_sl_CLK      :  in  std_logic;                      -- clock
	    o_sl_number   :  out std_logic_vector(7 downto 0);
	    o_sl_twelve     :  out std_logic_vector(11 downto 0)
        );
    end COMPONENT;

    -- "local" signals
    -- signals for UUT
    -- input 
    signal CLK    : std_logic := '0';

    -- ouput
    signal o_sl_number : std_logic_vector(7 downto 0) := "00000000";
    signal o_sl_twelve   : std_logic_vector(11 downto 0) := "000000000000";


BEGIN 
    -- Instance of unit under test.
    uut: pwm 
    PORT MAP (
        i_sl_CLK    => CLK,
	o_sl_number => o_sl_number,
	o_sl_twelve   => o_sl_twelve

    );

-------------------------------------------------------------------------------
    -- test bench definition.
    tb_CLK :process
    begin
        CLK <= '0';
        wait for 3 ns;
        CLK <= '1';
        wait for 3 ns;
    end process;




END;

FPGA/FPGA 05/Exercise_5/pwm.vcd
$date
  Wed Dec  9 13:56:07 2020
$end
$version
  GHDL v0
$end
$timescale
  1 fs
$end
$scope module standard $end
$upscope $end
$scope module textio $end
$upscope $end
$scope module std_logic_1164 $end
$upscope $end
$scope module numeric_std $end
$upscope $end
$scope module math_real $end
$upscope $end
$scope module pwm_tb $end
$var reg 1 ! clk $end
$var reg 8 " o_sl_number[7:0] $end
$var reg 12 # o_sl_twelve[11:0] $end
$scope module uut $end
$var reg 1 $ i_sl_clk $end
$var reg 8 % o_sl_number[7:0] $end
$var reg 12 & o_sl_twelve[11:0] $end
$var reg 8 ' slv_pwm_number[7:0] $end
$upscope $end
$upscope $end
$enddefinitions $end
#0
0!
b00000000 "
b000000000000 #
0$
b00000000 %
b000000000000 &
b00000000 '
#3000000
1!
1$
b00000001 '
#6000000
0!
b00000001 "
b000000000001 #
0$
b00000001 %
b000000000001 &
#9000000
1!
1$
b00000010 '
#12000000
0!
b00000010 "
b000000000010 #
0$
b00000010 %
b000000000010 &
#15000000
1!
1$
b00000011 '
#18000000
0!
b00000011 "
b000000000011 #
0$
b00000011 %
b000000000011 &
#21000000
1!
1$
b00000100 '
#24000000
0!
b00000100 "
b000000000100 #
0$
b00000100 %
b000000000100 &
#27000000
1!
1$
b00000101 '
#30000000
0!
b00000101 "
b000000000101 #
0$
b00000101 %
b000000000101 &
#33000000
1!
1$
b00000110 '
#36000000
0!
b00000110 "
b000000000110 #
0$
b00000110 %
b000000000110 &
#39000000
1!
1$
b00000111 '
#42000000
0!
b00000111 "
b000000000111 #
0$
b00000111 %
b000000000111 &
#45000000
1!
1$
b00001000 '
#48000000
0!
b00001000 "
b000000001000 #
0$
b00001000 %
b000000001000 &
#51000000
1!
1$
b00001001 '
#54000000
0!
b00001001 "
b000000001001 #
0$
b00001001 %
b000000001001 &
#57000000
1!
1$
b00001010 '
#60000000
0!
b00001010 "
b000000010000 #
0$
b00001010 %
b000000010000 &
#63000000
1!
1$
b00001011 '
#66000000
0!
b00001011 "
b000000010001 #
0$
b00001011 %
b000000010001 &
#69000000
1!
1$
b00001100 '
#72000000
0!
b00001100 "
b000000010010 #
0$
b00001100 %
b000000010010 &
#75000000
1!
1$
b00001101 '
#78000000
0!
b00001101 "
b000000010011 #
0$
b00001101 %
b000000010011 &
#81000000
1!
1$
b00001110 '
#84000000
0!
b00001110 "
b000000010100 #
0$
b00001110 %
b000000010100 &
#87000000
1!
1$
b00001111 '
#90000000
0!
b00001111 "
b000000010101 #
0$
b00001111 %
b000000010101 &
#93000000
1!
1$
b00010000 '
#96000000
0!
b00010000 "
b000000010110 #
0$
b00010000 %
b000000010110 &
#99000000
1!
1$
b00010001 '
#102000000
0!
b00010001 "
b000000010111 #
0$
b00010001 %
b000000010111 &
#105000000
1!
1$
b00010010 '
#108000000
0!
b00010010 "
b000000011000 #
0$
b00010010 %
b000000011000 &
#111000000
1!
1$
b00010011 '
#114000000
0!
b00010011 "
b000000011001 #
0$
b00010011 %
b000000011001 &
#117000000
1!
1$
b00010100 '
#120000000
0!
b00010100 "
b000000100000 #
0$
b00010100 %
b000000100000 &
#123000000
1!
1$
b00010101 '
#126000000
0!
b00010101 "
b000000100001 #
0$
b00010101 %
b000000100001 &
#129000000
1!
1$
b00010110 '
#132000000
0!
b00010110 "
b000000100010 #
0$
b00010110 %
b000000100010 &
#135000000
1!
1$
b00010111 '
#138000000
0!
b00010111 "
b000000100011 #
0$
b00010111 %
b000000100011 &
#141000000
1!
1$
b00011000 '
#144000000
0!
b00011000 "
b000000100100 #
0$
b00011000 %
b000000100100 &
#147000000
1!
1$
b00011001 '
#150000000
0!
b00011001 "
b000000100101 #
0$
b00011001 %
b000000100101 &
#153000000
1!
1$
b00011010 '
#156000000
0!
b00011010 "
b000000100110 #
0$
b00011010 %
b000000100110 &
#159000000
1!
1$
b00011011 '
#162000000
0!
b00011011 "
b000000100111 #
0$
b00011011 %
b000000100111 &
#165000000
1!
1$
b00011100 '
#168000000
0!
b00011100 "
b000000101000 #
0$
b00011100 %
b000000101000 &
#171000000
1!
1$
b00011101 '
#174000000
0!
b00011101 "
b000000101001 #
0$
b00011101 %
b000000101001 &
#177000000
1!
1$
b00011110 '
#180000000
0!
b00011110 "
b000000110000 #
0$
b00011110 %
b000000110000 &
#183000000
1!
1$
b00011111 '
#186000000
0!
b00011111 "
b000000110001 #
0$
b00011111 %
b000000110001 &
#189000000
1!
1$
b00100000 '
#192000000
0!
b00100000 "
b000000110010 #
0$
b00100000 %
b000000110010 &
#195000000
1!
1$
b00100001 '
#198000000
0!
b00100001 "
b000000110011 #
0$
b00100001 %
b000000110011 &
#201000000
1!
1$
b00100010 '
#204000000
0!
b00100010 "
b000000110100 #
0$
b00100010 %
b000000110100 &
#207000000
1!
1$
b00100011 '
#210000000
0!
b00100011 "
b000000110101 #
0$
b00100011 %
b000000110101 &
#213000000
1!
1$
b00100100 '
#216000000
0!
b00100100 "
b000000110110 #
0$
b00100100 %
b000000110110 &
#219000000
1!
1$
b00100101 '
#222000000
0!
b00100101 "
b000000110111 #
0$
b00100101 %
b000000110111 &
#225000000
1!
1$
b00100110 '
#228000000
0!
b00100110 "
b000000111000 #
0$
b00100110 %
b000000111000 &
#231000000
1!
1$
b00100111 '
#234000000
0!
b00100111 "
b000000111001 #
0$
b00100111 %
b000000111001 &
#237000000
1!
1$
b00101000 '
#240000000
0!
b00101000 "
b000001000000 #
0$
b00101000 %
b000001000000 &
#243000000
1!
1$
b00101001 '
#246000000
0!
b00101001 "
b000001000001 #
0$
b00101001 %
b000001000001 &
#249000000
1!
1$
b00101010 '
#252000000
0!
b00101010 "
b000001000010 #
0$
b00101010 %
b000001000010 &
#255000000
1!
1$
b00101011 '
#258000000
0!
b00101011 "
b000001000011 #
0$
b00101011 %
b000001000011 &
#261000000
1!
1$
b00101100 '
#264000000
0!
b00101100 "
b000001000100 #
0$
b00101100 %
b000001000100 &
#267000000
1!
1$
b00101101 '
#270000000
0!
b00101101 "
b000001000101 #
0$
b00101101 %
b000001000101 &
#273000000
1!
1$
b00101110 '
#276000000
0!
b00101110 "
b000001000110 #
0$
b00101110 %
b000001000110 &
#279000000
1!
1$
b00101111 '
#282000000
0!
b00101111 "
b000001000111 #
0$
b00101111 %
b000001000111 &
#285000000
1!
1$
b00110000 '
#288000000
0!
b00110000 "
b000001001000 #
0$
b00110000 %
b000001001000 &
#291000000
1!
1$
b00110001 '
#294000000
0!
b00110001 "
b000001001001 #
0$
b00110001 %
b000001001001 &
#297000000
1!
1$
b00110010 '
#300000000
0!
b00110010 "
b000001010000 #
0$
b00110010 %
b000001010000 &
#303000000
1!
1$
b00110011 '
#306000000
0!
b00110011 "
b000001010001 #
0$
b00110011 %
b000001010001 &
#309000000
1!
1$
b00110100 '
#312000000
0!
b00110100 "
b000001010010 #
0$
b00110100 %
b000001010010 &
#315000000
1!
1$
b00110101 '
#318000000
0!
b00110101 "
b000001010011 #
0$
b00110101 %
b000001010011 &
#321000000
1!
1$
b00110110 '
#324000000
0!
b00110110 "
b000001010100 #
0$
b00110110 %
b000001010100 &
#327000000
1!
1$
b00110111 '
#330000000
0!
b00110111 "
b000001010101 #
0$
b00110111 %
b000001010101 &
#333000000
1!
1$
b00111000 '
#336000000
0!
b00111000 "
b000001010110 #
0$
b00111000 %
b000001010110 &
#339000000
1!
1$
b00111001 '
#342000000
0!
b00111001 "
b000001010111 #
0$
b00111001 %
b000001010111 &
#345000000
1!
1$
b00111010 '
#348000000
0!
b00111010 "
b000001011000 #
0$
b00111010 %
b000001011000 &
#351000000
1!
1$
b00111011 '
#354000000
0!
b00111011 "
b000001011001 #
0$
b00111011 %
b000001011001 &
#357000000
1!
1$
b00111100 '
#360000000
0!
b00111100 "
b000001100000 #
0$
b00111100 %
b000001100000 &
#363000000
1!
1$
b00111101 '
#366000000
0!
b00111101 "
b000001100001 #
0$
b00111101 %
b000001100001 &
#369000000
1!
1$
b00111110 '
#372000000
0!
b00111110 "
b000001100010 #
0$
b00111110 %
b000001100010 &
#375000000
1!
1$
b00111111 '
#378000000
0!
b00111111 "
b000001100011 #
0$
b00111111 %
b000001100011 &
#381000000
1!
1$
b01000000 '
#384000000
0!
b01000000 "
b000001100100 #
0$
b01000000 %
b000001100100 &
#387000000
1!
1$
b01000001 '
#390000000
0!
b01000001 "
b000001100101 #
0$
b01000001 %
b000001100101 &
#393000000
1!
1$
b01000010 '
#396000000
0!
b01000010 "
b000001100110 #
0$
b01000010 %
b000001100110 &
#399000000
1!
1$
b01000011 '
#402000000
0!
b01000011 "
b000001100111 #
0$
b01000011 %
b000001100111 &
#405000000
1!
1$
b01000100 '
#408000000
0!
b01000100 "
b000001101000 #
0$
b01000100 %
b000001101000 &
#411000000
1!
1$
b01000101 '
#414000000
0!
b01000101 "
b000001101001 #
0$
b01000101 %
b000001101001 &
#417000000
1!
1$
b01000110 '
#420000000
0!
b01000110 "
b000001110000 #
0$
b01000110 %
b000001110000 &
#423000000
1!
1$
b01000111 '
#426000000
0!
b01000111 "
b000001110001 #
0$
b01000111 %
b000001110001 &
#429000000
1!
1$
b01001000 '
#432000000
0!
b01001000 "
b000001110010 #
0$
b01001000 %
b000001110010 &
#435000000
1!
1$
b01001001 '
#438000000
0!
b01001001 "
b000001110011 #
0$
b01001001 %
b000001110011 &
#441000000
1!
1$
b01001010 '
#444000000
0!
b01001010 "
b000001110100 #
0$
b01001010 %
b000001110100 &
#447000000
1!
1$
b01001011 '
#450000000
0!
b01001011 "
b000001110101 #
0$
b01001011 %
b000001110101 &
#453000000
1!
1$
b01001100 '
#456000000
0!
b01001100 "
b000001110110 #
0$
b01001100 %
b000001110110 &
#459000000
1!
1$
b01001101 '
#462000000
0!
b01001101 "
b000001110111 #
0$
b01001101 %
b000001110111 &
#465000000
1!
1$
b01001110 '
#468000000
0!
b01001110 "
b000001111000 #
0$
b01001110 %
b000001111000 &
#471000000
1!
1$
b01001111 '
#474000000
0!
b01001111 "
b000001111001 #
0$
b01001111 %
b000001111001 &
#477000000
1!
1$
b01010000 '
#480000000
0!
b01010000 "
b000010000000 #
0$
b01010000 %
b000010000000 &
#483000000
1!
1$
b01010001 '
#486000000
0!
b01010001 "
b000010000001 #
0$
b01010001 %
b000010000001 &
#489000000
1!
1$
b01010010 '
#492000000
0!
b01010010 "
b000010000010 #
0$
b01010010 %
b000010000010 &
#495000000
1!
1$
b01010011 '
#498000000
0!
b01010011 "
b000010000011 #
0$
b01010011 %
b000010000011 &
#501000000
1!
1$
b01010100 '
#504000000
0!
b01010100 "
b000010000100 #
0$
b01010100 %
b000010000100 &
#507000000
1!
1$
b01010101 '
#510000000
0!
b01010101 "
b000010000101 #
0$
b01010101 %
b000010000101 &
#513000000
1!
1$
b01010110 '
#516000000
0!
b01010110 "
b000010000110 #
0$
b01010110 %
b000010000110 &
#519000000
1!
1$
b01010111 '
#522000000
0!
b01010111 "
b000010000111 #
0$
b01010111 %
b000010000111 &
#525000000
1!
1$
b01011000 '
#528000000
0!
b01011000 "
b000010001000 #
0$
b01011000 %
b000010001000 &
#531000000
1!
1$
b01011001 '
#534000000
0!
b01011001 "
b000010001001 #
0$
b01011001 %
b000010001001 &
#537000000
1!
1$
b01011010 '
#540000000
0!
b01011010 "
b000010010000 #
0$
b01011010 %
b000010010000 &
#543000000
1!
1$
b01011011 '
#546000000
0!
b01011011 "
b000010010001 #
0$
b01011011 %
b000010010001 &
#549000000
1!
1$
b01011100 '
#552000000
0!
b01011100 "
b000010010010 #
0$
b01011100 %
b000010010010 &
#555000000
1!
1$
b01011101 '
#558000000
0!
b01011101 "
b000010010011 #
0$
b01011101 %
b000010010011 &
#561000000
1!
1$
b01011110 '
#564000000
0!
b01011110 "
b000010010100 #
0$
b01011110 %
b000010010100 &
#567000000
1!
1$
b01011111 '
#570000000
0!
b01011111 "
b000010010101 #
0$
b01011111 %
b000010010101 &
#573000000
1!
1$
b01100000 '
#576000000
0!
b01100000 "
b000010010110 #
0$
b01100000 %
b000010010110 &
#579000000
1!
1$
b01100001 '
#582000000
0!
b01100001 "
b000010010111 #
0$
b01100001 %
b000010010111 &
#585000000
1!
1$
b01100010 '
#588000000
0!
b01100010 "
b000010011000 #
0$
b01100010 %
b000010011000 &
#591000000
1!
1$
b01100011 '
#594000000
0!
b01100011 "
b000010011001 #
0$
b01100011 %
b000010011001 &
#597000000
1!
1$
b01100100 '
#600000000
0!
b01100100 "
b000100000000 #
0$
b01100100 %
b000100000000 &
#603000000
1!
1$
b01100101 '
#606000000
0!
b01100101 "
b000100000001 #
0$
b01100101 %
b000100000001 &
#609000000
1!
1$
b01100110 '
#612000000
0!
b01100110 "
b000100000010 #
0$
b01100110 %
b000100000010 &
#615000000
1!
1$
b01100111 '
#618000000
0!
b01100111 "
b000100000011 #
0$
b01100111 %
b000100000011 &
#621000000
1!
1$
b01101000 '
#624000000
0!
b01101000 "
b000100000100 #
0$
b01101000 %
b000100000100 &
#627000000
1!
1$
b01101001 '
#630000000
0!
b01101001 "
b000100000101 #
0$
b01101001 %
b000100000101 &
#633000000
1!
1$
b01101010 '
#636000000
0!
b01101010 "
b000100000110 #
0$
b01101010 %
b000100000110 &
#639000000
1!
1$
b01101011 '
#642000000
0!
b01101011 "
b000100000111 #
0$
b01101011 %
b000100000111 &
#645000000
1!
1$
b01101100 '
#648000000
0!
b01101100 "
b000100001000 #
0$
b01101100 %
b000100001000 &
#651000000
1!
1$
b01101101 '
#654000000
0!
b01101101 "
b000100001001 #
0$
b01101101 %
b000100001001 &
#657000000
1!
1$
b01101110 '
#660000000
0!
b01101110 "
b000100010000 #
0$
b01101110 %
b000100010000 &
#663000000
1!
1$
b01101111 '
#666000000
0!
b01101111 "
b000100010001 #
0$
b01101111 %
b000100010001 &
#669000000
1!
1$
b01110000 '
#672000000
0!
b01110000 "
b000100010010 #
0$
b01110000 %
b000100010010 &
#675000000
1!
1$
b01110001 '
#678000000
0!
b01110001 "
b000100010011 #
0$
b01110001 %
b000100010011 &
#681000000
1!
1$
b01110010 '
#684000000
0!
b01110010 "
b000100010100 #
0$
b01110010 %
b000100010100 &
#687000000
1!
1$
b01110011 '
#690000000
0!
b01110011 "
b000100010101 #
0$
b01110011 %
b000100010101 &
#693000000
1!
1$
b01110100 '
#696000000
0!
b01110100 "
b000100010110 #
0$
b01110100 %
b000100010110 &
#699000000
1!
1$
b01110101 '
#702000000
0!
b01110101 "
b000100010111 #
0$
b01110101 %
b000100010111 &
#705000000
1!
1$
b01110110 '
#708000000
0!
b01110110 "
b000100011000 #
0$
b01110110 %
b000100011000 &
#711000000
1!
1$
b01110111 '
#714000000
0!
b01110111 "
b000100011001 #
0$
b01110111 %
b000100011001 &
#717000000
1!
1$
b01111000 '
#720000000
0!
b01111000 "
b000100100000 #
0$
b01111000 %
b000100100000 &
#723000000
1!
1$
b01111001 '
#726000000
0!
b01111001 "
b000100100001 #
0$
b01111001 %
b000100100001 &
#729000000
1!
1$
b01111010 '
#732000000
0!
b01111010 "
b000100100010 #
0$
b01111010 %
b000100100010 &
#735000000
1!
1$
b01111011 '
#738000000
0!
b01111011 "
b000100100011 #
0$
b01111011 %
b000100100011 &
#741000000
1!
1$
b01111100 '
#744000000
0!
b01111100 "
b000100100100 #
0$
b01111100 %
b000100100100 &
#747000000
1!
1$
b01111101 '
#750000000
0!
b01111101 "
b000100100101 #
0$
b01111101 %
b000100100101 &
#753000000
1!
1$
b01111110 '
#756000000
0!
b01111110 "
b000100100110 #
0$
b01111110 %
b000100100110 &
#759000000
1!
1$
b01111111 '
#762000000
0!
b01111111 "
b000100100111 #
0$
b01111111 %
b000100100111 &
#765000000
1!
1$
b10000000 '
#768000000
0!
b10000000 "
b000100101000 #
0$
b10000000 %
b000100101000 &
#771000000
1!
1$
b10000001 '
#774000000
0!
b10000001 "
b000100101001 #
0$
b10000001 %
b000100101001 &
#777000000
1!
1$
b10000010 '
#780000000
0!
b10000010 "
b000100110000 #
0$
b10000010 %
b000100110000 &
#783000000
1!
1$
b10000011 '
#786000000
0!
b10000011 "
b000100110001 #
0$
b10000011 %
b000100110001 &
#789000000
1!
1$
b10000100 '
#792000000
0!
b10000100 "
b000100110010 #
0$
b10000100 %
b000100110010 &
#795000000
1!
1$
b10000101 '
#798000000
0!
b10000101 "
b000100110011 #
0$
b10000101 %
b000100110011 &
#801000000
1!
1$
b10000110 '
#804000000
0!
b10000110 "
b000100110100 #
0$
b10000110 %
b000100110100 &
#807000000
1!
1$
b10000111 '
#810000000
0!
b10000111 "
b000100110101 #
0$
b10000111 %
b000100110101 &
#813000000
1!
1$
b10001000 '
#816000000
0!
b10001000 "
b000100110110 #
0$
b10001000 %
b000100110110 &
#819000000
1!
1$
b10001001 '
#822000000
0!
b10001001 "
b000100110111 #
0$
b10001001 %
b000100110111 &
#825000000
1!
1$
b10001010 '
#828000000
0!
b10001010 "
b000100111000 #
0$
b10001010 %
b000100111000 &
#831000000
1!
1$
b10001011 '
#834000000
0!
b10001011 "
b000100111001 #
0$
b10001011 %
b000100111001 &
#837000000
1!
1$
b10001100 '
#840000000
0!
b10001100 "
b000101000000 #
0$
b10001100 %
b000101000000 &
#843000000
1!
1$
b10001101 '
#846000000
0!
b10001101 "
b000101000001 #
0$
b10001101 %
b000101000001 &
#849000000
1!
1$
b10001110 '
#852000000
0!
b10001110 "
b000101000010 #
0$
b10001110 %
b000101000010 &
#855000000
1!
1$
b10001111 '
#858000000
0!
b10001111 "
b000101000011 #
0$
b10001111 %
b000101000011 &
#861000000
1!
1$
b10010000 '
#864000000
0!
b10010000 "
b000101000100 #
0$
b10010000 %
b000101000100 &
#867000000
1!
1$
b10010001 '
#870000000
0!
b10010001 "
b000101000101 #
0$
b10010001 %
b000101000101 &
#873000000
1!
1$
b10010010 '
#876000000
0!
b10010010 "
b000101000110 #
0$
b10010010 %
b000101000110 &
#879000000
1!
1$
b10010011 '
#882000000
0!
b10010011 "
b000101000111 #
0$
b10010011 %
b000101000111 &
#885000000
1!
1$
b10010100 '
#888000000
0!
b10010100 "
b000101001000 #
0$
b10010100 %
b000101001000 &
#891000000
1!
1$
b10010101 '
#894000000
0!
b10010101 "
b000101001001 #
0$
b10010101 %
b000101001001 &
#897000000
1!
1$
b10010110 '
#900000000
0!
b10010110 "
b000101010000 #
0$
b10010110 %
b000101010000 &
#903000000
1!
1$
b10010111 '
#906000000
0!
b10010111 "
b000101010001 #
0$
b10010111 %
b000101010001 &
#909000000
1!
1$
b10011000 '
#912000000
0!
b10011000 "
b000101010010 #
0$
b10011000 %
b000101010010 &
#915000000
1!
1$
b10011001 '
#918000000
0!
b10011001 "
b000101010011 #
0$
b10011001 %
b000101010011 &
#921000000
1!
1$
b10011010 '
#924000000
0!
b10011010 "
b000101010100 #
0$
b10011010 %
b000101010100 &
#927000000
1!
1$
b10011011 '
#930000000
0!
b10011011 "
b000101010101 #
0$
b10011011 %
b000101010101 &
#933000000
1!
1$
b10011100 '
#936000000
0!
b10011100 "
b000101010110 #
0$
b10011100 %
b000101010110 &
#939000000
1!
1$
b10011101 '
#942000000
0!
b10011101 "
b000101010111 #
0$
b10011101 %
b000101010111 &
#945000000
1!
1$
b10011110 '
#948000000
0!
b10011110 "
b000101011000 #
0$
b10011110 %
b000101011000 &
#951000000
1!
1$
b10011111 '
#954000000
0!
b10011111 "
b000101011001 #
0$
b10011111 %
b000101011001 &
#957000000
1!
1$
b10100000 '
#960000000
0!
b10100000 "
b000101100000 #
0$
b10100000 %
b000101100000 &
#963000000
1!
1$
b10100001 '
#966000000
0!
b10100001 "
b000101100001 #
0$
b10100001 %
b000101100001 &
#969000000
1!
1$
b10100010 '
#972000000
0!
b10100010 "
b000101100010 #
0$
b10100010 %
b000101100010 &
#975000000
1!
1$
b10100011 '
#978000000
0!
b10100011 "
b000101100011 #
0$
b10100011 %
b000101100011 &
#981000000
1!
1$
b10100100 '
#984000000
0!
b10100100 "
b000101100100 #
0$
b10100100 %
b000101100100 &
#987000000
1!
1$
b10100101 '
#990000000
0!
b10100101 "
b000101100101 #
0$
b10100101 %
b000101100101 &
#993000000
1!
1$
b10100110 '
#996000000
0!
b10100110 "
b000101100110 #
0$
b10100110 %
b000101100110 &
#999000000
1!
1$
b10100111 '
#1002000000
0!
b10100111 "
b000101100111 #
0$
b10100111 %
b000101100111 &
#1005000000
1!
1$
b10101000 '
#1008000000
0!
b10101000 "
b000101101000 #
0$
b10101000 %
b000101101000 &
#1011000000
1!
1$
b10101001 '
#1014000000
0!
b10101001 "
b000101101001 #
0$
b10101001 %
b000101101001 &
#1017000000
1!
1$
b10101010 '
#1020000000
0!
b10101010 "
b000101110000 #
0$
b10101010 %
b000101110000 &
#1023000000
1!
1$
b10101011 '
#1026000000
0!
b10101011 "
b000101110001 #
0$
b10101011 %
b000101110001 &
#1029000000
1!
1$
b10101100 '
#1032000000
0!
b10101100 "
b000101110010 #
0$
b10101100 %
b000101110010 &
#1035000000
1!
1$
b10101101 '
#1038000000
0!
b10101101 "
b000101110011 #
0$
b10101101 %
b000101110011 &
#1041000000
1!
1$
b10101110 '
#1044000000
0!
b10101110 "
b000101110100 #
0$
b10101110 %
b000101110100 &
#1047000000
1!
1$
b10101111 '
#1050000000
0!
b10101111 "
b000101110101 #
0$
b10101111 %
b000101110101 &
#1053000000
1!
1$
b10110000 '
#1056000000
0!
b10110000 "
b000101110110 #
0$
b10110000 %
b000101110110 &
#1059000000
1!
1$
b10110001 '
#1062000000
0!
b10110001 "
b000101110111 #
0$
b10110001 %
b000101110111 &
#1065000000
1!
1$
b10110010 '
#1068000000
0!
b10110010 "
b000101111000 #
0$
b10110010 %
b000101111000 &
#1071000000
1!
1$
b10110011 '
#1074000000
0!
b10110011 "
b000101111001 #
0$
b10110011 %
b000101111001 &
#1077000000
1!
1$
b10110100 '
#1080000000
0!
b10110100 "
b000110000000 #
0$
b10110100 %
b000110000000 &
#1083000000
1!
1$
b10110101 '
#1086000000
0!
b10110101 "
b000110000001 #
0$
b10110101 %
b000110000001 &
#1089000000
1!
1$
b10110110 '
#1092000000
0!
b10110110 "
b000110000010 #
0$
b10110110 %
b000110000010 &
#1095000000
1!
1$
b10110111 '
#1098000000
0!
b10110111 "
b000110000011 #
0$
b10110111 %
b000110000011 &
#1101000000
1!
1$
b10111000 '
#1104000000
0!
b10111000 "
b000110000100 #
0$
b10111000 %
b000110000100 &
#1107000000
1!
1$
b10111001 '
#1110000000
0!
b10111001 "
b000110000101 #
0$
b10111001 %
b000110000101 &
#1113000000
1!
1$
b10111010 '
#1116000000
0!
b10111010 "
b000110000110 #
0$
b10111010 %
b000110000110 &
#1119000000
1!
1$
b10111011 '
#1122000000
0!
b10111011 "
b000110000111 #
0$
b10111011 %
b000110000111 &
#1125000000
1!
1$
b10111100 '
#1128000000
0!
b10111100 "
b000110001000 #
0$
b10111100 %
b000110001000 &
#1131000000
1!
1$
b10111101 '
#1134000000
0!
b10111101 "
b000110001001 #
0$
b10111101 %
b000110001001 &
#1137000000
1!
1$
b10111110 '
#1140000000
0!
b10111110 "
b000110010000 #
0$
b10111110 %
b000110010000 &
#1143000000
1!
1$
b10111111 '
#1146000000
0!
b10111111 "
b000110010001 #
0$
b10111111 %
b000110010001 &
#1149000000
1!
1$
b11000000 '
#1152000000
0!
b11000000 "
b000110010010 #
0$
b11000000 %
b000110010010 &
#1155000000
1!
1$
b11000001 '
#1158000000
0!
b11000001 "
b000110010011 #
0$
b11000001 %
b000110010011 &
#1161000000
1!
1$
b11000010 '
#1164000000
0!
b11000010 "
b000110010100 #
0$
b11000010 %
b000110010100 &
#1167000000
1!
1$
b11000011 '
#1170000000
0!
b11000011 "
b000110010101 #
0$
b11000011 %
b000110010101 &
#1173000000
1!
1$
b11000100 '
#1176000000
0!
b11000100 "
b000110010110 #
0$
b11000100 %
b000110010110 &
#1179000000
1!
1$
b11000101 '
#1182000000
0!
b11000101 "
b000110010111 #
0$
b11000101 %
b000110010111 &
#1185000000
1!
1$
b11000110 '
#1188000000
0!
b11000110 "
b000110011000 #
0$
b11000110 %
b000110011000 &
#1191000000
1!
1$
b11000111 '
#1194000000
0!
b11000111 "
b000110011001 #
0$
b11000111 %
b000110011001 &
#1197000000
1!
1$
b11001000 '
#1200000000
0!
b11001000 "
b001000000000 #
0$
b11001000 %
b001000000000 &
#1203000000
1!
1$
b11001001 '
#1206000000
0!
b11001001 "
b001000000001 #
0$
b11001001 %
b001000000001 &
#1209000000
1!
1$
b11001010 '
#1212000000
0!
b11001010 "
b001000000010 #
0$
b11001010 %
b001000000010 &
#1215000000
1!
1$
b11001011 '
#1218000000
0!
b11001011 "
b001000000011 #
0$
b11001011 %
b001000000011 &
#1221000000
1!
1$
b11001100 '
#1224000000
0!
b11001100 "
b001000000100 #
0$
b11001100 %
b001000000100 &
#1227000000
1!
1$
b11001101 '
#1230000000
0!
b11001101 "
b001000000101 #
0$
b11001101 %
b001000000101 &
#1233000000
1!
1$
b11001110 '
#1236000000
0!
b11001110 "
b001000000110 #
0$
b11001110 %
b001000000110 &
#1239000000
1!
1$
b11001111 '
#1242000000
0!
b11001111 "
b001000000111 #
0$
b11001111 %
b001000000111 &
#1245000000
1!
1$
b11010000 '
#1248000000
0!
b11010000 "
b001000001000 #
0$
b11010000 %
b001000001000 &
#1251000000
1!
1$
b11010001 '
#1254000000
0!
b11010001 "
b001000001001 #
0$
b11010001 %
b001000001001 &
#1257000000
1!
1$
b11010010 '
#1260000000
0!
b11010010 "
b001000010000 #
0$
b11010010 %
b001000010000 &
#1263000000
1!
1$
b11010011 '
#1266000000
0!
b11010011 "
b001000010001 #
0$
b11010011 %
b001000010001 &
#1269000000
1!
1$
b11010100 '
#1272000000
0!
b11010100 "
b001000010010 #
0$
b11010100 %
b001000010010 &
#1275000000
1!
1$
b11010101 '
#1278000000
0!
b11010101 "
b001000010011 #
0$
b11010101 %
b001000010011 &
#1281000000
1!
1$
b11010110 '
#1284000000
0!
b11010110 "
b001000010100 #
0$
b11010110 %
b001000010100 &
#1287000000
1!
1$
b11010111 '
#1290000000
0!
b11010111 "
b001000010101 #
0$
b11010111 %
b001000010101 &
#1293000000
1!
1$
b11011000 '
#1296000000
0!
b11011000 "
b001000010110 #
0$
b11011000 %
b001000010110 &
#1299000000
1!
1$
b11011001 '
#1302000000
0!
b11011001 "
b001000010111 #
0$
b11011001 %
b001000010111 &
#1305000000
1!
1$
b11011010 '
#1308000000
0!
b11011010 "
b001000011000 #
0$
b11011010 %
b001000011000 &
#1311000000
1!
1$
b11011011 '
#1314000000
0!
b11011011 "
b001000011001 #
0$
b11011011 %
b001000011001 &
#1317000000
1!
1$
b11011100 '
#1320000000
0!
b11011100 "
b001000100000 #
0$
b11011100 %
b001000100000 &
#1323000000
1!
1$
b11011101 '
#1326000000
0!
b11011101 "
b001000100001 #
0$
b11011101 %
b001000100001 &
