FPGA/FPGA 04/Exercise_4/pwm.m.vhd
---------------------------------------
-- lecture 02 shift register
-- just forwarding the signal
----------------------------------------

library ieee;
use ieee.std_logic_1164.all;
use ieee.numeric_std.all;

----------------------------------------

entity pwm is

    port(   
        i_sl_CLK      :  in  std_logic;                                 -- clock
	i_sl_en	      :  in std_logic;
	i_sl_sixteen  :  in std_logic_vector(15 downto 0);
        o_sl_pwm      :  out std_logic_vector(1 downto 0);    -- pwm output
	o_sl_four     :  out std_logic_vector(3 downto 0)
    );
end pwm;  

----------------------------------------

architecture behavior of pwm is
signal slv_pwm_cnt : std_logic_vector(1 downto 0) := "00";
signal slv_pwm_four : std_logic_vector(3 downto 0) := "0000";


begin
    process(i_sl_CLK)
    begin
        if rising_edge(i_sl_CLK) then
		if (i_sl_en = '1') then
			slv_pwm_cnt <= std_logic_vector(unsigned(slv_pwm_cnt)+1);
			o_sl_pwm <= slv_pwm_cnt;
		end if;
		if (i_sl_en = '0') then 
			slv_pwm_cnt <= std_logic_vector(unsigned(slv_pwm_cnt)-1);
			o_sl_pwm <= slv_pwm_cnt;
		end if;
        end if;

	if (o_sl_pwm = "00") then
		slv_pwm_four <= i_sl_sixteen(3 downto 0);
	elsif (o_sl_pwm = "01") then
		slv_pwm_four <= i_sl_sixteen(7 downto 4);
	elsif (o_sl_pwm = "10") then
		slv_pwm_four <= i_sl_sixteen(11 downto 8);
	elsif (o_sl_pwm = "11") then
		slv_pwm_four <= i_sl_sixteen(15 downto 12);
	end if;

	o_sl_four <= slv_pwm_four;

	
    end process;

end behavior;

------------------------------------------

FPGA/FPGA 04/Exercise_4/pwm.tb.vhd
library ieee;
use ieee.std_logic_1164.all;

ENTITY pwm_tb IS
END pwm_tb;

ARCHITECTURE tb OF pwm_tb IS 

    COMPONENT pwm is

        port(   
            i_sl_CLK      :  in  std_logic;                      -- clock
	    i_sl_en	  :  in  std_logic;
	    i_sl_sixteen  :  in std_logic_vector(15 downto 0);
            o_sl_pwm      :  out std_logic_vector(1 downto 0);   -- output
	    o_sl_four     :  out std_logic_vector(3 downto 0)
        );
    end COMPONENT;

    -- "local" signals
    -- signals for UUT
    -- input 
    signal CLK    : std_logic := '0';
    signal en     : std_logic := '0';
    signal sixteen : std_logic_vector(15 downto 0) := "0000010110101111";
    -- ouput
    signal o_sl_pwm : std_logic_vector(1 downto 0) := "00";
    signal o_sl_four : std_logic_vector(3 downto 0) := "0000";

BEGIN 
    -- Instance of unit under test.
    uut: pwm 
    PORT MAP (
        i_sl_CLK    => CLK,
	i_sl_en     => en,
	i_sl_sixteen => sixteen,
        o_sl_pwm    => o_sl_pwm,
	o_sl_four   => o_sl_four
    );

-------------------------------------------------------------------------------
    -- test bench definition.
    tb_CLK :process
    begin
        CLK <= '0';
        wait for 1 ns;
        CLK <= '1';
        wait for 1 ns;
    end process;

    tb_en :process
    begin
        en <= '1';
        wait for 20 ns;
        en <= '0';
        wait for 20 ns;
    end process;


END;

FPGA/FPGA 04/Exercise_4/pwm.vcd
$date
  Wed Dec  9 10:56:07 2020
$end
$version
  GHDL v0
$end
$timescale
  1 fs
$end
$scope module standard $end
$upscope $end
$scope module textio $end
$upscope $end
$scope module std_logic_1164 $end
$upscope $end
$scope module numeric_std $end
$upscope $end
$scope module pwm_tb $end
$var reg 1 ! clk $end
$var reg 1 " en $end
$var reg 16 # sixteen[15:0] $end
$var reg 2 $ o_sl_pwm[1:0] $end
$var reg 4 % o_sl_four[3:0] $end
$scope module uut $end
$var reg 1 & i_sl_clk $end
$var reg 1 ' i_sl_en $end
$var reg 16 ( i_sl_sixteen[15:0] $end
$var reg 2 ) o_sl_pwm[1:0] $end
$var reg 4 * o_sl_four[3:0] $end
$var reg 2 + slv_pwm_cnt[1:0] $end
$var reg 4 , slv_pwm_four[3:0] $end
$upscope $end
$upscope $end
$enddefinitions $end
#0
0!
1"
b0000010110101111 #
bUU $
b0000 %
0&
1'
b0000010110101111 (
bUU )
b0000 *
b00 +
b0000 ,
#1000000
1!
b00 $
1&
b00 )
b01 +
#2000000
0!
0&
b1111 ,
#3000000
1!
b01 $
b1111 %
1&
b01 )
b1111 *
b10 +
#4000000
0!
0&
b1010 ,
#5000000
1!
b10 $
b1010 %
1&
b10 )
b1010 *
b11 +
#6000000
0!
0&
b0101 ,
#7000000
1!
b11 $
b0101 %
1&
b11 )
b0101 *
b00 +
#8000000
0!
0&
b0000 ,
#9000000
1!
b00 $
b0000 %
1&
b00 )
b0000 *
b01 +
#10000000
0!
0&
b1111 ,
#11000000
1!
b01 $
b1111 %
1&
b01 )
b1111 *
b10 +
#12000000
0!
0&
b1010 ,
#13000000
1!
b10 $
b1010 %
1&
b10 )
b1010 *
b11 +
#14000000
0!
0&
b0101 ,
#15000000
1!
b11 $
b0101 %
1&
b11 )
b0101 *
b00 +
#16000000
0!
0&
b0000 ,
#17000000
1!
b00 $
b0000 %
1&
b00 )
b0000 *
b01 +
#18000000
0!
0&
b1111 ,
#19000000
1!
b01 $
b1111 %
1&
b01 )
b1111 *
b10 +
#20000000
0!
0"
0&
0'
b1010 ,
#21000000
1!
b10 $
b1010 %
1&
b10 )
b1010 *
b01 +
#22000000
0!
0&
b0101 ,
#23000000
1!
b01 $
b0101 %
1&
b01 )
b0101 *
b00 +
#24000000
0!
0&
b1010 ,
#25000000
1!
b00 $
b1010 %
1&
b00 )
b1010 *
b11 +
#26000000
0!
0&
b1111 ,
#27000000
1!
b11 $
b1111 %
1&
b11 )
b1111 *
b10 +
#28000000
0!
0&
b0000 ,
#29000000
1!
b10 $
b0000 %
1&
b10 )
b0000 *
b01 +
#30000000
0!
0&
b0101 ,
#31000000
1!
b01 $
b0101 %
1&
b01 )
b0101 *
b00 +
#32000000
0!
0&
b1010 ,
#33000000
1!
b00 $
b1010 %
1&
b00 )
b1010 *
b11 +
#34000000
0!
0&
b1111 ,
#35000000
1!
b11 $
b1111 %
1&
b11 )
b1111 *
b10 +
#36000000
0!
0&
b0000 ,
#37000000
1!
b10 $
b0000 %
1&
b10 )
b0000 *
b01 +
#38000000
0!
0&
b0101 ,
#39000000
1!
b01 $
b0101 %
1&
b01 )
b0101 *
b00 +
#40000000
0!
1"
0&
1'
b1010 ,
#41000000
1!
b00 $
b1010 %
1&
b00 )
b1010 *
b01 +
#42000000
0!
0&
b1111 ,
#43000000
1!
b01 $
b1111 %
1&
b01 )
b1111 *
b10 +
#44000000
0!
0&
b1010 ,
#45000000
1!
b10 $
b1010 %
1&
b10 )
b1010 *
b11 +
#46000000
0!
0&
b0101 ,
#47000000
1!
b11 $
b0101 %
1&
b11 )
b0101 *
b00 +
#48000000
0!
0&
b0000 ,
#49000000
1!
b00 $
b0000 %
1&
b00 )
b0000 *
b01 +
#50000000
0!
0&
b1111 ,
#51000000
1!
b01 $
b1111 %
1&
b01 )
b1111 *
b10 +
#52000000
0!
0&
b1010 ,
#53000000
1!
b10 $
b1010 %
1&
b10 )
b1010 *
b11 +
#54000000
0!
0&
b0101 ,
#55000000
1!
b11 $
b0101 %
1&
b11 )
b0101 *
b00 +
#56000000
0!
0&
b0000 ,
#57000000
1!
b00 $
b0000 %
1&
b00 )
b0000 *
b01 +
#58000000
0!
0&
b1111 ,
#59000000
1!
b01 $
b1111 %
1&
b01 )
b1111 *
b10 +
#60000000
0!
0"
0&
0'
b1010 ,
#61000000
1!
b10 $
b1010 %
1&
b10 )
b1010 *
b01 +
#62000000
0!
0&
b0101 ,
#63000000
1!
b01 $
b0101 %
1&
b01 )
b0101 *
b00 +
#64000000
0!
0&
b1010 ,
#65000000
1!
b00 $
b1010 %
1&
b00 )
b1010 *
b11 +
#66000000
0!
0&
b1111 ,
#67000000
1!
b11 $
b1111 %
1&
b11 )
b1111 *
b10 +
#68000000
0!
0&
b0000 ,
#69000000
1!
b10 $
b0000 %
1&
b10 )
b0000 *
b01 +
#70000000
0!
0&
b0101 ,
#71000000
1!
b01 $
b0101 %
1&
b01 )
b0101 *
b00 +
#72000000
0!
0&
b1010 ,
#73000000
1!
b00 $
b1010 %
1&
b00 )
b1010 *
b11 +
#74000000
0!
0&
b1111 ,
#75000000
1!
b11 $
b1111 %
1&
b11 )
b1111 *
b10 +
#76000000
0!
0&
b0000 ,
#77000000
1!
b10 $
b0000 %
1&
b10 )
b0000 *
b01 +
#78000000
0!
0&
b0101 ,
#79000000
1!
b01 $
b0101 %
1&
b01 )
b0101 *
b00 +
#80000000
0!
1"
0&
1'
b1010 ,
#81000000
1!
b00 $
b1010 %
1&
b00 )
b1010 *
b01 +
#82000000
0!
0&
b1111 ,
#83000000
1!
b01 $
b1111 %
1&
b01 )
b1111 *
b10 +
#84000000
0!
0&
b1010 ,
#85000000
1!
b10 $
b1010 %
1&
b10 )
b1010 *
b11 +
#86000000
0!
0&
b0101 ,
#87000000
1!
b11 $
b0101 %
1&
b11 )
b0101 *
b00 +
#88000000
0!
0&
b0000 ,
#89000000
1!
b00 $
b0000 %
1&
b00 )
b0000 *
b01 +
#90000000
0!
0&
b1111 ,
#91000000
1!
b01 $
b1111 %
1&
b01 )
b1111 *
b10 +
#92000000
0!
0&
b1010 ,
#93000000
1!
b10 $
b1010 %
1&
b10 )
b1010 *
b11 +
#94000000
0!
0&
b0101 ,
#95000000
1!
b11 $
b0101 %
1&
b11 )
b0101 *
b00 +
#96000000
0!
0&
b0000 ,
#97000000
1!
b00 $
b0000 %
1&
b00 )
b0000 *
b01 +
#98000000
0!
0&
b1111 ,
#99000000
1!
b01 $
b1111 %
1&
b01 )
b1111 *
b10 +
#100000000
0!
0"
0&
0'
b1010 ,
#101000000
1!
b10 $
b1010 %
1&
b10 )
b1010 *
b01 +
#102000000
0!
0&
b0101 ,
#103000000
1!
b01 $
b0101 %
1&
b01 )
b0101 *
b00 +
#104000000
0!
0&
b1010 ,
#105000000
1!
b00 $
b1010 %
1&
b00 )
b1010 *
b11 +
#106000000
0!
0&
b1111 ,
#107000000
1!
b11 $
b1111 %
1&
b11 )
b1111 *
b10 +
#108000000
0!
0&
b0000 ,
#109000000
1!
b10 $
b0000 %
1&
b10 )
b0000 *
b01 +
#110000000
0!
0&
b0101 ,
#111000000
1!
b01 $
b0101 %
1&
b01 )
b0101 *
b00 +
#112000000
0!
0&
b1010 ,
#113000000
1!
b00 $
b1010 %
1&
b00 )
b1010 *
b11 +
#114000000
0!
0&
b1111 ,
#115000000
1!
b11 $
b1111 %
1&
b11 )
b1111 *
b10 +
#116000000
0!
0&
b0000 ,
#117000000
1!
b10 $
b0000 %
1&
b10 )
b0000 *
b01 +
#118000000
0!
0&
b0101 ,
#119000000
1!
b01 $
b0101 %
1&
b01 )
b0101 *
b00 +
#120000000
0!
1"
0&
1'
b1010 ,
#121000000
1!
b00 $
b1010 %
1&
b00 )
b1010 *
b01 +
#122000000
0!
0&
b1111 ,
#123000000
1!
b01 $
b1111 %
1&
b01 )
b1111 *
b10 +
#124000000
0!
0&
b1010 ,
#125000000
1!
b10 $
b1010 %
1&
b10 )
b1010 *
b11 +
#126000000
0!
0&
b0101 ,
#127000000
1!
b11 $
b0101 %
1&
b11 )
b0101 *
b00 +
#128000000
0!
0&
b0000 ,
#129000000
1!
b00 $
b0000 %
1&
b00 )
b0000 *
b01 +
#130000000
0!
0&
b1111 ,
#131000000
1!
b01 $
b1111 %
1&
b01 )
b1111 *
b10 +
#132000000
0!
0&
b1010 ,
#133000000
1!
b10 $
b1010 %
1&
b10 )
b1010 *
b11 +
#134000000
0!
0&
b0101 ,
#135000000
1!
b11 $
b0101 %
1&
b11 )
b0101 *
b00 +
#136000000
0!
0&
b0000 ,
#137000000
1!
b00 $
b0000 %
1&
b00 )
b0000 *
b01 +
#138000000
0!
0&
b1111 ,
#139000000
1!
b01 $
b1111 %
1&
b01 )
b1111 *
b10 +
#140000000
0!
0"
0&
0'
b1010 ,
#141000000
1!
b10 $
b1010 %
1&
b10 )
b1010 *
b01 +
#142000000
0!
0&
b0101 ,
#143000000
1!
b01 $
b0101 %
1&
b01 )
b0101 *
b00 +
#144000000
0!
0&
b1010 ,
#145000000
1!
b00 $
b1010 %
1&
b00 )
b1010 *
b11 +
#146000000
0!
0&
b1111 ,
#147000000
1!
b11 $
b1111 %
1&
b11 )
b1111 *
b10 +
#148000000
0!
0&
b0000 ,
#149000000
1!
b10 $
b0000 %
1&
b10 )
b0000 *
b01 +
#150000000
0!
0&
b0101 ,
#151000000
1!
b01 $
b0101 %
1&
b01 )
b0101 *
b00 +
#152000000
0!
0&
b1010 ,
#153000000
1!
b00 $
b1010 %
1&
b00 )
b1010 *
b11 +
#154000000
0!
0&
b1111 ,
#155000000
1!
b11 $
b1111 %
1&
b11 )
b1111 *
b10 +
#156000000
0!
0&
b0000 ,
#157000000
1!
b10 $
b0000 %
1&
b10 )
b0000 *
b01 +
#158000000
0!
0&
b0101 ,
#159000000
1!
b01 $
b0101 %
1&
b01 )
b0101 *
b00 +
#160000000
0!
1"
0&
1'
b1010 ,
#161000000
1!
b00 $
b1010 %
1&
b00 )
b1010 *
b01 +
#162000000
0!
0&
b1111 ,
#163000000
1!
b01 $
b1111 %
1&
b01 )
b1111 *
b10 +
#164000000
0!
0&
b1010 ,
#165000000
1!
b10 $
b1010 %
1&
b10 )
b1010 *
b11 +
#166000000
0!
0&
b0101 ,
#167000000
1!
b11 $
b0101 %
1&
b11 )
b0101 *
b00 +
#168000000
0!
0&
b0000 ,
#169000000
1!
b00 $
b0000 %
1&
b00 )
b0000 *
b01 +
#170000000
0!
0&
b1111 ,
#171000000
1!
b01 $
b1111 %
1&
b01 )
b1111 *
b10 +
#172000000
0!
0&
b1010 ,
#173000000
1!
b10 $
b1010 %
1&
b10 )
b1010 *
b11 +
#174000000
0!
0&
b0101 ,
#175000000
1!
b11 $
b0101 %
1&
b11 )
b0101 *
b00 +
#176000000
0!
0&
b0000 ,
#177000000
1!
b00 $
b0000 %
1&
b00 )
b0000 *
b01 +
#178000000
0!
0&
b1111 ,
#179000000
1!
b01 $
b1111 %
1&
b01 )
b1111 *
b10 +
#180000000
0!
0"
0&
0'
b1010 ,
#181000000
1!
b10 $
b1010 %
1&
b10 )
b1010 *
b01 +
#182000000
0!
0&
b0101 ,
#183000000
1!
b01 $
b0101 %
1&
b01 )
b0101 *
b00 +
#184000000
0!
0&
b1010 ,
#185000000
1!
b00 $
b1010 %
1&
b00 )
b1010 *
b11 +
#186000000
0!
0&
b1111 ,
#187000000
1!
b11 $
b1111 %
1&
b11 )
b1111 *
b10 +
#188000000
0!
0&
b0000 ,
#189000000
1!
b10 $
b0000 %
1&
b10 )
b0000 *
b01 +
#190000000
0!
0&
b0101 ,
#191000000
1!
b01 $
b0101 %
1&
b01 )
b0101 *
b00 +
#192000000
0!
0&
b1010 ,
#193000000
1!
b00 $
b1010 %
1&
b00 )
b1010 *
b11 +
#194000000
0!
0&
b1111 ,
#195000000
1!
b11 $
b1111 %
1&
b11 )
b1111 *
b10 +
#196000000
0!
0&
b0000 ,
#197000000
1!
b10 $
b0000 %
1&
b10 )
b0000 *
b01 +
#198000000
0!
0&
b0101 ,
#199000000
1!
b01 $
b0101 %
1&
b01 )
b0101 *
b00 +
#200000000
0!
1"
0&
1'
b1010 ,
#201000000
1!
b00 $
b1010 %
1&
b00 )
b1010 *
b01 +
#202000000
0!
0&
b1111 ,
#203000000
1!
b01 $
b1111 %
1&
b01 )
b1111 *
b10 +
#204000000
0!
0&
b1010 ,
#205000000
1!
b10 $
b1010 %
1&
b10 )
b1010 *
b11 +
#206000000
0!
0&
b0101 ,
#207000000
1!
b11 $
b0101 %
1&
b11 )
b0101 *
b00 +
#208000000
0!
0&
b0000 ,
#209000000
1!
b00 $
b0000 %
1&
b00 )
b0000 *
b01 +
#210000000
0!
0&
b1111 ,
#211000000
1!
b01 $
b1111 %
1&
b01 )
b1111 *
b10 +
#212000000
0!
0&
b1010 ,
#213000000
1!
b10 $
b1010 %
1&
b10 )
b1010 *
b11 +
#214000000
0!
0&
b0101 ,
#215000000
1!
b11 $
b0101 %
1&
b11 )
b0101 *
b00 +
#216000000
0!
0&
b0000 ,
#217000000
1!
b00 $
b0000 %
1&
b00 )
b0000 *
b01 +
#218000000
0!
0&
b1111 ,
#219000000
1!
b01 $
b1111 %
1&
b01 )
b1111 *
b10 +
#220000000
0!
0"
0&
0'
b1010 ,
#221000000
1!
b10 $
b1010 %
1&
b10 )
b1010 *
b01 +
#222000000
0!
0&
b0101 ,
#223000000
1!
b01 $
b0101 %
1&
b01 )
b0101 *
b00 +
#224000000
0!
0&
b1010 ,
#225000000
1!
b00 $
b1010 %
1&
b00 )
b1010 *
b11 +
#226000000
0!
0&
b1111 ,
#227000000
1!
b11 $
b1111 %
1&
b11 )
b1111 *
b10 +
#228000000
0!
0&
b0000 ,
#229000000
1!
b10 $
b0000 %
1&
b10 )
b0000 *
b01 +
#230000000
0!
0&
b0101 ,
#231000000
1!
b01 $
b0101 %
1&
b01 )
b0101 *
b00 +
#232000000
0!
0&
b1010 ,
#233000000
1!
b00 $
b1010 %
1&
b00 )
b1010 *
b11 +
#234000000
0!
0&
b1111 ,
#235000000
1!
b11 $
b1111 %
1&
b11 )
b1111 *
b10 +
#236000000
0!
0&
b0000 ,
#237000000
1!
b10 $
b0000 %
1&
b10 )
b0000 *
b01 +
#238000000
0!
0&
b0101 ,
#239000000
1!
b01 $
b0101 %
1&
b01 )
b0101 *
b00 +
#240000000
0!
1"
0&
1'
b1010 ,
#241000000
1!
b00 $
b1010 %
1&
b00 )
b1010 *
b01 +
#242000000
0!
0&
b1111 ,
#243000000
1!
b01 $
b1111 %
1&
b01 )
b1111 *
b10 +
#244000000
0!
0&
b1010 ,
#245000000
1!
b10 $
b1010 %
1&
b10 )
b1010 *
b11 +
#246000000
0!
0&
b0101 ,
#247000000
1!
b11 $
b0101 %
1&
b11 )
b0101 *
b00 +
#248000000
0!
0&
b0000 ,
#249000000
1!
b00 $
b0000 %
1&
b00 )
b0000 *
b01 +
#250000000
0!
0&
b1111 ,
#251000000
1!
b01 $
b1111 %
1&
b01 )
b1111 *
b10 +
#252000000
0!
0&
b1010 ,
#253000000
1!
b10 $
b1010 %
1&
b10 )
b1010 *
b11 +
#254000000
0!
0&
b0101 ,
#255000000
1!
b11 $
b0101 %
1&
b11 )
b0101 *
b00 +
#256000000
0!
0&
b0000 ,
#257000000
1!
b00 $
b0000 %
1&
b00 )
b0000 *
b01 +
#258000000
0!
0&
b1111 ,
#259000000
1!
b01 $
b1111 %
1&
b01 )
b1111 *
b10 +
#260000000
0!
0"
0&
0'
b1010 ,
#261000000
1!
b10 $
b1010 %
1&
b10 )
b1010 *
b01 +
#262000000
0!
0&
b0101 ,
#263000000
1!
b01 $
b0101 %
1&
b01 )
b0101 *
b00 +
#264000000
0!
0&
b1010 ,
#265000000
1!
b00 $
b1010 %
1&
b00 )
b1010 *
b11 +
#266000000
0!
0&
b1111 ,
#267000000
1!
b11 $
b1111 %
1&
b11 )
b1111 *
b10 +
#268000000
0!
0&
b0000 ,
#269000000
1!
b10 $
b0000 %
1&
b10 )
b0000 *
b01 +
#270000000
0!
0&
b0101 ,
#271000000
1!
b01 $
b0101 %
1&
b01 )
b0101 *
b00 +
#272000000
0!
0&
b1010 ,
#273000000
1!
b00 $
b1010 %
1&
b00 )
b1010 *
b11 +
#274000000
0!
0&
b1111 ,
#275000000
1!
b11 $
b1111 %
1&
b11 )
b1111 *
b10 +
#276000000
0!
0&
b0000 ,
#277000000
1!
b10 $
b0000 %
1&
b10 )
b0000 *
b01 +
#278000000
0!
0&
b0101 ,
#279000000
1!
b01 $
b0101 %
1&
b01 )
b0101 *
b00 +
#280000000
0!
1"
0&
1'
b1010 ,
#281000000
1!
b00 $
b1010 %
1&
b00 )
b1010 *
b01 +
#282000000
0!
0&
b1111 ,
#283000000
1!
b01 $
b1111 %
1&
b01 )
b1111 *
b10 +
#284000000
0!
0&
b1010 ,
#285000000
1!
b10 $
b1010 %
1&
b10 )
b1010 *
b11 +
#286000000
0!
0&
b0101 ,
#287000000
1!
b11 $
b0101 %
1&
b11 )
b0101 *
b00 +
#288000000
0!
0&
b0000 ,
#289000000
1!
b00 $
b0000 %
1&
b00 )
b0000 *
b01 +
#290000000
0!
0&
b1111 ,
#291000000
1!
b01 $
b1111 %
1&
b01 )
b1111 *
b10 +
#292000000
0!
0&
b1010 ,
#293000000
1!
b10 $
b1010 %
1&
b10 )
b1010 *
b11 +
#294000000
0!
0&
b0101 ,
#295000000
1!
b11 $
b0101 %
1&
b11 )
b0101 *
b00 +
#296000000
0!
0&
b0000 ,
#297000000
1!
b00 $
b0000 %
1&
b00 )
b0000 *
b01 +
#298000000
0!
0&
b1111 ,
#299000000
1!
b01 $
b1111 %
1&
b01 )
b1111 *
b10 +
#300000000
0!
0"
0&
0'
b1010 ,
#301000000
1!
b10 $
b1010 %
1&
b10 )
b1010 *
b01 +
#302000000
0!
0&
b0101 ,
#303000000
1!
b01 $
b0101 %
1&
b01 )
b0101 *
b00 +
#304000000
0!
0&
b1010 ,
#305000000
1!
b00 $
b1010 %
1&
b00 )
b1010 *
b11 +
#306000000
0!
0&
b1111 ,
#307000000
1!
b11 $
b1111 %
1&
b11 )
b1111 *
b10 +
#308000000
0!
0&
b0000 ,
#309000000
1!
b10 $
b0000 %
1&
b10 )
b0000 *
b01 +
#310000000
0!
0&
b0101 ,
#311000000
1!
b01 $
b0101 %
1&
b01 )
b0101 *
b00 +
#312000000
0!
0&
b1010 ,
#313000000
1!
b00 $
b1010 %
1&
b00 )
b1010 *
b11 +
#314000000
0!
0&
b1111 ,
#315000000
1!
b11 $
b1111 %
1&
b11 )
b1111 *
b10 +
#316000000
0!
0&
b0000 ,
#317000000
1!
b10 $
b0000 %
1&
b10 )
b0000 *
b01 +
#318000000
0!
0&
b0101 ,
#319000000
1!
b01 $
b0101 %
1&
b01 )
b0101 *
b00 +
#320000000
0!
1"
0&
1'
b1010 ,
#321000000
1!
b00 $
b1010 %
1&
b00 )
b1010 *
b01 +
#322000000
0!
0&
b1111 ,
#323000000
1!
b01 $
b1111 %
1&
b01 )
b1111 *
b10 +
#324000000
0!
0&
b1010 ,
#325000000
1!
b10 $
b1010 %
1&
b10 )
b1010 *
b11 +
#326000000
0!
0&
b0101 ,
#327000000
1!
b11 $
b0101 %
1&
b11 )
b0101 *
b00 +
#328000000
0!
0&
b0000 ,
#329000000
1!
b00 $
b0000 %
1&
b00 )
b0000 *
b01 +
#330000000
0!
0&
b1111 ,
#331000000
1!
b01 $
b1111 %
1&
b01 )
b1111 *
b10 +
#332000000
0!
0&
b1010 ,
#333000000
1!
b10 $
b1010 %
1&
b10 )
b1010 *
b11 +
#334000000
0!
0&
b0101 ,
#335000000
1!
b11 $
b0101 %
1&
b11 )
b0101 *
b00 +
#336000000
0!
0&
b0000 ,
#337000000
1!
b00 $
b0000 %
1&
b00 )
b0000 *
b01 +
#338000000
0!
0&
b1111 ,
#339000000
1!
b01 $
b1111 %
1&
b01 )
b1111 *
b10 +
#340000000
0!
0"
0&
0'
b1010 ,
#341000000
1!
b10 $
b1010 %
1&
b10 )
b1010 *
b01 +
#342000000
0!
0&
b0101 ,
#343000000
1!
b01 $
b0101 %
1&
b01 )
b0101 *
b00 +
#344000000
0!
0&
b1010 ,
#345000000
1!
b00 $
b1010 %
1&
b00 )
b1010 *
b11 +
#346000000
0!
0&
b1111 ,
#347000000
1!
b11 $
b1111 %
1&
b11 )
b1111 *
b10 +
#348000000
0!
0&
b0000 ,
#349000000
1!
b10 $
b0000 %
1&
b10 )
b0000 *
b01 +
#350000000
0!
0&
b0101 ,
#351000000
1!
b01 $
b0101 %
1&
b01 )
b0101 *
b00 +
#352000000
0!
0&
b1010 ,
#353000000
1!
b00 $
b1010 %
1&
b00 )
b1010 *
b11 +
#354000000
0!
0&
b1111 ,
#355000000
1!
b11 $
b1111 %
1&
b11 )
b1111 *
b10 +
#356000000
0!
0&
b0000 ,
#357000000
1!
b10 $
b0000 %
1&
b10 )
b0000 *
b01 +
#358000000
0!
0&
b0101 ,
#359000000
1!
b01 $
b0101 %
1&
b01 )
b0101 *
b00 +
#360000000
0!
1"
0&
1'
b1010 ,
#361000000
1!
b00 $
b1010 %
1&
b00 )
b1010 *
b01 +
#362000000
0!
0&
b1111 ,
#363000000
1!
b01 $
b1111 %
1&
b01 )
b1111 *
b10 +
#364000000
0!
0&
b1010 ,
#365000000
1!
b10 $
b1010 %
1&
b10 )
b1010 *
b11 +
#366000000
0!
0&
b0101 ,
#367000000
1!
b11 $
b0101 %
1&
b11 )
b0101 *
b00 +
#368000000
0!
0&
b0000 ,
#369000000
1!
b00 $
b0000 %
1&
b00 )
b0000 *
b01 +
#370000000
0!
0&
b1111 ,
#371000000
1!
b01 $
b1111 %
1&
b01 )
b1111 *
b10 +
#372000000
0!
0&
b1010 ,
#373000000
1!
b10 $
b1010 %
1&
b10 )
b1010 *
b11 +
#374000000
0!
0&
b0101 ,
#375000000
1!
b11 $
b0101 %
1&
b11 )
b0101 *
b00 +
#376000000
0!
0&
b0000 ,
#377000000
1!
b00 $
b0000 %
1&
b00 )
b0000 *
b01 +
#378000000
0!
0&
b1111 ,
#379000000
1!
b01 $
b1111 %
1&
b01 )
b1111 *
b10 +
#380000000
0!
0"
0&
0'
b1010 ,
#381000000
1!
b10 $
b1010 %
1&
b10 )
b1010 *
b01 +
#382000000
0!
0&
b0101 ,
#383000000
1!
b01 $
b0101 %
1&
b01 )
b0101 *
b00 +
#384000000
0!
0&
b1010 ,
#385000000
1!
b00 $
b1010 %
1&
b00 )
b1010 *
b11 +
#386000000
0!
0&
b1111 ,
#387000000
1!
b11 $
b1111 %
1&
b11 )
b1111 *
b10 +
#388000000
0!
0&
b0000 ,
#389000000
1!
b10 $
b0000 %
1&
b10 )
b0000 *
b01 +
#390000000
0!
0&
b0101 ,
#391000000
1!
b01 $
b0101 %
1&
b01 )
b0101 *
b00 +
#392000000
0!
0&
b1010 ,
#393000000
1!
b00 $
b1010 %
1&
b00 )
b1010 *
b11 +
#394000000
0!
0&
b1111 ,
#395000000
1!
b11 $
b1111 %
1&
b11 )
b1111 *
b10 +
#396000000
0!
0&
b0000 ,
#397000000
1!
b10 $
b0000 %
1&
b10 )
b0000 *
b01 +
#398000000
0!
0&
b0101 ,
#399000000
1!
b01 $
b0101 %
1&
b01 )
b0101 *
b00 +
#400000000
0!
1"
0&
1'
b1010 ,
#401000000
1!
b00 $
b1010 %
1&
b00 )
b1010 *
b01 +
#402000000
0!
0&
b1111 ,
#403000000
1!
b01 $
b1111 %
1&
b01 )
b1111 *
b10 +
#404000000
0!
0&
b1010 ,
#405000000
1!
b10 $
b1010 %
1&
b10 )
b1010 *
b11 +
#406000000
0!
0&
b0101 ,
#407000000
1!
b11 $
b0101 %
1&
b11 )
b0101 *
b00 +
#408000000
0!
0&
b0000 ,
#409000000
1!
b00 $
b0000 %
1&
b00 )
b0000 *
b01 +
#410000000
0!
0&
b1111 ,
#411000000
1!
b01 $
b1111 %
1&
b01 )
b1111 *
b10 +
#412000000
0!
0&
b1010 ,
#413000000
1!
b10 $
b1010 %
1&
b10 )
b1010 *
b11 +
#414000000
0!
0&
b0101 ,
#415000000
1!
b11 $
b0101 %
1&
b11 )
b0101 *
b00 +
#416000000
0!
0&
b0000 ,
#417000000
1!
b00 $
b0000 %
1&
b00 )
b0000 *
b01 +
#418000000
0!
0&
b1111 ,
#419000000
1!
b01 $
b1111 %
1&
b01 )
b1111 *
b10 +
#420000000
0!
0"
0&
0'
b1010 ,
#421000000
1!
b10 $
b1010 %
1&
b10 )
b1010 *
b01 +
#422000000
0!
0&
b0101 ,
#423000000
1!
b01 $
b0101 %
1&
b01 )
b0101 *
b00 +
#424000000
0!
0&
b1010 ,
#425000000
1!
b00 $
b1010 %
1&
b00 )
b1010 *
b11 +
#426000000
0!
0&
b1111 ,
#427000000
1!
b11 $
b1111 %
1&
b11 )
b1111 *
b10 +
#428000000
0!
0&
b0000 ,
#429000000
1!
b10 $
b0000 %
1&
b10 )
b0000 *
b01 +
#430000000
0!
0&
b0101 ,
#431000000
1!
b01 $
b0101 %
1&
b01 )
b0101 *
b00 +
#432000000
0!
0&
b1010 ,
#433000000
1!
b00 $
b1010 %
1&
b00 )
b1010 *
b11 +
#434000000
0!
0&
b1111 ,
#435000000
1!
b11 $
b1111 %
1&
b11 )
b1111 *
b10 +
#436000000
0!
0&
b0000 ,
#437000000
1!
b10 $
b0000 %
1&
b10 )
b0000 *
b01 +
#438000000
0!
0&
b0101 ,
#439000000
1!
b01 $
b0101 %
1&
b01 )
b0101 *
b00 +
#440000000
0!
1"
0&
1'
b1010 ,
#441000000
1!
b00 $
b1010 %
1&
b00 )
b1010 *
b01 +
#442000000
0!
0&
b1111 ,
#443000000
1!
b01 $
b1111 %
1&
b01 )
b1111 *
b10 +
#444000000
0!
0&
b1010 ,
#445000000
1!
b10 $
b1010 %
1&
b10 )
b1010 *
b11 +
#446000000
0!
0&
b0101 ,
#447000000
1!
b11 $
b0101 %
1&
b11 )
b0101 *
b00 +
#448000000
0!
0&
b0000 ,
#449000000
1!
b00 $
b0000 %
1&
b00 )
b0000 *
b01 +
#450000000
0!
0&
b1111 ,
#451000000
1!
b01 $
b1111 %
1&
b01 )
b1111 *
b10 +
#452000000
0!
0&
b1010 ,
#453000000
1!
b10 $
b1010 %
1&
b10 )
b1010 *
b11 +
#454000000
0!
0&
b0101 ,
#455000000
1!
b11 $
b0101 %
1&
b11 )
b0101 *
b00 +
#456000000
0!
0&
b0000 ,
#457000000
1!
b00 $
b0000 %
1&
b00 )
b0000 *
b01 +
#458000000
0!
0&
b1111 ,
#459000000
1!
b01 $
b1111 %
1&
b01 )
b1111 *
b10 +
