FPGA/FPGA 02/skeleton3c/pwm.m.vhd
---------------------------------------
-- lecture 02 shift register
-- just forwarding the signal
----------------------------------------

library ieee;
use ieee.std_logic_1164.all;
use ieee.numeric_std.all;

----------------------------------------

entity pwm is
    generic(
        DATA_WIDTH    :  integer := 8
    );
    port(   
        i_sl_CLK      :  in  std_logic;                                 -- clock
	i_sl_reset    :  in std_logic;
        i_slv_en     :  in  std_logic;   -- pwm value
        o_sl_pwm      :  out std_logic_vector(DATA_WIDTH-1 downto 0)    -- pwm output
    );
end pwm;  

----------------------------------------

architecture behavior of pwm is
signal slv_pwm_cnt : std_logic_vector(DATA_WIDTH-1 downto 0) := "00000001";
signal reseter : std_logic_vector(DATA_WIDTH-1 downto 0) := "00000001";

begin
    process(i_sl_CLK)
    begin
	if (i_slv_en = '1') then
            if rising_edge(i_sl_CLK) then
		    slv_pwm_cnt <= slv_pwm_cnt(8-2 downto 0) & slv_pwm_cnt(8-1);
		    o_sl_pwm <= slv_pwm_cnt;
            end if;
	end if;
	if rising_edge(i_sl_reset) then
	    slv_pwm_cnt <= reseter;
	end if;
    end process;

end behavior;

------------------------------------------

FPGA/FPGA 02/skeleton3c/pwm.tb.vhd
library ieee;
use ieee.std_logic_1164.all;

ENTITY pwm_tb IS
END pwm_tb;

ARCHITECTURE tb OF pwm_tb IS 

    COMPONENT pwm is
    generic(
        DATA_WIDTH    :  integer := 8
    );
        port(   
            i_sl_CLK      :  in  std_logic;                      -- clock
	    i_sl_reset    :  in std_logic;
            i_slv_en      :  in  std_logic;    -- pwm value
            o_sl_pwm      :  out std_logic_vector(DATA_WIDTH-1 downto 0)   -- output
        );
    end COMPONENT;

    -- "local" signals
    constant DATA_WIDTH : integer := 8;
    -- signals for UUT
    -- input 
    signal CLK    : std_logic := '0';

    signal i_slv_en : std_logic := '0';
    signal reset  :  std_logic := '0';
    -- ouput
    signal o_sl_pwm : std_logic_vector(DATA_WIDTH-1 downto 0) := "00000001";

BEGIN 
    -- Instance of unit under test.
    uut: pwm 
    PORT MAP (
        i_sl_CLK    => CLK,
        i_slv_en   => i_slv_en,
        o_sl_pwm    => o_sl_pwm,
	i_sl_reset   => reset
    );

-------------------------------------------------------------------------------
    -- test bench definition.
    tb_CLK :process
    begin
        CLK <= '0';
        wait for 1 ns;
        CLK <= '1';
        wait for 1 ns;
    end process;

    tb_en :process
    begin
        i_slv_en <= '0';
        wait for  10 ns;
        i_slv_en <= '1';
        wait for 30 ns;
    end process;

    tb_reset :process
    begin
        reset <= '0';
        wait for 50 ns;
        reset <= '1';
        wait for 1 ns;
    end process;
END;

FPGA/FPGA 02/skeleton3c/pwm.vcd
$date
  Wed Dec  9 09:31:01 2020
$end
$version
  GHDL v0
$end
$timescale
  1 fs
$end
$scope module standard $end
$upscope $end
$scope module textio $end
$upscope $end
$scope module std_logic_1164 $end
$upscope $end
$scope module numeric_std $end
$upscope $end
$scope module pwm_tb $end
$var reg 1 ! clk $end
$var reg 1 " i_slv_en $end
$var reg 1 # reset $end
$var reg 8 $ o_sl_pwm[7:0] $end
$scope module uut $end
$var reg 1 % i_sl_clk $end
$var reg 1 & i_sl_reset $end
$var reg 1 ' i_slv_en $end
$var reg 8 ( o_sl_pwm[7:0] $end
$var reg 8 ) slv_pwm_cnt[7:0] $end
$var reg 8 * reseter[7:0] $end
$upscope $end
$upscope $end
$enddefinitions $end
#0
0!
0"
0#
bUUUUUUUU $
0%
0&
0'
bUUUUUUUU (
b00000001 )
b00000001 *
#1000000
1!
1%
#2000000
0!
0%
#3000000
1!
1%
#4000000
0!
0%
#5000000
1!
1%
#6000000
0!
0%
#7000000
1!
1%
#8000000
0!
0%
#9000000
1!
1%
#10000000
0!
1"
0%
1'
#11000000
1!
b00000001 $
1%
b00000001 (
b00000010 )
#12000000
0!
0%
#13000000
1!
b00000010 $
1%
b00000010 (
b00000100 )
#14000000
0!
0%
#15000000
1!
b00000100 $
1%
b00000100 (
b00001000 )
#16000000
0!
0%
#17000000
1!
b00001000 $
1%
b00001000 (
b00010000 )
#18000000
0!
0%
#19000000
1!
b00010000 $
1%
b00010000 (
b00100000 )
#20000000
0!
0%
#21000000
1!
b00100000 $
1%
b00100000 (
b01000000 )
#22000000
0!
0%
#23000000
1!
b01000000 $
1%
b01000000 (
b10000000 )
#24000000
0!
0%
#25000000
1!
b10000000 $
1%
b10000000 (
b00000001 )
#26000000
0!
0%
#27000000
1!
b00000001 $
1%
b00000001 (
b00000010 )
#28000000
0!
0%
#29000000
1!
b00000010 $
1%
b00000010 (
b00000100 )
#30000000
0!
0%
#31000000
1!
b00000100 $
1%
b00000100 (
b00001000 )
#32000000
0!
0%
#33000000
1!
b00001000 $
1%
b00001000 (
b00010000 )
#34000000
0!
0%
#35000000
1!
b00010000 $
1%
b00010000 (
b00100000 )
#36000000
0!
0%
#37000000
1!
b00100000 $
1%
b00100000 (
b01000000 )
#38000000
0!
0%
#39000000
1!
b01000000 $
1%
b01000000 (
b10000000 )
#40000000
0!
0"
0%
0'
#41000000
1!
1%
#42000000
0!
0%
#43000000
1!
1%
#44000000
0!
0%
#45000000
1!
1%
#46000000
0!
0%
#47000000
1!
1%
#48000000
0!
0%
#49000000
1!
1%
#50000000
0!
1"
1#
0%
1&
1'
b00000001 )
#51000000
1!
0#
b00000001 $
1%
0&
b00000001 (
b00000010 )
#52000000
0!
0%
#53000000
1!
b00000010 $
1%
b00000010 (
b00000100 )
#54000000
0!
0%
#55000000
1!
b00000100 $
1%
b00000100 (
b00001000 )
#56000000
0!
0%
#57000000
1!
b00001000 $
1%
b00001000 (
b00010000 )
#58000000
0!
0%
#59000000
1!
b00010000 $
1%
b00010000 (
b00100000 )
#60000000
0!
0%
#61000000
1!
b00100000 $
1%
b00100000 (
b01000000 )
#62000000
0!
0%
#63000000
1!
b01000000 $
1%
b01000000 (
b10000000 )
#64000000
0!
0%
#65000000
1!
b10000000 $
1%
b10000000 (
b00000001 )
#66000000
0!
0%
#67000000
1!
b00000001 $
1%
b00000001 (
b00000010 )
#68000000
0!
0%
#69000000
1!
b00000010 $
1%
b00000010 (
b00000100 )
#70000000
0!
0%
#71000000
1!
b00000100 $
1%
b00000100 (
b00001000 )
#72000000
0!
0%
#73000000
1!
b00001000 $
1%
b00001000 (
b00010000 )
#74000000
0!
0%
#75000000
1!
b00010000 $
1%
b00010000 (
b00100000 )
#76000000
0!
0%
#77000000
1!
b00100000 $
1%
b00100000 (
b01000000 )
#78000000
0!
0%
#79000000
1!
b01000000 $
1%
b01000000 (
b10000000 )
#80000000
0!
0"
0%
0'
#81000000
1!
1%
#82000000
0!
0%
#83000000
1!
1%
#84000000
0!
0%
#85000000
1!
1%
#86000000
0!
0%
#87000000
1!
1%
#88000000
0!
0%
#89000000
1!
1%
#90000000
0!
1"
0%
1'
#91000000
1!
b10000000 $
1%
b10000000 (
b00000001 )
#92000000
0!
0%
#93000000
1!
b00000001 $
1%
b00000001 (
b00000010 )
#94000000
0!
0%
#95000000
1!
b00000010 $
1%
b00000010 (
b00000100 )
#96000000
0!
0%
#97000000
1!
b00000100 $
1%
b00000100 (
b00001000 )
#98000000
0!
0%
#99000000
1!
b00001000 $
1%
b00001000 (
b00010000 )
#100000000
0!
0%
#101000000
1!
1#
b00010000 $
1%
1&
b00010000 (
b00000001 )
#102000000
0!
0#
0%
0&
#103000000
1!
b00000001 $
1%
b00000001 (
b00000010 )
#104000000
0!
0%
#105000000
1!
b00000010 $
1%
b00000010 (
b00000100 )
#106000000
0!
0%
#107000000
1!
b00000100 $
1%
b00000100 (
b00001000 )
#108000000
0!
0%
#109000000
1!
b00001000 $
1%
b00001000 (
b00010000 )
#110000000
0!
0%
#111000000
1!
b00010000 $
1%
b00010000 (
b00100000 )
#112000000
0!
0%
#113000000
1!
b00100000 $
1%
b00100000 (
b01000000 )
#114000000
0!
0%
#115000000
1!
b01000000 $
1%
b01000000 (
b10000000 )
#116000000
0!
0%
#117000000
1!
b10000000 $
1%
b10000000 (
b00000001 )
#118000000
0!
0%
#119000000
1!
b00000001 $
1%
b00000001 (
b00000010 )
#120000000
0!
0"
0%
0'
#121000000
1!
1%
#122000000
0!
0%
#123000000
1!
1%
#124000000
0!
0%
#125000000
1!
1%
#126000000
0!
0%
#127000000
1!
1%
#128000000
0!
0%
#129000000
1!
1%
#130000000
0!
1"
0%
1'
#131000000
1!
b00000010 $
1%
b00000010 (
b00000100 )
#132000000
0!
0%
#133000000
1!
b00000100 $
1%
b00000100 (
b00001000 )
#134000000
0!
0%
#135000000
1!
b00001000 $
1%
b00001000 (
b00010000 )
#136000000
0!
0%
#137000000
1!
b00010000 $
1%
b00010000 (
b00100000 )
#138000000
0!
0%
#139000000
1!
b00100000 $
1%
b00100000 (
b01000000 )
#140000000
0!
0%
#141000000
1!
b01000000 $
1%
b01000000 (
b10000000 )
#142000000
0!
0%
#143000000
1!
b10000000 $
1%
b10000000 (
b00000001 )
#144000000
0!
0%
#145000000
1!
b00000001 $
1%
b00000001 (
b00000010 )
#146000000
0!
0%
#147000000
1!
b00000010 $
1%
b00000010 (
b00000100 )
#148000000
0!
0%
#149000000
1!
b00000100 $
1%
b00000100 (
b00001000 )
#150000000
0!
0%
#151000000
1!
b00001000 $
1%
b00001000 (
b00010000 )
#152000000
0!
1#
0%
1&
b00000001 )
#153000000
1!
0#
b00000001 $
1%
0&
b00000001 (
b00000010 )
#154000000
0!
0%
#155000000
1!
b00000010 $
1%
b00000010 (
b00000100 )
#156000000
0!
0%
#157000000
1!
b00000100 $
1%
b00000100 (
b00001000 )
#158000000
0!
0%
#159000000
1!
b00001000 $
1%
b00001000 (
b00010000 )
#160000000
0!
0"
0%
0'
#161000000
1!
1%
#162000000
0!
0%
#163000000
1!
1%
#164000000
0!
0%
#165000000
1!
1%
#166000000
0!
0%
#167000000
1!
1%
#168000000
0!
0%
#169000000
1!
1%
#170000000
0!
1"
0%
1'
#171000000
1!
b00010000 $
1%
b00010000 (
b00100000 )
#172000000
0!
0%
#173000000
1!
b00100000 $
1%
b00100000 (
b01000000 )
#174000000
0!
0%
#175000000
1!
b01000000 $
1%
b01000000 (
b10000000 )
#176000000
0!
0%
#177000000
1!
b10000000 $
1%
b10000000 (
b00000001 )
#178000000
0!
0%
#179000000
1!
b00000001 $
1%
b00000001 (
b00000010 )
#180000000
0!
0%
#181000000
1!
b00000010 $
1%
b00000010 (
b00000100 )
#182000000
0!
0%
#183000000
1!
b00000100 $
1%
b00000100 (
b00001000 )
#184000000
0!
0%
#185000000
1!
b00001000 $
1%
b00001000 (
b00010000 )
#186000000
0!
0%
#187000000
1!
b00010000 $
1%
b00010000 (
b00100000 )
#188000000
0!
0%
#189000000
1!
b00100000 $
1%
b00100000 (
b01000000 )
#190000000
0!
0%
#191000000
1!
b01000000 $
1%
b01000000 (
b10000000 )
#192000000
0!
0%
#193000000
1!
b10000000 $
1%
b10000000 (
b00000001 )
#194000000
0!
0%
#195000000
1!
b00000001 $
1%
b00000001 (
b00000010 )
#196000000
0!
0%
#197000000
1!
b00000010 $
1%
b00000010 (
b00000100 )
#198000000
0!
0%
#199000000
1!
b00000100 $
1%
b00000100 (
b00001000 )
#200000000
0!
0"
0%
0'
#201000000
1!
1%
#202000000
0!
0%
#203000000
1!
1#
1%
1&
b00000001 )
#204000000
0!
0#
0%
0&
#205000000
1!
1%
#206000000
0!
0%
#207000000
1!
1%
#208000000
0!
0%
#209000000
1!
1%
#210000000
0!
1"
0%
1'
#211000000
1!
b00000001 $
1%
b00000001 (
b00000010 )
#212000000
0!
0%
#213000000
1!
b00000010 $
1%
b00000010 (
b00000100 )
#214000000
0!
0%
#215000000
1!
b00000100 $
1%
b00000100 (
b00001000 )
#216000000
0!
0%
#217000000
1!
b00001000 $
1%
b00001000 (
b00010000 )
#218000000
0!
0%
#219000000
1!
b00010000 $
1%
b00010000 (
b00100000 )
#220000000
0!
0%
#221000000
1!
b00100000 $
1%
b00100000 (
b01000000 )
#222000000
0!
0%
#223000000
1!
b01000000 $
1%
b01000000 (
b10000000 )
#224000000
0!
0%
#225000000
1!
b10000000 $
1%
b10000000 (
b00000001 )
#226000000
0!
0%
#227000000
1!
b00000001 $
1%
b00000001 (
b00000010 )
#228000000
0!
0%
#229000000
1!
b00000010 $
1%
b00000010 (
b00000100 )
#230000000
0!
0%
#231000000
1!
b00000100 $
1%
b00000100 (
b00001000 )
#232000000
0!
0%
#233000000
1!
b00001000 $
1%
b00001000 (
b00010000 )
#234000000
0!
0%
#235000000
1!
b00010000 $
1%
b00010000 (
b00100000 )
#236000000
0!
0%
#237000000
1!
b00100000 $
1%
b00100000 (
b01000000 )
#238000000
0!
0%
#239000000
1!
b01000000 $
1%
b01000000 (
b10000000 )
#240000000
0!
0"
0%
0'
#241000000
1!
1%
#242000000
0!
0%
#243000000
1!
1%
#244000000
0!
0%
#245000000
1!
1%
#246000000
0!
0%
#247000000
1!
1%
#248000000
0!
0%
#249000000
1!
1%
#250000000
0!
1"
0%
1'
#251000000
1!
b10000000 $
1%
b10000000 (
b00000001 )
#252000000
0!
0%
#253000000
1!
b00000001 $
1%
b00000001 (
b00000010 )
#254000000
0!
1#
0%
1&
b00000001 )
#255000000
1!
0#
1%
0&
b00000010 )
#256000000
0!
0%
#257000000
1!
b00000010 $
1%
b00000010 (
b00000100 )
#258000000
0!
0%
#259000000
1!
b00000100 $
1%
b00000100 (
b00001000 )
#260000000
0!
0%
#261000000
1!
b00001000 $
1%
b00001000 (
b00010000 )
#262000000
0!
0%
#263000000
1!
b00010000 $
1%
b00010000 (
b00100000 )
#264000000
0!
0%
#265000000
1!
b00100000 $
1%
b00100000 (
b01000000 )
#266000000
0!
0%
#267000000
1!
b01000000 $
1%
b01000000 (
b10000000 )
#268000000
0!
0%
#269000000
1!
b10000000 $
1%
b10000000 (
b00000001 )
#270000000
0!
0%
#271000000
1!
b00000001 $
1%
b00000001 (
b00000010 )
#272000000
0!
0%
#273000000
1!
b00000010 $
1%
b00000010 (
b00000100 )
#274000000
0!
0%
#275000000
1!
b00000100 $
1%
b00000100 (
b00001000 )
#276000000
0!
0%
#277000000
1!
b00001000 $
1%
b00001000 (
b00010000 )
#278000000
0!
0%
#279000000
1!
b00010000 $
1%
b00010000 (
b00100000 )
#280000000
0!
0"
0%
0'
#281000000
1!
1%
#282000000
0!
0%
#283000000
1!
1%
#284000000
0!
0%
#285000000
1!
1%
#286000000
0!
0%
#287000000
1!
1%
#288000000
0!
0%
#289000000
1!
1%
#290000000
0!
1"
0%
1'
#291000000
1!
b00100000 $
1%
b00100000 (
b01000000 )
#292000000
0!
0%
#293000000
1!
b01000000 $
1%
b01000000 (
b10000000 )
#294000000
0!
0%
#295000000
1!
b10000000 $
1%
b10000000 (
b00000001 )
#296000000
0!
0%
#297000000
1!
b00000001 $
1%
b00000001 (
b00000010 )
#298000000
0!
0%
#299000000
1!
b00000010 $
1%
b00000010 (
b00000100 )
#300000000
0!
0%
#301000000
1!
b00000100 $
1%
b00000100 (
b00001000 )
#302000000
0!
0%
#303000000
1!
b00001000 $
1%
b00001000 (
b00010000 )
#304000000
0!
0%
#305000000
1!
1#
b00010000 $
1%
1&
b00010000 (
b00000001 )
#306000000
0!
0#
0%
0&
#307000000
1!
b00000001 $
1%
b00000001 (
b00000010 )
#308000000
0!
0%
#309000000
1!
b00000010 $
1%
b00000010 (
b00000100 )
#310000000
0!
0%
#311000000
1!
b00000100 $
1%
b00000100 (
b00001000 )
#312000000
0!
0%
#313000000
1!
b00001000 $
1%
b00001000 (
b00010000 )
#314000000
0!
0%
#315000000
1!
b00010000 $
1%
b00010000 (
b00100000 )
#316000000
0!
0%
#317000000
1!
b00100000 $
1%
b00100000 (
b01000000 )
#318000000
0!
0%
#319000000
1!
b01000000 $
1%
b01000000 (
b10000000 )
#320000000
0!
0"
0%
0'
#321000000
1!
1%
#322000000
0!
0%
#323000000
1!
1%
#324000000
0!
0%
#325000000
1!
1%
#326000000
0!
0%
#327000000
1!
1%
#328000000
0!
0%
#329000000
1!
1%
#330000000
0!
1"
0%
1'
#331000000
1!
b10000000 $
1%
b10000000 (
b00000001 )
#332000000
0!
0%
#333000000
1!
b00000001 $
1%
b00000001 (
b00000010 )
#334000000
0!
0%
#335000000
1!
b00000010 $
1%
b00000010 (
b00000100 )
#336000000
0!
0%
#337000000
1!
b00000100 $
1%
b00000100 (
b00001000 )
#338000000
0!
0%
#339000000
1!
b00001000 $
1%
b00001000 (
b00010000 )
#340000000
0!
0%
#341000000
1!
b00010000 $
1%
b00010000 (
b00100000 )
#342000000
0!
0%
#343000000
1!
b00100000 $
1%
b00100000 (
b01000000 )
#344000000
0!
0%
#345000000
1!
b01000000 $
1%
b01000000 (
b10000000 )
#346000000
0!
0%
#347000000
1!
b10000000 $
1%
b10000000 (
b00000001 )
#348000000
0!
0%
#349000000
1!
b00000001 $
1%
b00000001 (
b00000010 )
#350000000
0!
0%
#351000000
1!
b00000010 $
1%
b00000010 (
b00000100 )
#352000000
0!
0%
#353000000
1!
b00000100 $
1%
b00000100 (
b00001000 )
#354000000
0!
0%
#355000000
1!
b00001000 $
1%
b00001000 (
b00010000 )
#356000000
0!
1#
0%
1&
b00000001 )
#357000000
1!
0#
b00000001 $
1%
0&
b00000001 (
b00000010 )
#358000000
0!
0%
#359000000
1!
b00000010 $
1%
b00000010 (
b00000100 )
#360000000
0!
0"
0%
0'
#361000000
1!
1%
#362000000
0!
0%
#363000000
1!
1%
#364000000
0!
0%
#365000000
1!
1%
#366000000
0!
0%
#367000000
1!
1%
#368000000
0!
0%
#369000000
1!
1%
#370000000
0!
1"
0%
1'
#371000000
1!
b00000100 $
1%
b00000100 (
b00001000 )
#372000000
0!
0%
#373000000
1!
b00001000 $
1%
b00001000 (
b00010000 )
#374000000
0!
0%
#375000000
1!
b00010000 $
1%
b00010000 (
b00100000 )
#376000000
0!
0%
#377000000
1!
b00100000 $
1%
b00100000 (
b01000000 )
#378000000
0!
0%
#379000000
1!
b01000000 $
1%
b01000000 (
b10000000 )
#380000000
0!
0%
#381000000
1!
b10000000 $
1%
b10000000 (
b00000001 )
#382000000
0!
0%
#383000000
1!
b00000001 $
1%
b00000001 (
b00000010 )
#384000000
0!
0%
#385000000
1!
b00000010 $
1%
b00000010 (
b00000100 )
#386000000
0!
0%
#387000000
1!
b00000100 $
1%
b00000100 (
b00001000 )
#388000000
0!
0%
#389000000
1!
b00001000 $
1%
b00001000 (
b00010000 )
#390000000
0!
0%
#391000000
1!
b00010000 $
1%
b00010000 (
b00100000 )
#392000000
0!
0%
#393000000
1!
b00100000 $
1%
b00100000 (
b01000000 )
#394000000
0!
0%
#395000000
1!
b01000000 $
1%
b01000000 (
b10000000 )
#396000000
0!
0%
#397000000
1!
b10000000 $
1%
b10000000 (
b00000001 )
#398000000
0!
0%
#399000000
1!
b00000001 $
1%
b00000001 (
b00000010 )
#400000000
0!
0"
0%
0'
#401000000
1!
1%
#402000000
0!
0%
#403000000
1!
1%
#404000000
0!
0%
#405000000
1!
1%
#406000000
0!
0%
#407000000
1!
1#
1%
1&
b00000001 )
#408000000
0!
0#
0%
0&
#409000000
1!
1%
#410000000
0!
1"
0%
1'
#411000000
1!
1%
b00000010 )
#412000000
0!
0%
#413000000
1!
b00000010 $
1%
b00000010 (
b00000100 )
#414000000
0!
0%
#415000000
1!
b00000100 $
1%
b00000100 (
b00001000 )
#416000000
0!
0%
#417000000
1!
b00001000 $
1%
b00001000 (
b00010000 )
#418000000
0!
0%
#419000000
1!
b00010000 $
1%
b00010000 (
b00100000 )
#420000000
0!
0%
#421000000
1!
b00100000 $
1%
b00100000 (
b01000000 )
#422000000
0!
0%
#423000000
1!
b01000000 $
1%
b01000000 (
b10000000 )
#424000000
0!
0%
#425000000
1!
b10000000 $
1%
b10000000 (
b00000001 )
#426000000
0!
0%
#427000000
1!
b00000001 $
1%
b00000001 (
b00000010 )
#428000000
0!
0%
#429000000
1!
b00000010 $
1%
b00000010 (
b00000100 )
#430000000
0!
0%
#431000000
1!
b00000100 $
1%
b00000100 (
b00001000 )
#432000000
0!
0%
#433000000
1!
b00001000 $
1%
b00001000 (
b00010000 )
#434000000
0!
0%
#435000000
1!
b00010000 $
1%
b00010000 (
b00100000 )
#436000000
0!
0%
#437000000
1!
b00100000 $
1%
b00100000 (
b01000000 )
#438000000
0!
0%
#439000000
1!
b01000000 $
1%
b01000000 (
b10000000 )
#440000000
0!
0"
0%
0'
#441000000
1!
1%
#442000000
0!
0%
#443000000
1!
1%
#444000000
0!
0%
#445000000
1!
1%
#446000000
0!
0%
#447000000
1!
1%
#448000000
0!
0%
#449000000
1!
1%
#450000000
0!
1"
0%
1'
#451000000
1!
b10000000 $
1%
b10000000 (
b00000001 )
#452000000
0!
0%
#453000000
1!
b00000001 $
1%
b00000001 (
b00000010 )
#454000000
0!
0%
#455000000
1!
b00000010 $
1%
b00000010 (
b00000100 )
#456000000
0!
0%
#457000000
1!
b00000100 $
1%
b00000100 (
b00001000 )
#458000000
0!
1#
0%
1&
b00000001 )
#459000000
1!
0#
b00000001 $
1%
0&
b00000001 (
b00000010 )
#460000000
0!
0%
#461000000
1!
b00000010 $
1%
b00000010 (
b00000100 )
#462000000
0!
0%
#463000000
1!
b00000100 $
1%
b00000100 (
b00001000 )
#464000000
0!
0%
#465000000
1!
b00001000 $
1%
b00001000 (
b00010000 )
#466000000
0!
0%
#467000000
1!
b00010000 $
1%
b00010000 (
b00100000 )
#468000000
0!
0%
#469000000
1!
b00100000 $
1%
b00100000 (
b01000000 )
#470000000
0!
0%
#471000000
1!
b01000000 $
1%
b01000000 (
b10000000 )
#472000000
0!
0%
#473000000
1!
b10000000 $
1%
b10000000 (
b00000001 )
#474000000
0!
0%
#475000000
1!
b00000001 $
1%
b00000001 (
b00000010 )
#476000000
0!
0%
#477000000
1!
b00000010 $
1%
b00000010 (
b00000100 )
#478000000
0!
0%
#479000000
1!
b00000100 $
1%
b00000100 (
b00001000 )
#480000000
0!
0"
0%
0'
#481000000
1!
1%
#482000000
0!
0%
#483000000
1!
1%
#484000000
0!
0%
#485000000
1!
1%
#486000000
0!
0%
#487000000
1!
1%
#488000000
0!
0%
#489000000
1!
1%
#490000000
0!
1"
0%
1'
#491000000
1!
b00001000 $
1%
b00001000 (
b00010000 )
#492000000
0!
0%
#493000000
1!
b00010000 $
1%
b00010000 (
b00100000 )
#494000000
0!
0%
#495000000
1!
b00100000 $
1%
b00100000 (
b01000000 )
#496000000
0!
0%
#497000000
1!
b01000000 $
1%
b01000000 (
b10000000 )
#498000000
0!
0%
#499000000
1!
b10000000 $
1%
b10000000 (
b00000001 )
#500000000
0!
0%
#501000000
1!
b00000001 $
1%
b00000001 (
b00000010 )
#502000000
0!
0%
#503000000
1!
b00000010 $
1%
b00000010 (
b00000100 )
#504000000
0!
0%
#505000000
1!
b00000100 $
1%
b00000100 (
b00001000 )
#506000000
0!
0%
#507000000
1!
b00001000 $
1%
b00001000 (
b00010000 )
#508000000
0!
0%
#509000000
1!
1#
b00010000 $
1%
1&
b00010000 (
b00000001 )
#510000000
0!
0#
0%
0&
#511000000
1!
b00000001 $
1%
b00000001 (
b00000010 )
#512000000
0!
0%
#513000000
1!
b00000010 $
1%
b00000010 (
b00000100 )
#514000000
0!
0%
#515000000
1!
b00000100 $
1%
b00000100 (
b00001000 )
#516000000
0!
0%
#517000000
1!
b00001000 $
1%
b00001000 (
b00010000 )
#518000000
0!
0%
#519000000
1!
b00010000 $
1%
b00010000 (
b00100000 )
#520000000
0!
0"
0%
0'
#521000000
1!
1%
#522000000
0!
0%
#523000000
1!
1%
#524000000
0!
0%
#525000000
1!
1%
#526000000
0!
0%
#527000000
1!
1%
#528000000
0!
0%
#529000000
1!
1%
#530000000
0!
1"
0%
1'
#531000000
1!
b00100000 $
1%
b00100000 (
b01000000 )
#532000000
0!
0%
#533000000
1!
b01000000 $
1%
b01000000 (
b10000000 )
#534000000
0!
0%
#535000000
1!
b10000000 $
1%
b10000000 (
b00000001 )
#536000000
0!
0%
#537000000
1!
b00000001 $
1%
b00000001 (
b00000010 )
#538000000
0!
0%
#539000000
1!
b00000010 $
1%
b00000010 (
b00000100 )
#540000000
0!
0%
#541000000
1!
b00000100 $
1%
b00000100 (
b00001000 )
#542000000
0!
0%
#543000000
1!
b00001000 $
1%
b00001000 (
b00010000 )
#544000000
0!
0%
#545000000
1!
b00010000 $
1%
b00010000 (
b00100000 )
#546000000
0!
0%
#547000000
1!
b00100000 $
1%
b00100000 (
b01000000 )
#548000000
0!
0%
#549000000
1!
b01000000 $
1%
b01000000 (
b10000000 )
#550000000
0!
0%
#551000000
1!
b10000000 $
1%
b10000000 (
b00000001 )
#552000000
0!
0%
#553000000
1!
b00000001 $
1%
b00000001 (
b00000010 )
#554000000
0!
0%
#555000000
1!
b00000010 $
1%
b00000010 (
b00000100 )
#556000000
0!
0%
#557000000
1!
b00000100 $
1%
b00000100 (
b00001000 )
#558000000
0!
0%
#559000000
1!
b00001000 $
1%
b00001000 (
b00010000 )
#560000000
0!
0"
1#
0%
1&
0'
b00000001 )
#561000000
1!
0#
1%
0&
#562000000
0!
0%
#563000000
1!
1%
#564000000
0!
0%
#565000000
1!
1%
#566000000
0!
0%
#567000000
1!
1%
#568000000
0!
0%
#569000000
1!
1%
#570000000
0!
1"
0%
1'
#571000000
1!
b00000001 $
1%
b00000001 (
b00000010 )
#572000000
0!
0%
#573000000
1!
b00000010 $
1%
b00000010 (
b00000100 )
#574000000
0!
0%
#575000000
1!
b00000100 $
1%
b00000100 (
b00001000 )
#576000000
0!
0%
#577000000
1!
b00001000 $
1%
b00001000 (
b00010000 )
#578000000
0!
0%
#579000000
1!
b00010000 $
1%
b00010000 (
b00100000 )
#580000000
0!
0%
#581000000
1!
b00100000 $
1%
b00100000 (
b01000000 )
#582000000
0!
0%
#583000000
1!
b01000000 $
1%
b01000000 (
b10000000 )
#584000000
0!
0%
#585000000
1!
b10000000 $
1%
b10000000 (
b00000001 )
#586000000
0!
0%
#587000000
1!
b00000001 $
1%
b00000001 (
b00000010 )
#588000000
0!
0%
#589000000
1!
b00000010 $
1%
b00000010 (
b00000100 )
#590000000
0!
0%
#591000000
1!
b00000100 $
1%
b00000100 (
b00001000 )
#592000000
0!
0%
#593000000
1!
b00001000 $
1%
b00001000 (
b00010000 )
#594000000
0!
0%
#595000000
1!
b00010000 $
1%
b00010000 (
b00100000 )
#596000000
0!
0%
#597000000
1!
b00100000 $
1%
b00100000 (
b01000000 )
#598000000
0!
0%
#599000000
1!
b01000000 $
1%
b01000000 (
b10000000 )
#600000000
0!
0"
0%
0'
#601000000
1!
1%
#602000000
0!
0%
#603000000
1!
1%
#604000000
0!
0%
#605000000
1!
1%
#606000000
0!
0%
#607000000
1!
1%
#608000000
0!
0%
#609000000
1!
1%
#610000000
0!
1"
0%
1'
#611000000
1!
1#
b10000000 $
1%
1&
b10000000 (
b00000001 )
#612000000
0!
0#
0%
0&
#613000000
1!
b00000001 $
1%
b00000001 (
b00000010 )
#614000000
0!
0%
#615000000
1!
b00000010 $
1%
b00000010 (
b00000100 )
#616000000
0!
0%
#617000000
1!
b00000100 $
1%
b00000100 (
b00001000 )
#618000000
0!
0%
#619000000
1!
b00001000 $
1%
b00001000 (
b00010000 )
#620000000
0!
0%
#621000000
1!
b00010000 $
1%
b00010000 (
b00100000 )
#622000000
0!
0%
#623000000
1!
b00100000 $
1%
b00100000 (
b01000000 )
#624000000
0!
0%
#625000000
1!
b01000000 $
1%
b01000000 (
b10000000 )
#626000000
0!
0%
#627000000
1!
b10000000 $
1%
b10000000 (
b00000001 )
#628000000
0!
0%
#629000000
1!
b00000001 $
1%
b00000001 (
b00000010 )
#630000000
0!
0%
#631000000
1!
b00000010 $
1%
b00000010 (
b00000100 )
#632000000
0!
0%
#633000000
1!
b00000100 $
1%
b00000100 (
b00001000 )
#634000000
0!
0%
#635000000
1!
b00001000 $
1%
b00001000 (
b00010000 )
#636000000
0!
0%
#637000000
1!
b00010000 $
1%
b00010000 (
b00100000 )
#638000000
0!
0%
#639000000
1!
b00100000 $
1%
b00100000 (
b01000000 )
#640000000
0!
0"
0%
0'
#641000000
1!
1%
#642000000
0!
0%
#643000000
1!
1%
#644000000
0!
0%
#645000000
1!
1%
#646000000
0!
0%
#647000000
1!
1%
#648000000
0!
0%
#649000000
1!
1%
#650000000
0!
1"
0%
1'
#651000000
1!
b01000000 $
1%
b01000000 (
b10000000 )
#652000000
0!
0%
#653000000
1!
b10000000 $
1%
b10000000 (
b00000001 )
#654000000
0!
0%
#655000000
1!
b00000001 $
1%
b00000001 (
b00000010 )
#656000000
0!
0%
#657000000
1!
b00000010 $
1%
b00000010 (
b00000100 )
#658000000
0!
0%
#659000000
1!
b00000100 $
1%
b00000100 (
b00001000 )
#660000000
0!
0%
#661000000
1!
b00001000 $
1%
b00001000 (
b00010000 )
#662000000
0!
1#
0%
1&
b00000001 )
#663000000
1!
0#
b00000001 $
1%
0&
b00000001 (
b00000010 )
#664000000
0!
0%
#665000000
1!
b00000010 $
1%
b00000010 (
b00000100 )
#666000000
0!
0%
#667000000
1!
b00000100 $
1%
b00000100 (
b00001000 )
#668000000
0!
0%
#669000000
1!
b00001000 $
1%
b00001000 (
b00010000 )
#670000000
0!
0%
#671000000
1!
b00010000 $
1%
b00010000 (
b00100000 )
#672000000
0!
0%
#673000000
1!
b00100000 $
1%
b00100000 (
b01000000 )
#674000000
0!
0%
#675000000
1!
b01000000 $
1%
b01000000 (
b10000000 )
#676000000
0!
0%
#677000000
1!
b10000000 $
1%
b10000000 (
b00000001 )
#678000000
0!
0%
#679000000
1!
b00000001 $
1%
b00000001 (
b00000010 )
#680000000
0!
0"
0%
0'
