FPGA/FPGA 02/a/simple_gate.m.vhd
---------------------------------------
-- lecture 01 simple gate
-- just forwarding the signal
----------------------------------------

library ieee;
use ieee.std_logic_1164.all;

----------------------------------------

entity lecture01 is
port(	
	    i_sl_x : in  std_logic;
	    o_slv_shift : out std_logic_vector(7 downto 0)
);
end lecture01;  

----------------------------------------

architecture behaviour of lecture01 is
	signal shift_reg : std_logic_vector(7 downto 0) := "00000001";
begin

    process(i_sl_x)
    begin
        -- compare to truth table
	if rising_edge(i_sl_x) then
		shift_reg <= shift_reg(6 downto 0) & shift_reg(7);
	end if;
	o_slv_shift <= shift_reg;
    end process;
end behaviour;

------------------------------------------

FPGA/FPGA 02/a/simple_gate.tb.vhd
library ieee;
use ieee.std_logic_1164.all;

ENTITY lecture01_tb IS
END lecture01_tb;

ARCHITECTURE tb OF lecture01_tb IS 
    COMPONENT lecture01 is
        port(	
            i_sl_x      : in  std_logic;
	    o_slv_shift : out std_logic_vector(7 downto 0)
        );
    end COMPONENT;

    -- "local" signals

    -- signals for UUT
    -- input 
    signal x    : std_logic := '0';

    -- ouput
    signal o_slv_shift : std_logic_vector(7 downto 0) := (others => '0');

BEGIN 
    -- Instance of unit under test.
    uut: lecture01 
    PORT MAP (
        i_sl_x  => x,
	o_slv_shift => o_slv_shift
    );

-------------------------------------------------------------------------------
    -- test bench definition.
    tb_process :process
    begin
        x <= '0';
        wait for 10 ns;
        x <= '1';
        wait for 10 ns;
    end process;


END;

FPGA/FPGA 02/a/simple_gate.vcd
$date
  Thu Jan  7 17:47:01 2021
$end
$version
  GHDL v0
$end
$timescale
  1 fs
$end
$scope module standard $end
$upscope $end
$scope module textio $end
$upscope $end
$scope module std_logic_1164 $end
$upscope $end
$scope module lecture01_tb $end
$var reg 1 ! x $end
$var reg 8 " o_slv_shift[7:0] $end
$scope module uut $end
$var reg 1 # i_sl_x $end
$var reg 8 $ o_slv_shift[7:0] $end
$var reg 8 % shift_reg[7:0] $end
$upscope $end
$upscope $end
$enddefinitions $end
#0
0!
b00000001 "
0#
b00000001 $
b00000001 %
#10000000
1!
1#
b00000010 %
#20000000
0!
b00000010 "
0#
b00000010 $
#30000000
1!
1#
b00000100 %
#40000000
0!
b00000100 "
0#
b00000100 $
#50000000
1!
1#
b00001000 %
#60000000
0!
b00001000 "
0#
b00001000 $
#70000000
1!
1#
b00010000 %
#80000000
0!
b00010000 "
0#
b00010000 $
#90000000
1!
1#
b00100000 %
#100000000
0!
b00100000 "
0#
b00100000 $
#110000000
1!
1#
b01000000 %
#120000000
0!
b01000000 "
0#
b01000000 $
#130000000
1!
1#
b10000000 %
#140000000
0!
b10000000 "
0#
b10000000 $
#150000000
1!
1#
b00000001 %
#160000000
0!
b00000001 "
0#
b00000001 $
#170000000
1!
1#
b00000010 %
#180000000
0!
b00000010 "
0#
b00000010 $
#190000000
1!
1#
b00000100 %
#200000000
0!
b00000100 "
0#
b00000100 $
