FPGA/Material Lecture 01 - 28.10.2020/simple_gate.m.vhd
---------------------------------------
-- lecture 01 simple gate
-- just forwarding the signal
----------------------------------------

library ieee;
use ieee.std_logic_1164.all;

----------------------------------------

entity lecture01 is
port(	
	i_sl_x : in  std_logic;
	i_sl_y : in  std_logic;
	o_sl_and: out std_logic;
	o_sl_or: out std_logic;
	o_sl_nand: out std_logic;
	o_sl_nor: out std_logic;
	o_sl_xor: out std_logic;
	o_sl_not: out std_logic
);
end lecture01;  

----------------------------------------

architecture behaviour of lecture01 is
begin

    process(i_sl_x, i_sl_y)
    begin
        -- compare to truth table
        o_sl_and <= i_sl_x and i_sl_y;
        o_sl_or <= i_sl_x or i_sl_y;
        o_sl_nand <= i_sl_x nand i_sl_y;
        o_sl_nor <= i_sl_x nor i_sl_y;
        o_sl_xor <= i_sl_x xor i_sl_y;
        o_sl_not <= not i_sl_x;
    end process;
end behaviour;

------------------------------------------

FPGA/FPGA 01/simple_gate.tb.vhd
library ieee;
use ieee.std_logic_1164.all;

ENTITY lecture01_tb IS
END lecture01_tb;

ARCHITECTURE tb OF lecture01_tb IS 
    COMPONENT lecture01 is
        port(	
            i_sl_x    : in  std_logic;
	    i_sl_y    : in std_logic;
            o_sl_AND  : out std_logic;
            o_sl_OR   : out std_logic;
            o_sl_NAND : out std_logic;
            o_sl_NOR  : out std_logic;
            o_sl_XOR  : out std_logic;
            o_sl_NOT  : out std_logic
        );
    end COMPONENT;

    -- "local" signals

    -- signals for UUT
    -- input 
    signal x    : std_logic := '0';
    signal y    : std_logic := '0';

    -- ouput
    signal o_sl_AND : std_logic := '0';
    signal o_sl_OR : std_logic := '0';
    signal o_sl_NAND : std_logic := '0';
    signal o_sl_NOR : std_logic := '0';
    signal o_sl_XOR : std_logic := '0';
    signal o_sl_NOT : std_logic := '0';
BEGIN 
    -- Instance of unit under test.
    uut: lecture01 
    PORT MAP (
        i_sl_x  => x,
	i_sl_y  => y,
	o_sl_AND => o_sl_AND,
	o_sl_OR => o_sl_OR,
	o_sl_NAND => o_sl_NAND,
	o_sl_NOR => o_sl_NOR,
	o_sl_XOR => o_sl_XOR,
	o_sl_NOT => o_sl_NOT
    );

-------------------------------------------------------------------------------
    -- test bench definition.
    tb_process :process
    begin
        x <= '0';
        wait for 10 ns;
        x <= '1';
        wait for 10 ns;
    end process;
    tb_process_y :process
    begin
        y <= '0';
        wait for 20 ns;
        y <= '1';
        wait for 20 ns;
    end process;


END;

FPGA/FPGA 01/simple_gate.vcd
$date
  Wed Jan  6 12:50:47 2021
$end
$version
  GHDL v0
$end
$timescale
  1 fs
$end
$scope module standard $end
$upscope $end
$scope module textio $end
$upscope $end
$scope module std_logic_1164 $end
$upscope $end
$scope module lecture01_tb $end
$var reg 1 ! x $end
$var reg 1 " y $end
$var reg 1 # o_sl_and $end
$var reg 1 $ o_sl_or $end
$var reg 1 % o_sl_nand $end
$var reg 1 & o_sl_nor $end
$var reg 1 ' o_sl_xor $end
$var reg 1 ( o_sl_not $end
$scope module uut $end
$var reg 1 ) i_sl_x $end
$var reg 1 * i_sl_y $end
$var reg 1 + o_sl_and $end
$var reg 1 , o_sl_or $end
$var reg 1 - o_sl_nand $end
$var reg 1 . o_sl_nor $end
$var reg 1 / o_sl_xor $end
$var reg 1 0 o_sl_not $end
$upscope $end
$upscope $end
$enddefinitions $end
#0
0!
0"
0#
0$
1%
1&
0'
1(
0)
0*
0+
0,
1-
1.
0/
10
#10000000
1!
1$
0&
1'
1)
1,
0.
1/
#20000000
0!
1"
0(
0)
1*
00
#30000000
1!
1#
0%
0'
1)
1+
0-
0/
#40000000
0!
0"
0#
0$
1%
1&
1(
0)
0*
0+
0,
1-
1.
10
#50000000
1!
1$
0&
1'
1)
1,
0.
1/
#60000000
0!
1"
0(
0)
1*
00
#70000000
1!
1#
0%
0'
1)
1+
0-
0/
#80000000
0!
0"
0#
0$
1%
1&
1(
0)
0*
0+
0,
1-
1.
10
#90000000
1!
1$
0&
1'
1)
1,
0.
1/
#100000000
0!
1"
0(
0)
1*
00
#110000000
1!
1#
0%
0'
1)
1+
0-
0/
#120000000
0!
0"
0#
0$
1%
1&
1(
0)
0*
0+
0,
1-
1.
10
#130000000
1!
1$
0&
1'
1)
1,
0.
1/
#140000000
0!
1"
0(
0)
1*
00
#150000000
1!
1#
0%
0'
1)
1+
0-
0/
#160000000
0!
0"
0#
0$
1%
1&
1(
0)
0*
0+
0,
1-
1.
10
#170000000
1!
1$
0&
1'
1)
1,
0.
1/
#180000000
0!
1"
0(
0)
1*
00
#190000000
1!
1#
0%
0'
1)
1+
0-
0/
#200000000
0!
0"
0#
0$
1%
1&
1(
0)
0*
0+
0,
1-
1.
10
