FPGA/FPGA 02/skeleton3c_Test/pwm.m.vhd
---------------------------------------
-- lecture 02 shift register
-- just forwarding the signal
----------------------------------------

library ieee;
use ieee.std_logic_1164.all;
use ieee.numeric_std.all;

----------------------------------------

entity pwm is
    generic(
        DATA_WIDTH    :  integer := 8
    );
    port(   
        i_sl_CLK      :  in  std_logic;                                 -- clock
	i_sl_en	      :  in std_logic;
        o_sl_pwm      :  out std_logic_vector(DATA_WIDTH-1 downto 0)    -- pwm output
    );
end pwm;  

----------------------------------------

architecture behavior of pwm is
signal slv_pwm_cnt : std_logic_vector(DATA_WIDTH-1 downto 0) := "00000001";


begin
    process(i_sl_CLK)
    begin
        if rising_edge(i_sl_CLK) then
		if (i_sl_en = '1') then
			slv_pwm_cnt <= std_logic_vector(unsigned(slv_pwm_cnt)+1);
			o_sl_pwm <= slv_pwm_cnt;
		end if;
		if (i_sl_en = '0') then 
			slv_pwm_cnt <= std_logic_vector(unsigned(slv_pwm_cnt)-1);
			o_sl_pwm <= slv_pwm_cnt;
		end if;
        end if;
    end process;

end behavior;

------------------------------------------

FPGA/FPGA 02/skeleton3c_Test/pwm.tb.vhd
library ieee;
use ieee.std_logic_1164.all;

ENTITY pwm_tb IS
END pwm_tb;

ARCHITECTURE tb OF pwm_tb IS 

    COMPONENT pwm is
    generic(
        DATA_WIDTH    :  integer := 8
    );
        port(   
            i_sl_CLK      :  in  std_logic;                      -- clock
	    i_sl_en	  :  in  std_logic;
            o_sl_pwm      :  out std_logic_vector(DATA_WIDTH-1 downto 0)   -- output
        );
    end COMPONENT;

    -- "local" signals
    constant DATA_WIDTH : integer := 8;
    -- signals for UUT
    -- input 
    signal CLK    : std_logic := '0';
    signal en     : std_logic := '0';
    -- ouput
    signal o_sl_pwm : std_logic_vector(DATA_WIDTH-1 downto 0) := "00000001";

BEGIN 
    -- Instance of unit under test.
    uut: pwm 
    PORT MAP (
        i_sl_CLK    => CLK,
	i_sl_en     => en,
        o_sl_pwm    => o_sl_pwm
    );

-------------------------------------------------------------------------------
    -- test bench definition.
    tb_CLK :process
    begin
        CLK <= '0';
        wait for 1 ns;
        CLK <= '1';
        wait for 1 ns;
    end process;

    tb_en :process
    begin
        en <= '0';
        wait for 20 ns;
        en <= '1';
        wait for 20 ns;
    end process;


END;

FPGA/FPGA 02/skeleton3c_Test/pwm.vcd
$date
  Wed Dec  9 09:53:28 2020
$end
$version
  GHDL v0
$end
$timescale
  1 fs
$end
$scope module standard $end
$upscope $end
$scope module textio $end
$upscope $end
$scope module std_logic_1164 $end
$upscope $end
$scope module numeric_std $end
$upscope $end
$scope module pwm_tb $end
$var reg 1 ! clk $end
$var reg 1 " en $end
$var reg 8 # o_sl_pwm[7:0] $end
$scope module uut $end
$var reg 1 $ i_sl_clk $end
$var reg 1 % i_sl_en $end
$var reg 8 & o_sl_pwm[7:0] $end
$var reg 8 ' slv_pwm_cnt[7:0] $end
$upscope $end
$upscope $end
$enddefinitions $end
#0
0!
0"
bUUUUUUUU #
0$
0%
bUUUUUUUU &
b00000001 '
#1000000
1!
b00000001 #
1$
b00000001 &
b00000000 '
#2000000
0!
0$
#3000000
1!
b00000000 #
1$
b00000000 &
b11111111 '
#4000000
0!
0$
#5000000
1!
b11111111 #
1$
b11111111 &
b11111110 '
#6000000
0!
0$
#7000000
1!
b11111110 #
1$
b11111110 &
b11111101 '
#8000000
0!
0$
#9000000
1!
b11111101 #
1$
b11111101 &
b11111100 '
#10000000
0!
0$
#11000000
1!
b11111100 #
1$
b11111100 &
b11111011 '
#12000000
0!
0$
#13000000
1!
b11111011 #
1$
b11111011 &
b11111010 '
#14000000
0!
0$
#15000000
1!
b11111010 #
1$
b11111010 &
b11111001 '
#16000000
0!
0$
#17000000
1!
b11111001 #
1$
b11111001 &
b11111000 '
#18000000
0!
0$
#19000000
1!
b11111000 #
1$
b11111000 &
b11110111 '
#20000000
0!
1"
0$
1%
#21000000
1!
b11110111 #
1$
b11110111 &
b11111000 '
#22000000
0!
0$
#23000000
1!
b11111000 #
1$
b11111000 &
b11111001 '
#24000000
0!
0$
#25000000
1!
b11111001 #
1$
b11111001 &
b11111010 '
#26000000
0!
0$
#27000000
1!
b11111010 #
1$
b11111010 &
b11111011 '
#28000000
0!
0$
#29000000
1!
b11111011 #
1$
b11111011 &
b11111100 '
#30000000
0!
0$
#31000000
1!
b11111100 #
1$
b11111100 &
b11111101 '
#32000000
0!
0$
#33000000
1!
b11111101 #
1$
b11111101 &
b11111110 '
#34000000
0!
0$
#35000000
1!
b11111110 #
1$
b11111110 &
b11111111 '
#36000000
0!
0$
#37000000
1!
b11111111 #
1$
b11111111 &
b00000000 '
#38000000
0!
0$
#39000000
1!
b00000000 #
1$
b00000000 &
b00000001 '
#40000000
0!
0"
0$
0%
#41000000
1!
b00000001 #
1$
b00000001 &
b00000000 '
#42000000
0!
0$
#43000000
1!
b00000000 #
1$
b00000000 &
b11111111 '
#44000000
0!
0$
#45000000
1!
b11111111 #
1$
b11111111 &
b11111110 '
#46000000
0!
0$
#47000000
1!
b11111110 #
1$
b11111110 &
b11111101 '
#48000000
0!
0$
#49000000
1!
b11111101 #
1$
b11111101 &
b11111100 '
#50000000
0!
0$
#51000000
1!
b11111100 #
1$
b11111100 &
b11111011 '
#52000000
0!
0$
#53000000
1!
b11111011 #
1$
b11111011 &
b11111010 '
#54000000
0!
0$
#55000000
1!
b11111010 #
1$
b11111010 &
b11111001 '
#56000000
0!
0$
#57000000
1!
b11111001 #
1$
b11111001 &
b11111000 '
#58000000
0!
0$
#59000000
1!
b11111000 #
1$
b11111000 &
b11110111 '
#60000000
0!
1"
0$
1%
#61000000
1!
b11110111 #
1$
b11110111 &
b11111000 '
#62000000
0!
0$
#63000000
1!
b11111000 #
1$
b11111000 &
b11111001 '
#64000000
0!
0$
#65000000
1!
b11111001 #
1$
b11111001 &
b11111010 '
#66000000
0!
0$
#67000000
1!
b11111010 #
1$
b11111010 &
b11111011 '
#68000000
0!
0$
#69000000
1!
b11111011 #
1$
b11111011 &
b11111100 '
#70000000
0!
0$
#71000000
1!
b11111100 #
1$
b11111100 &
b11111101 '
#72000000
0!
0$
#73000000
1!
b11111101 #
1$
b11111101 &
b11111110 '
#74000000
0!
0$
#75000000
1!
b11111110 #
1$
b11111110 &
b11111111 '
#76000000
0!
0$
#77000000
1!
b11111111 #
1$
b11111111 &
b00000000 '
#78000000
0!
0$
#79000000
1!
b00000000 #
1$
b00000000 &
b00000001 '
#80000000
0!
0"
0$
0%
#81000000
1!
b00000001 #
1$
b00000001 &
b00000000 '
#82000000
0!
0$
#83000000
1!
b00000000 #
1$
b00000000 &
b11111111 '
#84000000
0!
0$
#85000000
1!
b11111111 #
1$
b11111111 &
b11111110 '
#86000000
0!
0$
#87000000
1!
b11111110 #
1$
b11111110 &
b11111101 '
#88000000
0!
0$
#89000000
1!
b11111101 #
1$
b11111101 &
b11111100 '
#90000000
0!
0$
#91000000
1!
b11111100 #
1$
b11111100 &
b11111011 '
#92000000
0!
0$
#93000000
1!
b11111011 #
1$
b11111011 &
b11111010 '
#94000000
0!
0$
#95000000
1!
b11111010 #
1$
b11111010 &
b11111001 '
#96000000
0!
0$
#97000000
1!
b11111001 #
1$
b11111001 &
b11111000 '
#98000000
0!
0$
#99000000
1!
b11111000 #
1$
b11111000 &
b11110111 '
#100000000
0!
1"
0$
1%
#101000000
1!
b11110111 #
1$
b11110111 &
b11111000 '
#102000000
0!
0$
#103000000
1!
b11111000 #
1$
b11111000 &
b11111001 '
#104000000
0!
0$
#105000000
1!
b11111001 #
1$
b11111001 &
b11111010 '
#106000000
0!
0$
#107000000
1!
b11111010 #
1$
b11111010 &
b11111011 '
#108000000
0!
0$
#109000000
1!
b11111011 #
1$
b11111011 &
b11111100 '
#110000000
0!
0$
#111000000
1!
b11111100 #
1$
b11111100 &
b11111101 '
#112000000
0!
0$
#113000000
1!
b11111101 #
1$
b11111101 &
b11111110 '
#114000000
0!
0$
#115000000
1!
b11111110 #
1$
b11111110 &
b11111111 '
#116000000
0!
0$
#117000000
1!
b11111111 #
1$
b11111111 &
b00000000 '
#118000000
0!
0$
#119000000
1!
b00000000 #
1$
b00000000 &
b00000001 '
#120000000
0!
0"
0$
0%
#121000000
1!
b00000001 #
1$
b00000001 &
b00000000 '
#122000000
0!
0$
#123000000
1!
b00000000 #
1$
b00000000 &
b11111111 '
#124000000
0!
0$
#125000000
1!
b11111111 #
1$
b11111111 &
b11111110 '
#126000000
0!
0$
#127000000
1!
b11111110 #
1$
b11111110 &
b11111101 '
#128000000
0!
0$
#129000000
1!
b11111101 #
1$
b11111101 &
b11111100 '
#130000000
0!
0$
#131000000
1!
b11111100 #
1$
b11111100 &
b11111011 '
#132000000
0!
0$
#133000000
1!
b11111011 #
1$
b11111011 &
b11111010 '
#134000000
0!
0$
#135000000
1!
b11111010 #
1$
b11111010 &
b11111001 '
#136000000
0!
0$
#137000000
1!
b11111001 #
1$
b11111001 &
b11111000 '
#138000000
0!
0$
#139000000
1!
b11111000 #
1$
b11111000 &
b11110111 '
#140000000
0!
1"
0$
1%
#141000000
1!
b11110111 #
1$
b11110111 &
b11111000 '
#142000000
0!
0$
#143000000
1!
b11111000 #
1$
b11111000 &
b11111001 '
#144000000
0!
0$
#145000000
1!
b11111001 #
1$
b11111001 &
b11111010 '
#146000000
0!
0$
#147000000
1!
b11111010 #
1$
b11111010 &
b11111011 '
#148000000
0!
0$
#149000000
1!
b11111011 #
1$
b11111011 &
b11111100 '
#150000000
0!
0$
#151000000
1!
b11111100 #
1$
b11111100 &
b11111101 '
#152000000
0!
0$
#153000000
1!
b11111101 #
1$
b11111101 &
b11111110 '
#154000000
0!
0$
#155000000
1!
b11111110 #
1$
b11111110 &
b11111111 '
#156000000
0!
0$
#157000000
1!
b11111111 #
1$
b11111111 &
b00000000 '
#158000000
0!
0$
#159000000
1!
b00000000 #
1$
b00000000 &
b00000001 '
#160000000
0!
0"
0$
0%
#161000000
1!
b00000001 #
1$
b00000001 &
b00000000 '
#162000000
0!
0$
#163000000
1!
b00000000 #
1$
b00000000 &
b11111111 '
#164000000
0!
0$
#165000000
1!
b11111111 #
1$
b11111111 &
b11111110 '
#166000000
0!
0$
#167000000
1!
b11111110 #
1$
b11111110 &
b11111101 '
#168000000
0!
0$
#169000000
1!
b11111101 #
1$
b11111101 &
b11111100 '
#170000000
0!
0$
#171000000
1!
b11111100 #
1$
b11111100 &
b11111011 '
#172000000
0!
0$
#173000000
1!
b11111011 #
1$
b11111011 &
b11111010 '
#174000000
0!
0$
#175000000
1!
b11111010 #
1$
b11111010 &
b11111001 '
#176000000
0!
0$
#177000000
1!
b11111001 #
1$
b11111001 &
b11111000 '
#178000000
0!
0$
#179000000
1!
b11111000 #
1$
b11111000 &
b11110111 '
#180000000
0!
1"
0$
1%
#181000000
1!
b11110111 #
1$
b11110111 &
b11111000 '
#182000000
0!
0$
#183000000
1!
b11111000 #
1$
b11111000 &
b11111001 '
#184000000
0!
0$
#185000000
1!
b11111001 #
1$
b11111001 &
b11111010 '
#186000000
0!
0$
#187000000
1!
b11111010 #
1$
b11111010 &
b11111011 '
#188000000
0!
0$
#189000000
1!
b11111011 #
1$
b11111011 &
b11111100 '
#190000000
0!
0$
#191000000
1!
b11111100 #
1$
b11111100 &
b11111101 '
#192000000
0!
0$
#193000000
1!
b11111101 #
1$
b11111101 &
b11111110 '
#194000000
0!
0$
#195000000
1!
b11111110 #
1$
b11111110 &
b11111111 '
#196000000
0!
0$
#197000000
1!
b11111111 #
1$
b11111111 &
b00000000 '
#198000000
0!
0$
#199000000
1!
b00000000 #
1$
b00000000 &
b00000001 '
#200000000
0!
0"
0$
0%
#201000000
1!
b00000001 #
1$
b00000001 &
b00000000 '
#202000000
0!
0$
#203000000
1!
b00000000 #
1$
b00000000 &
b11111111 '
#204000000
0!
0$
#205000000
1!
b11111111 #
1$
b11111111 &
b11111110 '
#206000000
0!
0$
#207000000
1!
b11111110 #
1$
b11111110 &
b11111101 '
#208000000
0!
0$
#209000000
1!
b11111101 #
1$
b11111101 &
b11111100 '
#210000000
0!
0$
#211000000
1!
b11111100 #
1$
b11111100 &
b11111011 '
#212000000
0!
0$
#213000000
1!
b11111011 #
1$
b11111011 &
b11111010 '
#214000000
0!
0$
#215000000
1!
b11111010 #
1$
b11111010 &
b11111001 '
#216000000
0!
0$
#217000000
1!
b11111001 #
1$
b11111001 &
b11111000 '
#218000000
0!
0$
#219000000
1!
b11111000 #
1$
b11111000 &
b11110111 '
#220000000
0!
1"
0$
1%
#221000000
1!
b11110111 #
1$
b11110111 &
b11111000 '
#222000000
0!
0$
#223000000
1!
b11111000 #
1$
b11111000 &
b11111001 '
#224000000
0!
0$
#225000000
1!
b11111001 #
1$
b11111001 &
b11111010 '
#226000000
0!
0$
#227000000
1!
b11111010 #
1$
b11111010 &
b11111011 '
#228000000
0!
0$
#229000000
1!
b11111011 #
1$
b11111011 &
b11111100 '
#230000000
0!
0$
#231000000
1!
b11111100 #
1$
b11111100 &
b11111101 '
#232000000
0!
0$
#233000000
1!
b11111101 #
1$
b11111101 &
b11111110 '
#234000000
0!
0$
#235000000
1!
b11111110 #
1$
b11111110 &
b11111111 '
#236000000
0!
0$
#237000000
1!
b11111111 #
1$
b11111111 &
b00000000 '
#238000000
0!
0$
#239000000
1!
b00000000 #
1$
b00000000 &
b00000001 '
#240000000
0!
0"
0$
0%
#241000000
1!
b00000001 #
1$
b00000001 &
b00000000 '
#242000000
0!
0$
#243000000
1!
b00000000 #
1$
b00000000 &
b11111111 '
#244000000
0!
0$
#245000000
1!
b11111111 #
1$
b11111111 &
b11111110 '
#246000000
0!
0$
#247000000
1!
b11111110 #
1$
b11111110 &
b11111101 '
#248000000
0!
0$
#249000000
1!
b11111101 #
1$
b11111101 &
b11111100 '
#250000000
0!
0$
#251000000
1!
b11111100 #
1$
b11111100 &
b11111011 '
#252000000
0!
0$
#253000000
1!
b11111011 #
1$
b11111011 &
b11111010 '
#254000000
0!
0$
#255000000
1!
b11111010 #
1$
b11111010 &
b11111001 '
#256000000
0!
0$
#257000000
1!
b11111001 #
1$
b11111001 &
b11111000 '
#258000000
0!
0$
#259000000
1!
b11111000 #
1$
b11111000 &
b11110111 '
#260000000
0!
1"
0$
1%
#261000000
1!
b11110111 #
1$
b11110111 &
b11111000 '
#262000000
0!
0$
#263000000
1!
b11111000 #
1$
b11111000 &
b11111001 '
#264000000
0!
0$
#265000000
1!
b11111001 #
1$
b11111001 &
b11111010 '
#266000000
0!
0$
#267000000
1!
b11111010 #
1$
b11111010 &
b11111011 '
#268000000
0!
0$
#269000000
1!
b11111011 #
1$
b11111011 &
b11111100 '
#270000000
0!
0$
#271000000
1!
b11111100 #
1$
b11111100 &
b11111101 '
#272000000
0!
0$
#273000000
1!
b11111101 #
1$
b11111101 &
b11111110 '
#274000000
0!
0$
#275000000
1!
b11111110 #
1$
b11111110 &
b11111111 '
#276000000
0!
0$
#277000000
1!
b11111111 #
1$
b11111111 &
b00000000 '
#278000000
0!
0$
#279000000
1!
b00000000 #
1$
b00000000 &
b00000001 '
#280000000
0!
0"
0$
0%
#281000000
1!
b00000001 #
1$
b00000001 &
b00000000 '
#282000000
0!
0$
#283000000
1!
b00000000 #
1$
b00000000 &
b11111111 '
#284000000
0!
0$
#285000000
1!
b11111111 #
1$
b11111111 &
b11111110 '
#286000000
0!
0$
#287000000
1!
b11111110 #
1$
b11111110 &
b11111101 '
#288000000
0!
0$
#289000000
1!
b11111101 #
1$
b11111101 &
b11111100 '
#290000000
0!
0$
#291000000
1!
b11111100 #
1$
b11111100 &
b11111011 '
#292000000
0!
0$
#293000000
1!
b11111011 #
1$
b11111011 &
b11111010 '
#294000000
0!
0$
#295000000
1!
b11111010 #
1$
b11111010 &
b11111001 '
#296000000
0!
0$
#297000000
1!
b11111001 #
1$
b11111001 &
b11111000 '
#298000000
0!
0$
#299000000
1!
b11111000 #
1$
b11111000 &
b11110111 '
#300000000
0!
1"
0$
1%
#301000000
1!
b11110111 #
1$
b11110111 &
b11111000 '
#302000000
0!
0$
#303000000
1!
b11111000 #
1$
b11111000 &
b11111001 '
#304000000
0!
0$
#305000000
1!
b11111001 #
1$
b11111001 &
b11111010 '
#306000000
0!
0$
#307000000
1!
b11111010 #
1$
b11111010 &
b11111011 '
#308000000
0!
0$
#309000000
1!
b11111011 #
1$
b11111011 &
b11111100 '
#310000000
0!
0$
#311000000
1!
b11111100 #
1$
b11111100 &
b11111101 '
#312000000
0!
0$
#313000000
1!
b11111101 #
1$
b11111101 &
b11111110 '
#314000000
0!
0$
#315000000
1!
b11111110 #
1$
b11111110 &
b11111111 '
#316000000
0!
0$
#317000000
1!
b11111111 #
1$
b11111111 &
b00000000 '
#318000000
0!
0$
#319000000
1!
b00000000 #
1$
b00000000 &
b00000001 '
#320000000
0!
0"
0$
0%
#321000000
1!
b00000001 #
1$
b00000001 &
b00000000 '
#322000000
0!
0$
#323000000
1!
b00000000 #
1$
b00000000 &
b11111111 '
#324000000
0!
0$
#325000000
1!
b11111111 #
1$
b11111111 &
b11111110 '
#326000000
0!
0$
#327000000
1!
b11111110 #
1$
b11111110 &
b11111101 '
#328000000
0!
0$
#329000000
1!
b11111101 #
1$
b11111101 &
b11111100 '
#330000000
0!
0$
#331000000
1!
b11111100 #
1$
b11111100 &
b11111011 '
#332000000
0!
0$
#333000000
1!
b11111011 #
1$
b11111011 &
b11111010 '
#334000000
0!
0$
#335000000
1!
b11111010 #
1$
b11111010 &
b11111001 '
#336000000
0!
0$
#337000000
1!
b11111001 #
1$
b11111001 &
b11111000 '
#338000000
0!
0$
#339000000
1!
b11111000 #
1$
b11111000 &
b11110111 '
#340000000
0!
1"
0$
1%
#341000000
1!
b11110111 #
1$
b11110111 &
b11111000 '
#342000000
0!
0$
#343000000
1!
b11111000 #
1$
b11111000 &
b11111001 '
#344000000
0!
0$
#345000000
1!
b11111001 #
1$
b11111001 &
b11111010 '
#346000000
0!
0$
#347000000
1!
b11111010 #
1$
b11111010 &
b11111011 '
#348000000
0!
0$
#349000000
1!
b11111011 #
1$
b11111011 &
b11111100 '
#350000000
0!
0$
#351000000
1!
b11111100 #
1$
b11111100 &
b11111101 '
#352000000
0!
0$
#353000000
1!
b11111101 #
1$
b11111101 &
b11111110 '
#354000000
0!
0$
#355000000
1!
b11111110 #
1$
b11111110 &
b11111111 '
#356000000
0!
0$
#357000000
1!
b11111111 #
1$
b11111111 &
b00000000 '
#358000000
0!
0$
#359000000
1!
b00000000 #
1$
b00000000 &
b00000001 '
#360000000
0!
0"
0$
0%
#361000000
1!
b00000001 #
1$
b00000001 &
b00000000 '
#362000000
0!
0$
#363000000
1!
b00000000 #
1$
b00000000 &
b11111111 '
#364000000
0!
0$
#365000000
1!
b11111111 #
1$
b11111111 &
b11111110 '
#366000000
0!
0$
#367000000
1!
b11111110 #
1$
b11111110 &
b11111101 '
#368000000
0!
0$
#369000000
1!
b11111101 #
1$
b11111101 &
b11111100 '
#370000000
0!
0$
#371000000
1!
b11111100 #
1$
b11111100 &
b11111011 '
#372000000
0!
0$
#373000000
1!
b11111011 #
1$
b11111011 &
b11111010 '
#374000000
0!
0$
#375000000
1!
b11111010 #
1$
b11111010 &
b11111001 '
#376000000
0!
0$
#377000000
1!
b11111001 #
1$
b11111001 &
b11111000 '
#378000000
0!
0$
#379000000
1!
b11111000 #
1$
b11111000 &
b11110111 '
#380000000
0!
1"
0$
1%
#381000000
1!
b11110111 #
1$
b11110111 &
b11111000 '
#382000000
0!
0$
#383000000
1!
b11111000 #
1$
b11111000 &
b11111001 '
#384000000
0!
0$
#385000000
1!
b11111001 #
1$
b11111001 &
b11111010 '
#386000000
0!
0$
#387000000
1!
b11111010 #
1$
b11111010 &
b11111011 '
#388000000
0!
0$
#389000000
1!
b11111011 #
1$
b11111011 &
b11111100 '
#390000000
0!
0$
#391000000
1!
b11111100 #
1$
b11111100 &
b11111101 '
#392000000
0!
0$
#393000000
1!
b11111101 #
1$
b11111101 &
b11111110 '
#394000000
0!
0$
#395000000
1!
b11111110 #
1$
b11111110 &
b11111111 '
#396000000
0!
0$
#397000000
1!
b11111111 #
1$
b11111111 &
b00000000 '
#398000000
0!
0$
#399000000
1!
b00000000 #
1$
b00000000 &
b00000001 '
#400000000
0!
0"
0$
0%
#401000000
1!
b00000001 #
1$
b00000001 &
b00000000 '
#402000000
0!
0$
#403000000
1!
b00000000 #
1$
b00000000 &
b11111111 '
#404000000
0!
0$
#405000000
1!
b11111111 #
1$
b11111111 &
b11111110 '
#406000000
0!
0$
#407000000
1!
b11111110 #
1$
b11111110 &
b11111101 '
#408000000
0!
0$
#409000000
1!
b11111101 #
1$
b11111101 &
b11111100 '
#410000000
0!
0$
#411000000
1!
b11111100 #
1$
b11111100 &
b11111011 '
#412000000
0!
0$
#413000000
1!
b11111011 #
1$
b11111011 &
b11111010 '
#414000000
0!
0$
#415000000
1!
b11111010 #
1$
b11111010 &
b11111001 '
#416000000
0!
0$
#417000000
1!
b11111001 #
1$
b11111001 &
b11111000 '
#418000000
0!
0$
#419000000
1!
b11111000 #
1$
b11111000 &
b11110111 '
#420000000
0!
1"
0$
1%
#421000000
1!
b11110111 #
1$
b11110111 &
b11111000 '
#422000000
0!
0$
#423000000
1!
b11111000 #
1$
b11111000 &
b11111001 '
#424000000
0!
0$
#425000000
1!
b11111001 #
1$
b11111001 &
b11111010 '
#426000000
0!
0$
#427000000
1!
b11111010 #
1$
b11111010 &
b11111011 '
#428000000
0!
0$
#429000000
1!
b11111011 #
1$
b11111011 &
b11111100 '
#430000000
0!
0$
#431000000
1!
b11111100 #
1$
b11111100 &
b11111101 '
#432000000
0!
0$
#433000000
1!
b11111101 #
1$
b11111101 &
b11111110 '
#434000000
0!
0$
#435000000
1!
b11111110 #
1$
b11111110 &
b11111111 '
#436000000
0!
0$
#437000000
1!
b11111111 #
1$
b11111111 &
b00000000 '
#438000000
0!
0$
#439000000
1!
b00000000 #
1$
b00000000 &
b00000001 '
#440000000
0!
0"
0$
0%
#441000000
1!
b00000001 #
1$
b00000001 &
b00000000 '
#442000000
0!
0$
#443000000
1!
b00000000 #
1$
b00000000 &
b11111111 '
#444000000
0!
0$
#445000000
1!
b11111111 #
1$
b11111111 &
b11111110 '
#446000000
0!
0$
#447000000
1!
b11111110 #
1$
b11111110 &
b11111101 '
#448000000
0!
0$
#449000000
1!
b11111101 #
1$
b11111101 &
b11111100 '
#450000000
0!
0$
#451000000
1!
b11111100 #
1$
b11111100 &
b11111011 '
#452000000
0!
0$
#453000000
1!
b11111011 #
1$
b11111011 &
b11111010 '
#454000000
0!
0$
#455000000
1!
b11111010 #
1$
b11111010 &
b11111001 '
#456000000
0!
0$
#457000000
1!
b11111001 #
1$
b11111001 &
b11111000 '
#458000000
0!
0$
#459000000
1!
b11111000 #
1$
b11111000 &
b11110111 '
#460000000
0!
1"
0$
1%
#461000000
1!
b11110111 #
1$
b11110111 &
b11111000 '
#462000000
0!
0$
#463000000
1!
b11111000 #
1$
b11111000 &
b11111001 '
#464000000
0!
0$
#465000000
1!
b11111001 #
1$
b11111001 &
b11111010 '
#466000000
0!
0$
#467000000
1!
b11111010 #
1$
b11111010 &
b11111011 '
#468000000
0!
0$
#469000000
1!
b11111011 #
1$
b11111011 &
b11111100 '
#470000000
0!
0$
#471000000
1!
b11111100 #
1$
b11111100 &
b11111101 '
#472000000
0!
0$
#473000000
1!
b11111101 #
1$
b11111101 &
b11111110 '
#474000000
0!
0$
#475000000
1!
b11111110 #
1$
b11111110 &
b11111111 '
#476000000
0!
0$
#477000000
1!
b11111111 #
1$
b11111111 &
b00000000 '
#478000000
0!
0$
#479000000
1!
b00000000 #
1$
b00000000 &
b00000001 '
#480000000
0!
0"
0$
0%
#481000000
1!
b00000001 #
1$
b00000001 &
b00000000 '
#482000000
0!
0$
#483000000
1!
b00000000 #
1$
b00000000 &
b11111111 '
#484000000
0!
0$
#485000000
1!
b11111111 #
1$
b11111111 &
b11111110 '
#486000000
0!
0$
#487000000
1!
b11111110 #
1$
b11111110 &
b11111101 '
#488000000
0!
0$
#489000000
1!
b11111101 #
1$
b11111101 &
b11111100 '
#490000000
0!
0$
#491000000
1!
b11111100 #
1$
b11111100 &
b11111011 '
#492000000
0!
0$
#493000000
1!
b11111011 #
1$
b11111011 &
b11111010 '
#494000000
0!
0$
#495000000
1!
b11111010 #
1$
b11111010 &
b11111001 '
#496000000
0!
0$
#497000000
1!
b11111001 #
1$
b11111001 &
b11111000 '
#498000000
0!
0$
#499000000
1!
b11111000 #
1$
b11111000 &
b11110111 '
#500000000
0!
1"
0$
1%
#501000000
1!
b11110111 #
1$
b11110111 &
b11111000 '
#502000000
0!
0$
#503000000
1!
b11111000 #
1$
b11111000 &
b11111001 '
#504000000
0!
0$
#505000000
1!
b11111001 #
1$
b11111001 &
b11111010 '
#506000000
0!
0$
#507000000
1!
b11111010 #
1$
b11111010 &
b11111011 '
#508000000
0!
0$
#509000000
1!
b11111011 #
1$
b11111011 &
b11111100 '
#510000000
0!
0$
#511000000
1!
b11111100 #
1$
b11111100 &
b11111101 '
#512000000
0!
0$
#513000000
1!
b11111101 #
1$
b11111101 &
b11111110 '
#514000000
0!
0$
#515000000
1!
b11111110 #
1$
b11111110 &
b11111111 '
#516000000
0!
0$
#517000000
1!
b11111111 #
1$
b11111111 &
b00000000 '
#518000000
0!
0$
#519000000
1!
b00000000 #
1$
b00000000 &
b00000001 '
#520000000
0!
0"
0$
0%
#521000000
1!
b00000001 #
1$
b00000001 &
b00000000 '
#522000000
0!
0$
#523000000
1!
b00000000 #
1$
b00000000 &
b11111111 '
#524000000
0!
0$
#525000000
1!
b11111111 #
1$
b11111111 &
b11111110 '
#526000000
0!
0$
#527000000
1!
b11111110 #
1$
b11111110 &
b11111101 '
#528000000
0!
0$
#529000000
1!
b11111101 #
1$
b11111101 &
b11111100 '
#530000000
0!
0$
#531000000
1!
b11111100 #
1$
b11111100 &
b11111011 '
#532000000
0!
0$
#533000000
1!
b11111011 #
1$
b11111011 &
b11111010 '
#534000000
0!
0$
#535000000
1!
b11111010 #
1$
b11111010 &
b11111001 '
#536000000
0!
0$
#537000000
1!
b11111001 #
1$
b11111001 &
b11111000 '
#538000000
0!
0$
#539000000
1!
b11111000 #
1$
b11111000 &
b11110111 '
#540000000
0!
1"
0$
1%
#541000000
1!
b11110111 #
1$
b11110111 &
b11111000 '
#542000000
0!
0$
#543000000
1!
b11111000 #
1$
b11111000 &
b11111001 '
#544000000
0!
0$
#545000000
1!
b11111001 #
1$
b11111001 &
b11111010 '
#546000000
0!
0$
#547000000
1!
b11111010 #
1$
b11111010 &
b11111011 '
#548000000
0!
0$
#549000000
1!
b11111011 #
1$
b11111011 &
b11111100 '
#550000000
0!
0$
#551000000
1!
b11111100 #
1$
b11111100 &
b11111101 '
#552000000
0!
0$
#553000000
1!
b11111101 #
1$
b11111101 &
b11111110 '
#554000000
0!
0$
#555000000
1!
b11111110 #
1$
b11111110 &
b11111111 '
#556000000
0!
0$
#557000000
1!
b11111111 #
1$
b11111111 &
b00000000 '
#558000000
0!
0$
#559000000
1!
b00000000 #
1$
b00000000 &
b00000001 '
#560000000
0!
0"
0$
0%
#561000000
1!
b00000001 #
1$
b00000001 &
b00000000 '
#562000000
0!
0$
#563000000
1!
b00000000 #
1$
b00000000 &
b11111111 '
#564000000
0!
0$
#565000000
1!
b11111111 #
1$
b11111111 &
b11111110 '
#566000000
0!
0$
#567000000
1!
b11111110 #
1$
b11111110 &
b11111101 '
#568000000
0!
0$
#569000000
1!
b11111101 #
1$
b11111101 &
b11111100 '
#570000000
0!
0$
#571000000
1!
b11111100 #
1$
b11111100 &
b11111011 '
#572000000
0!
0$
#573000000
1!
b11111011 #
1$
b11111011 &
b11111010 '
#574000000
0!
0$
#575000000
1!
b11111010 #
1$
b11111010 &
b11111001 '
#576000000
0!
0$
#577000000
1!
b11111001 #
1$
b11111001 &
b11111000 '
#578000000
0!
0$
#579000000
1!
b11111000 #
1$
b11111000 &
b11110111 '
#580000000
0!
1"
0$
1%
#581000000
1!
b11110111 #
1$
b11110111 &
b11111000 '
#582000000
0!
0$
#583000000
1!
b11111000 #
1$
b11111000 &
b11111001 '
#584000000
0!
0$
#585000000
1!
b11111001 #
1$
b11111001 &
b11111010 '
#586000000
0!
0$
#587000000
1!
b11111010 #
1$
b11111010 &
b11111011 '
#588000000
0!
0$
#589000000
1!
b11111011 #
1$
b11111011 &
b11111100 '
#590000000
0!
0$
#591000000
1!
b11111100 #
1$
b11111100 &
b11111101 '
#592000000
0!
0$
#593000000
1!
b11111101 #
1$
b11111101 &
b11111110 '
#594000000
0!
0$
#595000000
1!
b11111110 #
1$
b11111110 &
b11111111 '
#596000000
0!
0$
#597000000
1!
b11111111 #
1$
b11111111 &
b00000000 '
#598000000
0!
0$
#599000000
1!
b00000000 #
1$
b00000000 &
b00000001 '
#600000000
0!
0"
0$
0%
#601000000
1!
b00000001 #
1$
b00000001 &
b00000000 '
#602000000
0!
0$
#603000000
1!
b00000000 #
1$
b00000000 &
b11111111 '
#604000000
0!
0$
#605000000
1!
b11111111 #
1$
b11111111 &
b11111110 '
#606000000
0!
0$
#607000000
1!
b11111110 #
1$
b11111110 &
b11111101 '
#608000000
0!
0$
#609000000
1!
b11111101 #
1$
b11111101 &
b11111100 '
#610000000
0!
0$
#611000000
1!
b11111100 #
1$
b11111100 &
b11111011 '
#612000000
0!
0$
#613000000
1!
b11111011 #
1$
b11111011 &
b11111010 '
#614000000
0!
0$
#615000000
1!
b11111010 #
1$
b11111010 &
b11111001 '
#616000000
0!
0$
#617000000
1!
b11111001 #
1$
b11111001 &
b11111000 '
