FPGA/FPGA 04/skeleton04c/mux.m.vhd
---------------------------------------
-- lecture 02 shift register
-- just forwarding the signal
----------------------------------------

library ieee;
use ieee.std_logic_1164.all;
use ieee.numeric_std.all;

----------------------------------------

entity mux is
    GENERIC (
        OUTPUT_BITS    : integer := 4;  -- how many bits does each output have
        SLOTS          : integer := 2   -- giving how many slots we would like to mux
    );
    port(   
        i_slv_select  :   in std_logic_vector( 1 downto 0);
        i_slv_input   :   in std_logic_vector( 15 downto 0);-- insert size here
        o_slv_output  :  out std_logic_vector( OUTPUT_BITS-1 downto 0)-- insert size here
    );
end mux;  

----------------------------------------

architecture behavior of mux is
begin
	process(i_slv_input, i_slv_select)
	begin
		o_slv_output <= i_slv_input(to_integer(unsigned(i_slv_select))*4+3 downto to_integer(unsigned(i_slv_select))*4);
	end process;
end behavior;

------------------------------------------

FPGA/FPGA 04/skeleton04c/mux.tb.vhd
library ieee;
use ieee.std_logic_1164.all;
use ieee.numeric_std.all;

ENTITY mux_tb IS
END mux_tb;

ARCHITECTURE tb OF mux_tb IS 

    constant OUTPUT_BITS    : integer := 4;  -- how many bits does each output have
    constant SLOTS          : integer := 2;  -- giving how many slots we would like to mux

    COMPONENT mux is
        GENERIC (
            OUTPUT_BITS    : integer := 4;  -- how many bits does each output have
            SLOTS          : integer := 2   -- giving how many slots we would like to mux
        );
        port(   
            i_slv_select  :   in std_logic_vector( 1 downto 0);
            i_slv_input   :   in std_logic_vector( OUTPUT_BITS**2 - 1 downto 0);
            o_slv_output  :  out std_logic_vector( OUTPUT_BITS -1 downto 0)
        );
    end COMPONENT;

    -- "local" signals

    -- signals for UUT
    -- input 
    signal sel : std_logic_vector( 1 downto 0) := (others => '0');

    signal input : std_logic_vector( OUTPUT_BITS**2-1 downto 0);

    -- ouput
    signal o_slv_output  : std_logic_vector( OUTPUT_BITS-1 downto 0);

BEGIN 
    -- Instance of unit under test.
    mux1: mux 
        GENERIC MAP(
            OUTPUT_BITS  => OUTPUT_BITS,
            SLOTS        => SLOTS
        )
        port map(   
            i_slv_select => sel,
            i_slv_input  => input,
            o_slv_output => o_slv_output
        );

-------------------------------------------------------------------------------
    -- test bench definition.
    tb_test :process
    begin
        input <= "1111000010100101";

        sel <= "00";
        wait for 2 ns;
        sel <= "01";
        wait for 2 ns;
        sel <= "10";
        wait for 2 ns;
        sel <= "11";
        wait for 2 ns;

    end process;

END;

FPGA/FPGA 04/skeleton04c/mux.vcd
$date
  Fri Jan  8 15:12:59 2021
$end
$version
  GHDL v0
$end
$timescale
  1 fs
$end
$scope module standard $end
$upscope $end
$scope module textio $end
$upscope $end
$scope module std_logic_1164 $end
$upscope $end
$scope module numeric_std $end
$upscope $end
$scope module mux_tb $end
$var reg 2 ! sel[1:0] $end
$var reg 16 " input[15:0] $end
$var reg 4 # o_slv_output[3:0] $end
$scope module mux1 $end
$var reg 2 $ i_slv_select[1:0] $end
$var reg 16 % i_slv_input[15:0] $end
$var reg 4 & o_slv_output[3:0] $end
$upscope $end
$upscope $end
$enddefinitions $end
#0
b00 !
b1111000010100101 "
b0101 #
b00 $
b1111000010100101 %
b0101 &
#2000000
b01 !
b1010 #
b01 $
b1010 &
#4000000
b10 !
b0000 #
b10 $
b0000 &
#6000000
b11 !
b1111 #
b11 $
b1111 &
#8000000
b00 !
b0101 #
b00 $
b0101 &
#10000000
b01 !
b1010 #
b01 $
b1010 &
#12000000
b10 !
b0000 #
b10 $
b0000 &
#14000000
b11 !
b1111 #
b11 $
b1111 &
#16000000
b00 !
b0101 #
b00 $
b0101 &
#18000000
b01 !
b1010 #
b01 $
b1010 &
#20000000
b10 !
b0000 #
b10 $
b0000 &
#22000000
b11 !
b1111 #
b11 $
b1111 &
#24000000
b00 !
b0101 #
b00 $
b0101 &
#26000000
b01 !
b1010 #
b01 $
b1010 &
#28000000
b10 !
b0000 #
b10 $
b0000 &
#30000000
b11 !
b1111 #
b11 $
b1111 &
#32000000
b00 !
b0101 #
b00 $
b0101 &
#34000000
b01 !
b1010 #
b01 $
b1010 &
#36000000
b10 !
b0000 #
b10 $
b0000 &
#38000000
b11 !
b1111 #
b11 $
b1111 &
#40000000
b00 !
b0101 #
b00 $
b0101 &
#42000000
b01 !
b1010 #
b01 $
b1010 &
#44000000
b10 !
b0000 #
b10 $
b0000 &
#46000000
b11 !
b1111 #
b11 $
b1111 &
#48000000
b00 !
b0101 #
b00 $
b0101 &
#50000000
b01 !
b1010 #
b01 $
b1010 &
#52000000
b10 !
b0000 #
b10 $
b0000 &
#54000000
b11 !
b1111 #
b11 $
b1111 &
#56000000
b00 !
b0101 #
b00 $
b0101 &
#58000000
b01 !
b1010 #
b01 $
b1010 &
#60000000
b10 !
b0000 #
b10 $
b0000 &
#62000000
b11 !
b1111 #
b11 $
b1111 &
#64000000
b00 !
b0101 #
b00 $
b0101 &
#66000000
b01 !
b1010 #
b01 $
b1010 &
#68000000
b10 !
b0000 #
b10 $
b0000 &
#70000000
b11 !
b1111 #
b11 $
b1111 &
#72000000
b00 !
b0101 #
b00 $
b0101 &
#74000000
b01 !
b1010 #
b01 $
b1010 &
#76000000
b10 !
b0000 #
b10 $
b0000 &
#78000000
b11 !
b1111 #
b11 $
b1111 &
#80000000
b00 !
b0101 #
b00 $
b0101 &
#82000000
b01 !
b1010 #
b01 $
b1010 &
#84000000
b10 !
b0000 #
b10 $
b0000 &
#86000000
b11 !
b1111 #
b11 $
b1111 &
#88000000
b00 !
b0101 #
b00 $
b0101 &
#90000000
b01 !
b1010 #
b01 $
b1010 &
#92000000
b10 !
b0000 #
b10 $
b0000 &
#94000000
b11 !
b1111 #
b11 $
b1111 &
#96000000
b00 !
b0101 #
b00 $
b0101 &
#98000000
b01 !
b1010 #
b01 $
b1010 &
#100000000
b10 !
b0000 #
b10 $
b0000 &
#102000000
b11 !
b1111 #
b11 $
b1111 &
#104000000
b00 !
b0101 #
b00 $
b0101 &
#106000000
b01 !
b1010 #
b01 $
b1010 &
#108000000
b10 !
b0000 #
b10 $
b0000 &
#110000000
b11 !
b1111 #
b11 $
b1111 &
#112000000
b00 !
b0101 #
b00 $
b0101 &
#114000000
b01 !
b1010 #
b01 $
b1010 &
#116000000
b10 !
b0000 #
b10 $
b0000 &
#118000000
b11 !
b1111 #
b11 $
b1111 &
#120000000
b00 !
b0101 #
b00 $
b0101 &
#122000000
b01 !
b1010 #
b01 $
b1010 &
#124000000
b10 !
b0000 #
b10 $
b0000 &
#126000000
b11 !
b1111 #
b11 $
b1111 &
#128000000
b00 !
b0101 #
b00 $
b0101 &
#130000000
b01 !
b1010 #
b01 $
b1010 &
#132000000
b10 !
b0000 #
b10 $
b0000 &
#134000000
b11 !
b1111 #
b11 $
b1111 &
#136000000
b00 !
b0101 #
b00 $
b0101 &
#138000000
b01 !
b1010 #
b01 $
b1010 &
#140000000
b10 !
b0000 #
b10 $
b0000 &
#142000000
b11 !
b1111 #
b11 $
b1111 &
#144000000
b00 !
b0101 #
b00 $
b0101 &
#146000000
b01 !
b1010 #
b01 $
b1010 &
#148000000
b10 !
b0000 #
b10 $
b0000 &
#150000000
b11 !
b1111 #
b11 $
b1111 &
#152000000
b00 !
b0101 #
b00 $
b0101 &
#154000000
b01 !
b1010 #
b01 $
b1010 &
#156000000
b10 !
b0000 #
b10 $
b0000 &
#158000000
b11 !
b1111 #
b11 $
b1111 &
#160000000
b00 !
b0101 #
b00 $
b0101 &
#162000000
b01 !
b1010 #
b01 $
b1010 &
#164000000
b10 !
b0000 #
b10 $
b0000 &
#166000000
b11 !
b1111 #
b11 $
b1111 &
#168000000
b00 !
b0101 #
b00 $
b0101 &
#170000000
b01 !
b1010 #
b01 $
b1010 &
#172000000
b10 !
b0000 #
b10 $
b0000 &
#174000000
b11 !
b1111 #
b11 $
b1111 &
#176000000
b00 !
b0101 #
b00 $
b0101 &
#178000000
b01 !
b1010 #
b01 $
b1010 &
#180000000
b10 !
b0000 #
b10 $
b0000 &
#182000000
b11 !
b1111 #
b11 $
b1111 &
#184000000
b00 !
b0101 #
b00 $
b0101 &
#186000000
b01 !
b1010 #
b01 $
b1010 &
#188000000
b10 !
b0000 #
b10 $
b0000 &
#190000000
b11 !
b1111 #
b11 $
b1111 &
#192000000
b00 !
b0101 #
b00 $
b0101 &
#194000000
b01 !
b1010 #
b01 $
b1010 &
#196000000
b10 !
b0000 #
b10 $
b0000 &
#198000000
b11 !
b1111 #
b11 $
b1111 &
#200000000
b00 !
b0101 #
b00 $
b0101 &
#202000000
b01 !
b1010 #
b01 $
b1010 &
#204000000
b10 !
b0000 #
b10 $
b0000 &
#206000000
b11 !
b1111 #
b11 $
b1111 &
#208000000
b00 !
b0101 #
b00 $
b0101 &
#210000000
b01 !
b1010 #
b01 $
b1010 &
#212000000
b10 !
b0000 #
b10 $
b0000 &
#214000000
b11 !
b1111 #
b11 $
b1111 &
#216000000
b00 !
b0101 #
b00 $
b0101 &
#218000000
b01 !
b1010 #
b01 $
b1010 &
#220000000
b10 !
b0000 #
b10 $
b0000 &
#222000000
b11 !
b1111 #
b11 $
b1111 &
#224000000
b00 !
b0101 #
b00 $
b0101 &
#226000000
b01 !
b1010 #
b01 $
b1010 &
#228000000
b10 !
b0000 #
b10 $
b0000 &
#230000000
b11 !
b1111 #
b11 $
b1111 &
#232000000
b00 !
b0101 #
b00 $
b0101 &
#234000000
b01 !
b1010 #
b01 $
b1010 &
#236000000
b10 !
b0000 #
b10 $
b0000 &
#238000000
b11 !
b1111 #
b11 $
b1111 &
#240000000
b00 !
b0101 #
b00 $
b0101 &
#242000000
b01 !
b1010 #
b01 $
b1010 &
#244000000
b10 !
b0000 #
b10 $
b0000 &
#246000000
b11 !
b1111 #
b11 $
b1111 &
#248000000
b00 !
b0101 #
b00 $
b0101 &
#250000000
b01 !
b1010 #
b01 $
b1010 &
#252000000
b10 !
b0000 #
b10 $
b0000 &
#254000000
b11 !
b1111 #
b11 $
b1111 &
#256000000
b00 !
b0101 #
b00 $
b0101 &
#258000000
b01 !
b1010 #
b01 $
b1010 &
#260000000
b10 !
b0000 #
b10 $
b0000 &
#262000000
b11 !
b1111 #
b11 $
b1111 &
#264000000
b00 !
b0101 #
b00 $
b0101 &
#266000000
b01 !
b1010 #
b01 $
b1010 &
#268000000
b10 !
b0000 #
b10 $
b0000 &
#270000000
b11 !
b1111 #
b11 $
b1111 &
#272000000
b00 !
b0101 #
b00 $
b0101 &
#274000000
b01 !
b1010 #
b01 $
b1010 &
#276000000
b10 !
b0000 #
b10 $
b0000 &
#278000000
b11 !
b1111 #
b11 $
b1111 &
#280000000
b00 !
b0101 #
b00 $
b0101 &
#282000000
b01 !
b1010 #
b01 $
b1010 &
#284000000
b10 !
b0000 #
b10 $
b0000 &
#286000000
b11 !
b1111 #
b11 $
b1111 &
#288000000
b00 !
b0101 #
b00 $
b0101 &
#290000000
b01 !
b1010 #
b01 $
b1010 &
#292000000
b10 !
b0000 #
b10 $
b0000 &
#294000000
b11 !
b1111 #
b11 $
b1111 &
#296000000
b00 !
b0101 #
b00 $
b0101 &
#298000000
b01 !
b1010 #
b01 $
b1010 &
#300000000
b10 !
b0000 #
b10 $
b0000 &
#302000000
b11 !
b1111 #
b11 $
b1111 &
#304000000
b00 !
b0101 #
b00 $
b0101 &
#306000000
b01 !
b1010 #
b01 $
b1010 &
#308000000
b10 !
b0000 #
b10 $
b0000 &
#310000000
b11 !
b1111 #
b11 $
b1111 &
#312000000
b00 !
b0101 #
b00 $
b0101 &
#314000000
b01 !
b1010 #
b01 $
b1010 &
#316000000
b10 !
b0000 #
b10 $
b0000 &
#318000000
b11 !
b1111 #
b11 $
b1111 &
#320000000
b00 !
b0101 #
b00 $
b0101 &
#322000000
b01 !
b1010 #
b01 $
b1010 &
#324000000
b10 !
b0000 #
b10 $
b0000 &
#326000000
b11 !
b1111 #
b11 $
b1111 &
#328000000
b00 !
b0101 #
b00 $
b0101 &
#330000000
b01 !
b1010 #
b01 $
b1010 &
#332000000
b10 !
b0000 #
b10 $
b0000 &
#334000000
b11 !
b1111 #
b11 $
b1111 &
#336000000
b00 !
b0101 #
b00 $
b0101 &
#338000000
b01 !
b1010 #
b01 $
b1010 &
#340000000
b10 !
b0000 #
b10 $
b0000 &
#342000000
b11 !
b1111 #
b11 $
b1111 &
#344000000
b00 !
b0101 #
b00 $
b0101 &
#346000000
b01 !
b1010 #
b01 $
b1010 &
#348000000
b10 !
b0000 #
b10 $
b0000 &
#350000000
b11 !
b1111 #
b11 $
b1111 &
#352000000
b00 !
b0101 #
b00 $
b0101 &
#354000000
b01 !
b1010 #
b01 $
b1010 &
#356000000
b10 !
b0000 #
b10 $
b0000 &
#358000000
b11 !
b1111 #
b11 $
b1111 &
#360000000
b00 !
b0101 #
b00 $
b0101 &
#362000000
b01 !
b1010 #
b01 $
b1010 &
#364000000
b10 !
b0000 #
b10 $
b0000 &
#366000000
b11 !
b1111 #
b11 $
b1111 &
#368000000
b00 !
b0101 #
b00 $
b0101 &
#370000000
b01 !
b1010 #
b01 $
b1010 &
#372000000
b10 !
b0000 #
b10 $
b0000 &
#374000000
b11 !
b1111 #
b11 $
b1111 &
#376000000
b00 !
b0101 #
b00 $
b0101 &
#378000000
b01 !
b1010 #
b01 $
b1010 &
#380000000
b10 !
b0000 #
b10 $
b0000 &
#382000000
b11 !
b1111 #
b11 $
b1111 &
#384000000
b00 !
b0101 #
b00 $
b0101 &
#386000000
b01 !
b1010 #
b01 $
b1010 &
#388000000
b10 !
b0000 #
b10 $
b0000 &
#390000000
b11 !
b1111 #
b11 $
b1111 &
#392000000
b00 !
b0101 #
b00 $
b0101 &
#394000000
b01 !
b1010 #
b01 $
b1010 &
#396000000
b10 !
b0000 #
b10 $
b0000 &
#398000000
b11 !
b1111 #
b11 $
b1111 &
#400000000
b00 !
b0101 #
b00 $
b0101 &
#402000000
b01 !
b1010 #
b01 $
b1010 &
#404000000
b10 !
b0000 #
b10 $
b0000 &
#406000000
b11 !
b1111 #
b11 $
b1111 &
#408000000
b00 !
b0101 #
b00 $
b0101 &
#410000000
b01 !
b1010 #
b01 $
b1010 &
#412000000
b10 !
b0000 #
b10 $
b0000 &
#414000000
b11 !
b1111 #
b11 $
b1111 &
#416000000
b00 !
b0101 #
b00 $
b0101 &
#418000000
b01 !
b1010 #
b01 $
b1010 &
#420000000
b10 !
b0000 #
b10 $
b0000 &
#422000000
b11 !
b1111 #
b11 $
b1111 &
#424000000
b00 !
b0101 #
b00 $
b0101 &
#426000000
b01 !
b1010 #
b01 $
b1010 &
#428000000
b10 !
b0000 #
b10 $
b0000 &
#430000000
b11 !
b1111 #
b11 $
b1111 &
#432000000
b00 !
b0101 #
b00 $
b0101 &
#434000000
b01 !
b1010 #
b01 $
b1010 &
#436000000
b10 !
b0000 #
b10 $
b0000 &
#438000000
b11 !
b1111 #
b11 $
b1111 &
#440000000
b00 !
b0101 #
b00 $
b0101 &
#442000000
b01 !
b1010 #
b01 $
b1010 &
#444000000
b10 !
b0000 #
b10 $
b0000 &
#446000000
b11 !
b1111 #
b11 $
b1111 &
#448000000
b00 !
b0101 #
b00 $
b0101 &
#450000000
b01 !
b1010 #
b01 $
b1010 &
#452000000
b10 !
b0000 #
b10 $
b0000 &
#454000000
b11 !
b1111 #
b11 $
b1111 &
#456000000
b00 !
b0101 #
b00 $
b0101 &
#458000000
b01 !
b1010 #
b01 $
b1010 &
#460000000
b10 !
b0000 #
b10 $
b0000 &
#462000000
b11 !
b1111 #
b11 $
b1111 &
#464000000
b00 !
b0101 #
b00 $
b0101 &
#466000000
b01 !
b1010 #
b01 $
b1010 &
#468000000
b10 !
b0000 #
b10 $
b0000 &
#470000000
b11 !
b1111 #
b11 $
b1111 &
#472000000
b00 !
b0101 #
b00 $
b0101 &
#474000000
b01 !
b1010 #
b01 $
b1010 &
#476000000
b10 !
b0000 #
b10 $
b0000 &
#478000000
b11 !
b1111 #
b11 $
b1111 &
#480000000
b00 !
b0101 #
b00 $
b0101 &
#482000000
b01 !
b1010 #
b01 $
b1010 &
#484000000
b10 !
b0000 #
b10 $
b0000 &
#486000000
b11 !
b1111 #
b11 $
b1111 &
#488000000
b00 !
b0101 #
b00 $
b0101 &
#490000000
b01 !
b1010 #
b01 $
b1010 &
#492000000
b10 !
b0000 #
b10 $
b0000 &
#494000000
b11 !
b1111 #
b11 $
b1111 &
#496000000
b00 !
b0101 #
b00 $
b0101 &
#498000000
b01 !
b1010 #
b01 $
b1010 &
#500000000
b10 !
b0000 #
b10 $
b0000 &
#502000000
b11 !
b1111 #
b11 $
b1111 &
#504000000
b00 !
b0101 #
b00 $
b0101 &
#506000000
b01 !
b1010 #
b01 $
b1010 &
#508000000
b10 !
b0000 #
b10 $
b0000 &
#510000000
b11 !
b1111 #
b11 $
b1111 &
#512000000
b00 !
b0101 #
b00 $
b0101 &
#514000000
b01 !
b1010 #
b01 $
b1010 &
#516000000
b10 !
b0000 #
b10 $
b0000 &
#518000000
b11 !
b1111 #
b11 $
b1111 &
#520000000
b00 !
b0101 #
b00 $
b0101 &
#522000000
b01 !
b1010 #
b01 $
b1010 &
#524000000
b10 !
b0000 #
b10 $
b0000 &
#526000000
b11 !
b1111 #
b11 $
b1111 &
#528000000
b00 !
b0101 #
b00 $
b0101 &
#530000000
b01 !
b1010 #
b01 $
b1010 &
#532000000
b10 !
b0000 #
b10 $
b0000 &
#534000000
b11 !
b1111 #
b11 $
b1111 &
#536000000
b00 !
b0101 #
b00 $
b0101 &
#538000000
b01 !
b1010 #
b01 $
b1010 &
#540000000
b10 !
b0000 #
b10 $
b0000 &
#542000000
b11 !
b1111 #
b11 $
b1111 &
#544000000
b00 !
b0101 #
b00 $
b0101 &
#546000000
b01 !
b1010 #
b01 $
b1010 &
#548000000
b10 !
b0000 #
b10 $
b0000 &
#550000000
b11 !
b1111 #
b11 $
b1111 &
#552000000
b00 !
b0101 #
b00 $
b0101 &
#554000000
b01 !
b1010 #
b01 $
b1010 &
#556000000
b10 !
b0000 #
b10 $
b0000 &
#558000000
b11 !
b1111 #
b11 $
b1111 &
#560000000
b00 !
b0101 #
b00 $
b0101 &
#562000000
b01 !
b1010 #
b01 $
b1010 &
#564000000
b10 !
b0000 #
b10 $
b0000 &
#566000000
b11 !
b1111 #
b11 $
b1111 &
#568000000
b00 !
b0101 #
b00 $
b0101 &
#570000000
b01 !
b1010 #
b01 $
b1010 &
#572000000
b10 !
b0000 #
b10 $
b0000 &
#574000000
b11 !
b1111 #
b11 $
b1111 &
#576000000
b00 !
b0101 #
b00 $
b0101 &
#578000000
b01 !
b1010 #
b01 $
b1010 &
#580000000
b10 !
b0000 #
b10 $
b0000 &
#582000000
b11 !
b1111 #
b11 $
b1111 &
#584000000
b00 !
b0101 #
b00 $
b0101 &
#586000000
b01 !
b1010 #
b01 $
b1010 &
#588000000
b10 !
b0000 #
b10 $
b0000 &
#590000000
b11 !
b1111 #
b11 $
b1111 &
#592000000
b00 !
b0101 #
b00 $
b0101 &
#594000000
b01 !
b1010 #
b01 $
b1010 &
#596000000
b10 !
b0000 #
b10 $
b0000 &
#598000000
b11 !
b1111 #
b11 $
b1111 &
#600000000
b00 !
b0101 #
b00 $
b0101 &
#602000000
b01 !
b1010 #
b01 $
b1010 &
#604000000
b10 !
b0000 #
b10 $
b0000 &
#606000000
b11 !
b1111 #
b11 $
b1111 &
#608000000
b00 !
b0101 #
b00 $
b0101 &
#610000000
b01 !
b1010 #
b01 $
b1010 &
#612000000
b10 !
b0000 #
b10 $
b0000 &
#614000000
b11 !
b1111 #
b11 $
b1111 &
#616000000
b00 !
b0101 #
b00 $
b0101 &
#618000000
b01 !
b1010 #
b01 $
b1010 &
#620000000
b10 !
b0000 #
b10 $
b0000 &
#622000000
b11 !
b1111 #
b11 $
b1111 &
#624000000
b00 !
b0101 #
b00 $
b0101 &
#626000000
b01 !
b1010 #
b01 $
b1010 &
#628000000
b10 !
b0000 #
b10 $
b0000 &
#630000000
b11 !
b1111 #
b11 $
b1111 &
#632000000
b00 !
b0101 #
b00 $
b0101 &
#634000000
b01 !
b1010 #
b01 $
b1010 &
#636000000
b10 !
b0000 #
b10 $
b0000 &
#638000000
b11 !
b1111 #
b11 $
b1111 &
#640000000
b00 !
b0101 #
b00 $
b0101 &
#642000000
b01 !
b1010 #
b01 $
b1010 &
#644000000
b10 !
b0000 #
b10 $
b0000 &
#646000000
b11 !
b1111 #
b11 $
b1111 &
#648000000
b00 !
b0101 #
b00 $
b0101 &
#650000000
b01 !
b1010 #
b01 $
b1010 &
#652000000
b10 !
b0000 #
b10 $
b0000 &
#654000000
b11 !
b1111 #
b11 $
b1111 &
#656000000
b00 !
b0101 #
b00 $
b0101 &
#658000000
b01 !
b1010 #
b01 $
b1010 &
#660000000
b10 !
b0000 #
b10 $
b0000 &
#662000000
b11 !
b1111 #
b11 $
b1111 &
#664000000
b00 !
b0101 #
b00 $
b0101 &
#666000000
b01 !
b1010 #
b01 $
b1010 &
#668000000
b10 !
b0000 #
b10 $
b0000 &
#670000000
b11 !
b1111 #
b11 $
b1111 &
#672000000
b00 !
b0101 #
b00 $
b0101 &
#674000000
b01 !
b1010 #
b01 $
b1010 &
#676000000
b10 !
b0000 #
b10 $
b0000 &
#678000000
b11 !
b1111 #
b11 $
b1111 &
#680000000
b00 !
b0101 #
b00 $
b0101 &
#682000000
b01 !
b1010 #
b01 $
b1010 &
#684000000
b10 !
b0000 #
b10 $
b0000 &
#686000000
b11 !
b1111 #
b11 $
b1111 &
#688000000
b00 !
b0101 #
b00 $
b0101 &
#690000000
b01 !
b1010 #
b01 $
b1010 &
#692000000
b10 !
b0000 #
b10 $
b0000 &
#694000000
b11 !
b1111 #
b11 $
b1111 &
#696000000
b00 !
b0101 #
b00 $
b0101 &
#698000000
b01 !
b1010 #
b01 $
b1010 &
#700000000
b10 !
b0000 #
b10 $
b0000 &
#702000000
b11 !
b1111 #
b11 $
b1111 &
#704000000
b00 !
b0101 #
b00 $
b0101 &
#706000000
b01 !
b1010 #
b01 $
b1010 &
#708000000
b10 !
b0000 #
b10 $
b0000 &
#710000000
b11 !
b1111 #
b11 $
b1111 &
#712000000
b00 !
b0101 #
b00 $
b0101 &
#714000000
b01 !
b1010 #
b01 $
b1010 &
#716000000
b10 !
b0000 #
b10 $
b0000 &
#718000000
b11 !
b1111 #
b11 $
b1111 &
#720000000
b00 !
b0101 #
b00 $
b0101 &
#722000000
b01 !
b1010 #
b01 $
b1010 &
#724000000
b10 !
b0000 #
b10 $
b0000 &
#726000000
b11 !
b1111 #
b11 $
b1111 &
#728000000
b00 !
b0101 #
b00 $
b0101 &
#730000000
b01 !
b1010 #
b01 $
b1010 &
#732000000
b10 !
b0000 #
b10 $
b0000 &
#734000000
b11 !
b1111 #
b11 $
b1111 &
#736000000
b00 !
b0101 #
b00 $
b0101 &
#738000000
b01 !
b1010 #
b01 $
b1010 &
#740000000
b10 !
b0000 #
b10 $
b0000 &
#742000000
b11 !
b1111 #
b11 $
b1111 &
#744000000
b00 !
b0101 #
b00 $
b0101 &
#746000000
b01 !
b1010 #
b01 $
b1010 &
#748000000
b10 !
b0000 #
b10 $
b0000 &
#750000000
b11 !
b1111 #
b11 $
b1111 &
#752000000
b00 !
b0101 #
b00 $
b0101 &
#754000000
b01 !
b1010 #
b01 $
b1010 &
#756000000
b10 !
b0000 #
b10 $
b0000 &
#758000000
b11 !
b1111 #
b11 $
b1111 &
#760000000
b00 !
b0101 #
b00 $
b0101 &
#762000000
b01 !
b1010 #
b01 $
b1010 &
#764000000
b10 !
b0000 #
b10 $
b0000 &
#766000000
b11 !
b1111 #
b11 $
b1111 &
#768000000
b00 !
b0101 #
b00 $
b0101 &
#770000000
b01 !
b1010 #
b01 $
b1010 &
#772000000
b10 !
b0000 #
b10 $
b0000 &
#774000000
b11 !
b1111 #
b11 $
b1111 &
#776000000
b00 !
b0101 #
b00 $
b0101 &
#778000000
b01 !
b1010 #
b01 $
b1010 &
#780000000
b10 !
b0000 #
b10 $
b0000 &
#782000000
b11 !
b1111 #
b11 $
b1111 &
#784000000
b00 !
b0101 #
b00 $
b0101 &
#786000000
b01 !
b1010 #
b01 $
b1010 &
#788000000
b10 !
b0000 #
b10 $
b0000 &
#790000000
b11 !
b1111 #
b11 $
b1111 &
#792000000
b00 !
b0101 #
b00 $
b0101 &
#794000000
b01 !
b1010 #
b01 $
b1010 &
#796000000
b10 !
b0000 #
b10 $
b0000 &
#798000000
b11 !
b1111 #
b11 $
b1111 &
#800000000
b00 !
b0101 #
b00 $
b0101 &
#802000000
b01 !
b1010 #
b01 $
b1010 &
#804000000
b10 !
b0000 #
b10 $
b0000 &
#806000000
b11 !
b1111 #
b11 $
b1111 &
#808000000
b00 !
b0101 #
b00 $
b0101 &
#810000000
b01 !
b1010 #
b01 $
b1010 &
#812000000
b10 !
b0000 #
b10 $
b0000 &
#814000000
b11 !
b1111 #
b11 $
b1111 &
#816000000
b00 !
b0101 #
b00 $
b0101 &
#818000000
b01 !
b1010 #
b01 $
b1010 &
#820000000
b10 !
b0000 #
b10 $
b0000 &
#822000000
b11 !
b1111 #
b11 $
b1111 &
#824000000
b00 !
b0101 #
b00 $
b0101 &
#826000000
b01 !
b1010 #
b01 $
b1010 &
#828000000
b10 !
b0000 #
b10 $
b0000 &
#830000000
b11 !
b1111 #
b11 $
b1111 &
#832000000
b00 !
b0101 #
b00 $
b0101 &
#834000000
b01 !
b1010 #
b01 $
b1010 &
#836000000
b10 !
b0000 #
b10 $
b0000 &
#838000000
b11 !
b1111 #
b11 $
b1111 &
#840000000
b00 !
b0101 #
b00 $
b0101 &
#842000000
b01 !
b1010 #
b01 $
b1010 &
#844000000
b10 !
b0000 #
b10 $
b0000 &
#846000000
b11 !
b1111 #
b11 $
b1111 &
#848000000
b00 !
b0101 #
b00 $
b0101 &
#850000000
b01 !
b1010 #
b01 $
b1010 &
#852000000
b10 !
b0000 #
b10 $
b0000 &
#854000000
b11 !
b1111 #
b11 $
b1111 &
#856000000
b00 !
b0101 #
b00 $
b0101 &
#858000000
b01 !
b1010 #
b01 $
b1010 &
#860000000
b10 !
b0000 #
b10 $
b0000 &
#862000000
b11 !
b1111 #
b11 $
b1111 &
#864000000
b00 !
b0101 #
b00 $
b0101 &
#866000000
b01 !
b1010 #
b01 $
b1010 &
#868000000
b10 !
b0000 #
b10 $
b0000 &
#870000000
b11 !
b1111 #
b11 $
b1111 &
#872000000
b00 !
b0101 #
b00 $
b0101 &
#874000000
b01 !
b1010 #
b01 $
b1010 &
#876000000
b10 !
b0000 #
b10 $
b0000 &
#878000000
b11 !
b1111 #
b11 $
b1111 &
#880000000
b00 !
b0101 #
b00 $
b0101 &
#882000000
b01 !
b1010 #
b01 $
b1010 &
#884000000
b10 !
b0000 #
b10 $
b0000 &
#886000000
b11 !
b1111 #
b11 $
b1111 &
#888000000
b00 !
b0101 #
b00 $
b0101 &
#890000000
b01 !
b1010 #
b01 $
b1010 &
#892000000
b10 !
b0000 #
b10 $
b0000 &
#894000000
b11 !
b1111 #
b11 $
b1111 &
#896000000
b00 !
b0101 #
b00 $
b0101 &
#898000000
b01 !
b1010 #
b01 $
b1010 &
#900000000
b10 !
b0000 #
b10 $
b0000 &
#902000000
b11 !
b1111 #
b11 $
b1111 &
#904000000
b00 !
b0101 #
b00 $
b0101 &
#906000000
b01 !
b1010 #
b01 $
b1010 &
#908000000
b10 !
b0000 #
b10 $
b0000 &
#910000000
b11 !
b1111 #
b11 $
b1111 &
#912000000
b00 !
b0101 #
b00 $
b0101 &
#914000000
b01 !
b1010 #
b01 $
b1010 &
#916000000
b10 !
b0000 #
b10 $
b0000 &
#918000000
b11 !
b1111 #
b11 $
b1111 &
#920000000
b00 !
b0101 #
b00 $
b0101 &
#922000000
b01 !
b1010 #
b01 $
b1010 &
#924000000
b10 !
b0000 #
b10 $
b0000 &
#926000000
b11 !
b1111 #
b11 $
b1111 &
#928000000
b00 !
b0101 #
b00 $
b0101 &
#930000000
b01 !
b1010 #
b01 $
b1010 &
#932000000
b10 !
b0000 #
b10 $
b0000 &
#934000000
b11 !
b1111 #
b11 $
b1111 &
#936000000
b00 !
b0101 #
b00 $
b0101 &
#938000000
b01 !
b1010 #
b01 $
b1010 &
#940000000
b10 !
b0000 #
b10 $
b0000 &
#942000000
b11 !
b1111 #
b11 $
b1111 &
#944000000
b00 !
b0101 #
b00 $
b0101 &
#946000000
b01 !
b1010 #
b01 $
b1010 &
#948000000
b10 !
b0000 #
b10 $
b0000 &
#950000000
b11 !
b1111 #
b11 $
b1111 &
#952000000
b00 !
b0101 #
b00 $
b0101 &
#954000000
b01 !
b1010 #
b01 $
b1010 &
#956000000
b10 !
b0000 #
b10 $
b0000 &
#958000000
b11 !
b1111 #
b11 $
b1111 &
#960000000
b00 !
b0101 #
b00 $
b0101 &
#962000000
b01 !
b1010 #
b01 $
b1010 &
#964000000
b10 !
b0000 #
b10 $
b0000 &
#966000000
b11 !
b1111 #
b11 $
b1111 &
#968000000
b00 !
b0101 #
b00 $
b0101 &
#970000000
b01 !
b1010 #
b01 $
b1010 &
#972000000
b10 !
b0000 #
b10 $
b0000 &
#974000000
b11 !
b1111 #
b11 $
b1111 &
#976000000
b00 !
b0101 #
b00 $
b0101 &
#978000000
b01 !
b1010 #
b01 $
b1010 &
#980000000
b10 !
b0000 #
b10 $
b0000 &
#982000000
b11 !
b1111 #
b11 $
b1111 &
#984000000
b00 !
b0101 #
b00 $
b0101 &
#986000000
b01 !
b1010 #
b01 $
b1010 &
#988000000
b10 !
b0000 #
b10 $
b0000 &
#990000000
b11 !
b1111 #
b11 $
b1111 &
#992000000
b00 !
b0101 #
b00 $
b0101 &
