FPGA/Solutions 03/lecture03c/counter.m.vhd
---------------------------------------
-- lecture 02 shift register
-- just forwarding the signal
----------------------------------------

library ieee;
use ieee.std_logic_1164.all;
use ieee.numeric_std.all;

----------------------------------------

entity counter is
    generic(
        DATA_WIDTH    :  integer := 8
    );
    port(   
        i_sl_CLK      :  in  std_logic;                                 -- clock
        i_sl_en       :  in  std_logic;                                 -- enable
        i_sl_dir      :  in  std_logic;                                 -- direction
        i_sl_rst      :  in  std_logic;                                 -- reset
        o_slv_counter :  out std_logic_vector(DATA_WIDTH-1  downto 0)   -- counter
    );
end counter;  

----------------------------------------

architecture behavior of counter is
    signal cnt : unsigned(DATA_WIDTH-1 downto 0) := (others => '0');  -- define signal, because we cannot readback outputs
begin

    process(i_sl_CLK)
    begin
        if rising_edge(i_sl_CLK) then
            if (i_sl_en = '1') then
                if(i_sl_dir = '0') then
                    cnt <= cnt + 1;
                else
                    cnt <= cnt - 1;
                end if;
            elsif ( i_sl_rst = '1') then
                cnt <= (others => '0');
            end if;
            o_slv_counter <= std_logic_vector(cnt);
        end if;
    end process;

end behavior;

------------------------------------------

FPGA/Solutions 03/lecture03c/pwm.m.vhd
---------------------------------------
-- lecture 02 shift register
-- just forwarding the signal
----------------------------------------

library ieee;
use ieee.std_logic_1164.all;
use ieee.numeric_std.all;

----------------------------------------

entity pwm is
    generic(
        DATA_WIDTH    :  integer := 8
    );
    port(   
        i_sl_CLK      :  in  std_logic;                                 -- clock
        i_slv_val     :  in  std_logic_vector(DATA_WIDTH-1 downto 0);   -- pwm value
        o_sl_pwm      :  out std_logic                                  -- pwm output
    );
end pwm;  

----------------------------------------

architecture behavior of pwm is
    COMPONENT counter is
        generic(
            DATA_WIDTH    :  integer := 8
        );
        port(   
            i_sl_CLK      :  in  std_logic;                      -- clock
            i_sl_en       :  in  std_logic;                      -- enable
            i_sl_dir      :  in  std_logic;                      -- direction
            i_sl_rst      :  in  std_logic;                                 -- reset
            o_slv_counter :  out std_logic_vector(DATA_WIDTH-1 downto 0)    -- counter
        );
    end COMPONENT;

    signal slv_pwm_cnt : std_logic_vector(DATA_WIDTH-1 downto 0) := (others => '0');

begin
    pwm_cnt: counter 
    GENERIC MAP(
        DATA_WIDTH => DATA_WIDTH
    )
    PORT MAP (
        i_sl_CLK    => i_sl_clk,
        i_sl_en     => '1',
        i_sl_dir    => '0',
        i_sl_rst    => '0',
        o_slv_counter => slv_pwm_cnt
    );


    process(i_sl_CLK)
    begin
        if rising_edge(i_sl_CLK) then
            if unsigned(slv_pwm_cnt) >= unsigned(i_slv_val) then
                o_sl_pwm <= '0';
            else
                o_sl_pwm <= '1';
            end if;
        end if;
    end process;

end behavior;

------------------------------------------

FPGA/FPGA 03/skeleton3c/pwm.tb.vhd
library ieee;
use ieee.std_logic_1164.all;

ENTITY pwm_tb IS
END pwm_tb;

ARCHITECTURE tb OF pwm_tb IS 

    -- some constant values
    constant DATA_WIDTH : integer := 4;

    COMPONENT pwm is
        generic(
            DATA_WIDTH    :  integer := 8
        );
        port(   
            i_sl_CLK      :  in  std_logic;                      -- clock
            i_slv_val     :  in  std_logic_vector(DATA_WIDTH-1 downto 0);    -- pwm value
            o_sl_pwm      :  out std_logic                       -- output
        );
    end COMPONENT;

    -- "local" signals

    -- signals for UUT
    -- input 
    signal CLK    : std_logic := '0';

    signal i_slv_val : std_logic_vector(DATA_WIDTH-1 downto 0) := (others => '0');

    -- ouput
    signal o_sl_pwm : std_logic := '0';

BEGIN 
    -- Instance of unit under test.
    uut: pwm 
    GENERIC MAP(
        DATA_WIDTH  => DATA_WIDTH
    )
    PORT MAP (
        i_sl_CLK    => CLK,
        i_slv_val   => i_slv_val,
        o_sl_pwm    => o_sl_pwm
    );

-------------------------------------------------------------------------------
    -- test bench definition.
    tb_CLK :process
    begin
        CLK <= '0';
        wait for 1 ns;
        CLK <= '1';
        wait for 1 ns;
    end process;

    tb_rst: process
    begin
        wait for 300 ns;
        i_slv_val <= "0011";
        wait for 10 us;
    end process;

END;

FPGA/Solutions 03/lecture03c/pwm.vcd
$date
  Thu Jan  7 19:54:17 2021
$end
$version
  GHDL v0
$end
$timescale
  1 fs
$end
$scope module standard $end
$upscope $end
$scope module textio $end
$upscope $end
$scope module std_logic_1164 $end
$upscope $end
$scope module numeric_std $end
$upscope $end
$scope module pwm_tb $end
$var reg 1 ! clk $end
$var reg 4 " i_slv_val[3:0] $end
$var reg 1 # o_sl_pwm $end
$scope module uut $end
$var reg 1 $ i_sl_clk $end
$var reg 4 % i_slv_val[3:0] $end
$var reg 1 & o_sl_pwm $end
$var reg 4 ' slv_pwm_cnt[3:0] $end
$scope module pwm_cnt $end
$var reg 1 ( i_sl_clk $end
$var reg 1 ) i_sl_en $end
$var reg 1 * i_sl_dir $end
$var reg 1 + i_sl_rst $end
$var reg 4 , o_slv_counter[3:0] $end
$var reg 4 - cnt[3:0] $end
$upscope $end
$upscope $end
$upscope $end
$enddefinitions $end
#0
0!
b0000 "
U#
0$
b0000 %
U&
bUUUU '
0(
1)
0*
0+
bUUUU ,
b0000 -
#1000000
1!
1#
1$
1&
b0000 '
1(
b0000 ,
b0001 -
#2000000
0!
0$
0(
#3000000
1!
0#
1$
0&
b0001 '
1(
b0001 ,
b0010 -
#4000000
0!
0$
0(
#5000000
1!
1$
b0010 '
1(
b0010 ,
b0011 -
#6000000
0!
0$
0(
#7000000
1!
1$
b0011 '
1(
b0011 ,
b0100 -
#8000000
0!
0$
0(
#9000000
1!
1$
b0100 '
1(
b0100 ,
b0101 -
#10000000
0!
0$
0(
#11000000
1!
1$
b0101 '
1(
b0101 ,
b0110 -
#12000000
0!
0$
0(
#13000000
1!
1$
b0110 '
1(
b0110 ,
b0111 -
#14000000
0!
0$
0(
#15000000
1!
1$
b0111 '
1(
b0111 ,
b1000 -
#16000000
0!
0$
0(
#17000000
1!
1$
b1000 '
1(
b1000 ,
b1001 -
#18000000
0!
0$
0(
#19000000
1!
1$
b1001 '
1(
b1001 ,
b1010 -
#20000000
0!
0$
0(
#21000000
1!
1$
b1010 '
1(
b1010 ,
b1011 -
#22000000
0!
0$
0(
#23000000
1!
1$
b1011 '
1(
b1011 ,
b1100 -
#24000000
0!
0$
0(
#25000000
1!
1$
b1100 '
1(
b1100 ,
b1101 -
#26000000
0!
0$
0(
#27000000
1!
1$
b1101 '
1(
b1101 ,
b1110 -
#28000000
0!
0$
0(
#29000000
1!
1$
b1110 '
1(
b1110 ,
b1111 -
#30000000
0!
0$
0(
#31000000
1!
1$
b1111 '
1(
b1111 ,
b0000 -
#32000000
0!
0$
0(
#33000000
1!
1$
b0000 '
1(
b0000 ,
b0001 -
#34000000
0!
0$
0(
#35000000
1!
1$
b0001 '
1(
b0001 ,
b0010 -
#36000000
0!
0$
0(
#37000000
1!
1$
b0010 '
1(
b0010 ,
b0011 -
#38000000
0!
0$
0(
#39000000
1!
1$
b0011 '
1(
b0011 ,
b0100 -
#40000000
0!
0$
0(
#41000000
1!
1$
b0100 '
1(
b0100 ,
b0101 -
#42000000
0!
0$
0(
#43000000
1!
1$
b0101 '
1(
b0101 ,
b0110 -
#44000000
0!
0$
0(
#45000000
1!
1$
b0110 '
1(
b0110 ,
b0111 -
#46000000
0!
0$
0(
#47000000
1!
1$
b0111 '
1(
b0111 ,
b1000 -
#48000000
0!
0$
0(
#49000000
1!
1$
b1000 '
1(
b1000 ,
b1001 -
#50000000
0!
0$
0(
#51000000
1!
1$
b1001 '
1(
b1001 ,
b1010 -
#52000000
0!
0$
0(
#53000000
1!
1$
b1010 '
1(
b1010 ,
b1011 -
#54000000
0!
0$
0(
#55000000
1!
1$
b1011 '
1(
b1011 ,
b1100 -
#56000000
0!
0$
0(
#57000000
1!
1$
b1100 '
1(
b1100 ,
b1101 -
#58000000
0!
0$
0(
#59000000
1!
1$
b1101 '
1(
b1101 ,
b1110 -
#60000000
0!
0$
0(
#61000000
1!
1$
b1110 '
1(
b1110 ,
b1111 -
#62000000
0!
0$
0(
#63000000
1!
1$
b1111 '
1(
b1111 ,
b0000 -
#64000000
0!
0$
0(
#65000000
1!
1$
b0000 '
1(
b0000 ,
b0001 -
#66000000
0!
0$
0(
#67000000
1!
1$
b0001 '
1(
b0001 ,
b0010 -
#68000000
0!
0$
0(
#69000000
1!
1$
b0010 '
1(
b0010 ,
b0011 -
#70000000
0!
0$
0(
#71000000
1!
1$
b0011 '
1(
b0011 ,
b0100 -
#72000000
0!
0$
0(
#73000000
1!
1$
b0100 '
1(
b0100 ,
b0101 -
#74000000
0!
0$
0(
#75000000
1!
1$
b0101 '
1(
b0101 ,
b0110 -
#76000000
0!
0$
0(
#77000000
1!
1$
b0110 '
1(
b0110 ,
b0111 -
#78000000
0!
0$
0(
#79000000
1!
1$
b0111 '
1(
b0111 ,
b1000 -
#80000000
0!
0$
0(
#81000000
1!
1$
b1000 '
1(
b1000 ,
b1001 -
#82000000
0!
0$
0(
#83000000
1!
1$
b1001 '
1(
b1001 ,
b1010 -
#84000000
0!
0$
0(
#85000000
1!
1$
b1010 '
1(
b1010 ,
b1011 -
#86000000
0!
0$
0(
#87000000
1!
1$
b1011 '
1(
b1011 ,
b1100 -
#88000000
0!
0$
0(
#89000000
1!
1$
b1100 '
1(
b1100 ,
b1101 -
#90000000
0!
0$
0(
#91000000
1!
1$
b1101 '
1(
b1101 ,
b1110 -
#92000000
0!
0$
0(
#93000000
1!
1$
b1110 '
1(
b1110 ,
b1111 -
#94000000
0!
0$
0(
#95000000
1!
1$
b1111 '
1(
b1111 ,
b0000 -
#96000000
0!
0$
0(
#97000000
1!
1$
b0000 '
1(
b0000 ,
b0001 -
#98000000
0!
0$
0(
#99000000
1!
1$
b0001 '
1(
b0001 ,
b0010 -
#100000000
0!
0$
0(
#101000000
1!
1$
b0010 '
1(
b0010 ,
b0011 -
#102000000
0!
0$
0(
#103000000
1!
1$
b0011 '
1(
b0011 ,
b0100 -
#104000000
0!
0$
0(
#105000000
1!
1$
b0100 '
1(
b0100 ,
b0101 -
#106000000
0!
0$
0(
#107000000
1!
1$
b0101 '
1(
b0101 ,
b0110 -
#108000000
0!
0$
0(
#109000000
1!
1$
b0110 '
1(
b0110 ,
b0111 -
#110000000
0!
0$
0(
#111000000
1!
1$
b0111 '
1(
b0111 ,
b1000 -
#112000000
0!
0$
0(
#113000000
1!
1$
b1000 '
1(
b1000 ,
b1001 -
#114000000
0!
0$
0(
#115000000
1!
1$
b1001 '
1(
b1001 ,
b1010 -
#116000000
0!
0$
0(
#117000000
1!
1$
b1010 '
1(
b1010 ,
b1011 -
#118000000
0!
0$
0(
#119000000
1!
1$
b1011 '
1(
b1011 ,
b1100 -
#120000000
0!
0$
0(
#121000000
1!
1$
b1100 '
1(
b1100 ,
b1101 -
#122000000
0!
0$
0(
#123000000
1!
1$
b1101 '
1(
b1101 ,
b1110 -
#124000000
0!
0$
0(
#125000000
1!
1$
b1110 '
1(
b1110 ,
b1111 -
#126000000
0!
0$
0(
#127000000
1!
1$
b1111 '
1(
b1111 ,
b0000 -
#128000000
0!
0$
0(
#129000000
1!
1$
b0000 '
1(
b0000 ,
b0001 -
#130000000
0!
0$
0(
#131000000
1!
1$
b0001 '
1(
b0001 ,
b0010 -
#132000000
0!
0$
0(
#133000000
1!
1$
b0010 '
1(
b0010 ,
b0011 -
#134000000
0!
0$
0(
#135000000
1!
1$
b0011 '
1(
b0011 ,
b0100 -
#136000000
0!
0$
0(
#137000000
1!
1$
b0100 '
1(
b0100 ,
b0101 -
#138000000
0!
0$
0(
#139000000
1!
1$
b0101 '
1(
b0101 ,
b0110 -
#140000000
0!
0$
0(
#141000000
1!
1$
b0110 '
1(
b0110 ,
b0111 -
#142000000
0!
0$
0(
#143000000
1!
1$
b0111 '
1(
b0111 ,
b1000 -
#144000000
0!
0$
0(
#145000000
1!
1$
b1000 '
1(
b1000 ,
b1001 -
#146000000
0!
0$
0(
#147000000
1!
1$
b1001 '
1(
b1001 ,
b1010 -
#148000000
0!
0$
0(
#149000000
1!
1$
b1010 '
1(
b1010 ,
b1011 -
#150000000
0!
0$
0(
#151000000
1!
1$
b1011 '
1(
b1011 ,
b1100 -
#152000000
0!
0$
0(
#153000000
1!
1$
b1100 '
1(
b1100 ,
b1101 -
#154000000
0!
0$
0(
#155000000
1!
1$
b1101 '
1(
b1101 ,
b1110 -
#156000000
0!
0$
0(
#157000000
1!
1$
b1110 '
1(
b1110 ,
b1111 -
#158000000
0!
0$
0(
#159000000
1!
1$
b1111 '
1(
b1111 ,
b0000 -
#160000000
0!
0$
0(
#161000000
1!
1$
b0000 '
1(
b0000 ,
b0001 -
#162000000
0!
0$
0(
#163000000
1!
1$
b0001 '
1(
b0001 ,
b0010 -
#164000000
0!
0$
0(
#165000000
1!
1$
b0010 '
1(
b0010 ,
b0011 -
#166000000
0!
0$
0(
#167000000
1!
1$
b0011 '
1(
b0011 ,
b0100 -
#168000000
0!
0$
0(
#169000000
1!
1$
b0100 '
1(
b0100 ,
b0101 -
#170000000
0!
0$
0(
#171000000
1!
1$
b0101 '
1(
b0101 ,
b0110 -
#172000000
0!
0$
0(
#173000000
1!
1$
b0110 '
1(
b0110 ,
b0111 -
#174000000
0!
0$
0(
#175000000
1!
1$
b0111 '
1(
b0111 ,
b1000 -
#176000000
0!
0$
0(
#177000000
1!
1$
b1000 '
1(
b1000 ,
b1001 -
#178000000
0!
0$
0(
#179000000
1!
1$
b1001 '
1(
b1001 ,
b1010 -
#180000000
0!
0$
0(
#181000000
1!
1$
b1010 '
1(
b1010 ,
b1011 -
#182000000
0!
0$
0(
#183000000
1!
1$
b1011 '
1(
b1011 ,
b1100 -
#184000000
0!
0$
0(
#185000000
1!
1$
b1100 '
1(
b1100 ,
b1101 -
#186000000
0!
0$
0(
#187000000
1!
1$
b1101 '
1(
b1101 ,
b1110 -
#188000000
0!
0$
0(
#189000000
1!
1$
b1110 '
1(
b1110 ,
b1111 -
#190000000
0!
0$
0(
#191000000
1!
1$
b1111 '
1(
b1111 ,
b0000 -
#192000000
0!
0$
0(
#193000000
1!
1$
b0000 '
1(
b0000 ,
b0001 -
#194000000
0!
0$
0(
#195000000
1!
1$
b0001 '
1(
b0001 ,
b0010 -
#196000000
0!
0$
0(
#197000000
1!
1$
b0010 '
1(
b0010 ,
b0011 -
#198000000
0!
0$
0(
#199000000
1!
1$
b0011 '
1(
b0011 ,
b0100 -
#200000000
0!
0$
0(
#201000000
1!
1$
b0100 '
1(
b0100 ,
b0101 -
#202000000
0!
0$
0(
#203000000
1!
1$
b0101 '
1(
b0101 ,
b0110 -
#204000000
0!
0$
0(
#205000000
1!
1$
b0110 '
1(
b0110 ,
b0111 -
#206000000
0!
0$
0(
#207000000
1!
1$
b0111 '
1(
b0111 ,
b1000 -
#208000000
0!
0$
0(
#209000000
1!
1$
b1000 '
1(
b1000 ,
b1001 -
#210000000
0!
0$
0(
#211000000
1!
1$
b1001 '
1(
b1001 ,
b1010 -
#212000000
0!
0$
0(
#213000000
1!
1$
b1010 '
1(
b1010 ,
b1011 -
#214000000
0!
0$
0(
#215000000
1!
1$
b1011 '
1(
b1011 ,
b1100 -
#216000000
0!
0$
0(
#217000000
1!
1$
b1100 '
1(
b1100 ,
b1101 -
#218000000
0!
0$
0(
#219000000
1!
1$
b1101 '
1(
b1101 ,
b1110 -
#220000000
0!
0$
0(
#221000000
1!
1$
b1110 '
1(
b1110 ,
b1111 -
#222000000
0!
0$
0(
#223000000
1!
1$
b1111 '
1(
b1111 ,
b0000 -
#224000000
0!
0$
0(
#225000000
1!
1$
b0000 '
1(
b0000 ,
b0001 -
#226000000
0!
0$
0(
#227000000
1!
1$
b0001 '
1(
b0001 ,
b0010 -
#228000000
0!
0$
0(
#229000000
1!
1$
b0010 '
1(
b0010 ,
b0011 -
#230000000
0!
0$
0(
#231000000
1!
1$
b0011 '
1(
b0011 ,
b0100 -
#232000000
0!
0$
0(
#233000000
1!
1$
b0100 '
1(
b0100 ,
b0101 -
#234000000
0!
0$
0(
#235000000
1!
1$
b0101 '
1(
b0101 ,
b0110 -
#236000000
0!
0$
0(
#237000000
1!
1$
b0110 '
1(
b0110 ,
b0111 -
#238000000
0!
0$
0(
#239000000
1!
1$
b0111 '
1(
b0111 ,
b1000 -
#240000000
0!
0$
0(
#241000000
1!
1$
b1000 '
1(
b1000 ,
b1001 -
#242000000
0!
0$
0(
#243000000
1!
1$
b1001 '
1(
b1001 ,
b1010 -
#244000000
0!
0$
0(
#245000000
1!
1$
b1010 '
1(
b1010 ,
b1011 -
#246000000
0!
0$
0(
#247000000
1!
1$
b1011 '
1(
b1011 ,
b1100 -
#248000000
0!
0$
0(
#249000000
1!
1$
b1100 '
1(
b1100 ,
b1101 -
#250000000
0!
0$
0(
#251000000
1!
1$
b1101 '
1(
b1101 ,
b1110 -
#252000000
0!
0$
0(
#253000000
1!
1$
b1110 '
1(
b1110 ,
b1111 -
#254000000
0!
0$
0(
#255000000
1!
1$
b1111 '
1(
b1111 ,
b0000 -
#256000000
0!
0$
0(
#257000000
1!
1$
b0000 '
1(
b0000 ,
b0001 -
#258000000
0!
0$
0(
#259000000
1!
1$
b0001 '
1(
b0001 ,
b0010 -
#260000000
0!
0$
0(
#261000000
1!
1$
b0010 '
1(
b0010 ,
b0011 -
#262000000
0!
0$
0(
#263000000
1!
1$
b0011 '
1(
b0011 ,
b0100 -
#264000000
0!
0$
0(
#265000000
1!
1$
b0100 '
1(
b0100 ,
b0101 -
#266000000
0!
0$
0(
#267000000
1!
1$
b0101 '
1(
b0101 ,
b0110 -
#268000000
0!
0$
0(
#269000000
1!
1$
b0110 '
1(
b0110 ,
b0111 -
#270000000
0!
0$
0(
#271000000
1!
1$
b0111 '
1(
b0111 ,
b1000 -
#272000000
0!
0$
0(
#273000000
1!
1$
b1000 '
1(
b1000 ,
b1001 -
#274000000
0!
0$
0(
#275000000
1!
1$
b1001 '
1(
b1001 ,
b1010 -
#276000000
0!
0$
0(
#277000000
1!
1$
b1010 '
1(
b1010 ,
b1011 -
#278000000
0!
0$
0(
#279000000
1!
1$
b1011 '
1(
b1011 ,
b1100 -
#280000000
0!
0$
0(
#281000000
1!
1$
b1100 '
1(
b1100 ,
b1101 -
#282000000
0!
0$
0(
#283000000
1!
1$
b1101 '
1(
b1101 ,
b1110 -
#284000000
0!
0$
0(
#285000000
1!
1$
b1110 '
1(
b1110 ,
b1111 -
#286000000
0!
0$
0(
#287000000
1!
1$
b1111 '
1(
b1111 ,
b0000 -
#288000000
0!
0$
0(
#289000000
1!
1$
b0000 '
1(
b0000 ,
b0001 -
#290000000
0!
0$
0(
#291000000
1!
1$
b0001 '
1(
b0001 ,
b0010 -
#292000000
0!
0$
0(
#293000000
1!
1$
b0010 '
1(
b0010 ,
b0011 -
#294000000
0!
0$
0(
#295000000
1!
1$
b0011 '
1(
b0011 ,
b0100 -
#296000000
0!
0$
0(
#297000000
1!
1$
b0100 '
1(
b0100 ,
b0101 -
#298000000
0!
0$
0(
#299000000
1!
1$
b0101 '
1(
b0101 ,
b0110 -
#300000000
0!
b0011 "
0$
b0011 %
0(
#301000000
1!
1$
b0110 '
1(
b0110 ,
b0111 -
#302000000
0!
0$
0(
#303000000
1!
1$
b0111 '
1(
b0111 ,
b1000 -
#304000000
0!
0$
0(
#305000000
1!
1$
b1000 '
1(
b1000 ,
b1001 -
#306000000
0!
0$
0(
#307000000
1!
1$
b1001 '
1(
b1001 ,
b1010 -
#308000000
0!
0$
0(
#309000000
1!
1$
b1010 '
1(
b1010 ,
b1011 -
#310000000
0!
0$
0(
#311000000
1!
1$
b1011 '
1(
b1011 ,
b1100 -
#312000000
0!
0$
0(
#313000000
1!
1$
b1100 '
1(
b1100 ,
b1101 -
#314000000
0!
0$
0(
#315000000
1!
1$
b1101 '
1(
b1101 ,
b1110 -
#316000000
0!
0$
0(
#317000000
1!
1$
b1110 '
1(
b1110 ,
b1111 -
#318000000
0!
0$
0(
#319000000
1!
1$
b1111 '
1(
b1111 ,
b0000 -
#320000000
0!
0$
0(
#321000000
1!
1$
b0000 '
1(
b0000 ,
b0001 -
#322000000
0!
0$
0(
#323000000
1!
1#
1$
1&
b0001 '
1(
b0001 ,
b0010 -
#324000000
0!
0$
0(
#325000000
1!
1$
b0010 '
1(
b0010 ,
b0011 -
#326000000
0!
0$
0(
#327000000
1!
1$
b0011 '
1(
b0011 ,
b0100 -
#328000000
0!
0$
0(
#329000000
1!
0#
1$
0&
b0100 '
1(
b0100 ,
b0101 -
#330000000
0!
0$
0(
#331000000
1!
1$
b0101 '
1(
b0101 ,
b0110 -
#332000000
0!
0$
0(
#333000000
1!
1$
b0110 '
1(
b0110 ,
b0111 -
#334000000
0!
0$
0(
#335000000
1!
1$
b0111 '
1(
b0111 ,
b1000 -
#336000000
0!
0$
0(
#337000000
1!
1$
b1000 '
1(
b1000 ,
b1001 -
#338000000
0!
0$
0(
#339000000
1!
1$
b1001 '
1(
b1001 ,
b1010 -
#340000000
0!
0$
0(
#341000000
1!
1$
b1010 '
1(
b1010 ,
b1011 -
#342000000
0!
0$
0(
#343000000
1!
1$
b1011 '
1(
b1011 ,
b1100 -
#344000000
0!
0$
0(
#345000000
1!
1$
b1100 '
1(
b1100 ,
b1101 -
#346000000
0!
0$
0(
#347000000
1!
1$
b1101 '
1(
b1101 ,
b1110 -
#348000000
0!
0$
0(
#349000000
1!
1$
b1110 '
1(
b1110 ,
b1111 -
#350000000
0!
0$
0(
#351000000
1!
1$
b1111 '
1(
b1111 ,
b0000 -
#352000000
0!
0$
0(
#353000000
1!
1$
b0000 '
1(
b0000 ,
b0001 -
#354000000
0!
0$
0(
#355000000
1!
1#
1$
1&
b0001 '
1(
b0001 ,
b0010 -
#356000000
0!
0$
0(
#357000000
1!
1$
b0010 '
1(
b0010 ,
b0011 -
#358000000
0!
0$
0(
#359000000
1!
1$
b0011 '
1(
b0011 ,
b0100 -
#360000000
0!
0$
0(
#361000000
1!
0#
1$
0&
b0100 '
1(
b0100 ,
b0101 -
#362000000
0!
0$
0(
#363000000
1!
1$
b0101 '
1(
b0101 ,
b0110 -
#364000000
0!
0$
0(
#365000000
1!
1$
b0110 '
1(
b0110 ,
b0111 -
#366000000
0!
0$
0(
#367000000
1!
1$
b0111 '
1(
b0111 ,
b1000 -
#368000000
0!
0$
0(
#369000000
1!
1$
b1000 '
1(
b1000 ,
b1001 -
#370000000
0!
0$
0(
#371000000
1!
1$
b1001 '
1(
b1001 ,
b1010 -
#372000000
0!
0$
0(
#373000000
1!
1$
b1010 '
1(
b1010 ,
b1011 -
#374000000
0!
0$
0(
#375000000
1!
1$
b1011 '
1(
b1011 ,
b1100 -
#376000000
0!
0$
0(
#377000000
1!
1$
b1100 '
1(
b1100 ,
b1101 -
#378000000
0!
0$
0(
#379000000
1!
1$
b1101 '
1(
b1101 ,
b1110 -
#380000000
0!
0$
0(
#381000000
1!
1$
b1110 '
1(
b1110 ,
b1111 -
#382000000
0!
0$
0(
#383000000
1!
1$
b1111 '
1(
b1111 ,
b0000 -
#384000000
0!
0$
0(
#385000000
1!
1$
b0000 '
1(
b0000 ,
b0001 -
#386000000
0!
0$
0(
#387000000
1!
1#
1$
1&
b0001 '
1(
b0001 ,
b0010 -
#388000000
0!
0$
0(
#389000000
1!
1$
b0010 '
1(
b0010 ,
b0011 -
#390000000
0!
0$
0(
#391000000
1!
1$
b0011 '
1(
b0011 ,
b0100 -
#392000000
0!
0$
0(
#393000000
1!
0#
1$
0&
b0100 '
1(
b0100 ,
b0101 -
#394000000
0!
0$
0(
#395000000
1!
1$
b0101 '
1(
b0101 ,
b0110 -
#396000000
0!
0$
0(
#397000000
1!
1$
b0110 '
1(
b0110 ,
b0111 -
#398000000
0!
0$
0(
#399000000
1!
1$
b0111 '
1(
b0111 ,
b1000 -
#400000000
0!
0$
0(
#401000000
1!
1$
b1000 '
1(
b1000 ,
b1001 -
#402000000
0!
0$
0(
#403000000
1!
1$
b1001 '
1(
b1001 ,
b1010 -
#404000000
0!
0$
0(
#405000000
1!
1$
b1010 '
1(
b1010 ,
b1011 -
#406000000
0!
0$
0(
#407000000
1!
1$
b1011 '
1(
b1011 ,
b1100 -
#408000000
0!
0$
0(
#409000000
1!
1$
b1100 '
1(
b1100 ,
b1101 -
#410000000
0!
0$
0(
#411000000
1!
1$
b1101 '
1(
b1101 ,
b1110 -
#412000000
0!
0$
0(
#413000000
1!
1$
b1110 '
1(
b1110 ,
b1111 -
#414000000
0!
0$
0(
#415000000
1!
1$
b1111 '
1(
b1111 ,
b0000 -
#416000000
0!
0$
0(
#417000000
1!
1$
b0000 '
1(
b0000 ,
b0001 -
#418000000
0!
0$
0(
#419000000
1!
1#
1$
1&
b0001 '
1(
b0001 ,
b0010 -
#420000000
0!
0$
0(
#421000000
1!
1$
b0010 '
1(
b0010 ,
b0011 -
#422000000
0!
0$
0(
#423000000
1!
1$
b0011 '
1(
b0011 ,
b0100 -
#424000000
0!
0$
0(
#425000000
1!
0#
1$
0&
b0100 '
1(
b0100 ,
b0101 -
#426000000
0!
0$
0(
#427000000
1!
1$
b0101 '
1(
b0101 ,
b0110 -
#428000000
0!
0$
0(
#429000000
1!
1$
b0110 '
1(
b0110 ,
b0111 -
#430000000
0!
0$
0(
#431000000
1!
1$
b0111 '
1(
b0111 ,
b1000 -
#432000000
0!
0$
0(
#433000000
1!
1$
b1000 '
1(
b1000 ,
b1001 -
#434000000
0!
0$
0(
#435000000
1!
1$
b1001 '
1(
b1001 ,
b1010 -
#436000000
0!
0$
0(
#437000000
1!
1$
b1010 '
1(
b1010 ,
b1011 -
#438000000
0!
0$
0(
#439000000
1!
1$
b1011 '
1(
b1011 ,
b1100 -
#440000000
0!
0$
0(
#441000000
1!
1$
b1100 '
1(
b1100 ,
b1101 -
#442000000
0!
0$
0(
#443000000
1!
1$
b1101 '
1(
b1101 ,
b1110 -
#444000000
0!
0$
0(
#445000000
1!
1$
b1110 '
1(
b1110 ,
b1111 -
#446000000
0!
0$
0(
#447000000
1!
1$
b1111 '
1(
b1111 ,
b0000 -
#448000000
0!
0$
0(
#449000000
1!
1$
b0000 '
1(
b0000 ,
b0001 -
#450000000
0!
0$
0(
#451000000
1!
1#
1$
1&
b0001 '
1(
b0001 ,
b0010 -
#452000000
0!
0$
0(
#453000000
1!
1$
b0010 '
1(
b0010 ,
b0011 -
#454000000
0!
0$
0(
#455000000
1!
1$
b0011 '
1(
b0011 ,
b0100 -
#456000000
0!
0$
0(
#457000000
1!
0#
1$
0&
b0100 '
1(
b0100 ,
b0101 -
#458000000
0!
0$
0(
#459000000
1!
1$
b0101 '
1(
b0101 ,
b0110 -
#460000000
0!
0$
0(
#461000000
1!
1$
b0110 '
1(
b0110 ,
b0111 -
#462000000
0!
0$
0(
#463000000
1!
1$
b0111 '
1(
b0111 ,
b1000 -
#464000000
0!
0$
0(
#465000000
1!
1$
b1000 '
1(
b1000 ,
b1001 -
#466000000
0!
0$
0(
#467000000
1!
1$
b1001 '
1(
b1001 ,
b1010 -
#468000000
0!
0$
0(
#469000000
1!
1$
b1010 '
1(
b1010 ,
b1011 -
#470000000
0!
0$
0(
#471000000
1!
1$
b1011 '
1(
b1011 ,
b1100 -
#472000000
0!
0$
0(
#473000000
1!
1$
b1100 '
1(
b1100 ,
b1101 -
#474000000
0!
0$
0(
#475000000
1!
1$
b1101 '
1(
b1101 ,
b1110 -
#476000000
0!
0$
0(
#477000000
1!
1$
b1110 '
1(
b1110 ,
b1111 -
#478000000
0!
0$
0(
#479000000
1!
1$
b1111 '
1(
b1111 ,
b0000 -
#480000000
0!
0$
0(
#481000000
1!
1$
b0000 '
1(
b0000 ,
b0001 -
#482000000
0!
0$
0(
#483000000
1!
1#
1$
1&
b0001 '
1(
b0001 ,
b0010 -
#484000000
0!
0$
0(
#485000000
1!
1$
b0010 '
1(
b0010 ,
b0011 -
#486000000
0!
0$
0(
#487000000
1!
1$
b0011 '
1(
b0011 ,
b0100 -
#488000000
0!
0$
0(
#489000000
1!
0#
1$
0&
b0100 '
1(
b0100 ,
b0101 -
#490000000
0!
0$
0(
#491000000
1!
1$
b0101 '
1(
b0101 ,
b0110 -
#492000000
0!
0$
0(
#493000000
1!
1$
b0110 '
1(
b0110 ,
b0111 -
#494000000
0!
0$
0(
#495000000
1!
1$
b0111 '
1(
b0111 ,
b1000 -
#496000000
0!
0$
0(
#497000000
1!
1$
b1000 '
1(
b1000 ,
b1001 -
#498000000
0!
0$
0(
#499000000
1!
1$
b1001 '
1(
b1001 ,
b1010 -
#500000000
0!
0$
0(
#501000000
1!
1$
b1010 '
1(
b1010 ,
b1011 -
#502000000
0!
0$
0(
#503000000
1!
1$
b1011 '
1(
b1011 ,
b1100 -
#504000000
0!
0$
0(
#505000000
1!
1$
b1100 '
1(
b1100 ,
b1101 -
#506000000
0!
0$
0(
#507000000
1!
1$
b1101 '
1(
b1101 ,
b1110 -
#508000000
0!
0$
0(
#509000000
1!
1$
b1110 '
1(
b1110 ,
b1111 -
#510000000
0!
0$
0(
#511000000
1!
1$
b1111 '
1(
b1111 ,
b0000 -
#512000000
0!
0$
0(
#513000000
1!
1$
b0000 '
1(
b0000 ,
b0001 -
#514000000
0!
0$
0(
#515000000
1!
1#
1$
1&
b0001 '
1(
b0001 ,
b0010 -
#516000000
0!
0$
0(
#517000000
1!
1$
b0010 '
1(
b0010 ,
b0011 -
#518000000
0!
0$
0(
#519000000
1!
1$
b0011 '
1(
b0011 ,
b0100 -
#520000000
0!
0$
0(
#521000000
1!
0#
1$
0&
b0100 '
1(
b0100 ,
b0101 -
#522000000
0!
0$
0(
#523000000
1!
1$
b0101 '
1(
b0101 ,
b0110 -
#524000000
0!
0$
0(
